Workbook
Name Agency_List: [1]Control!$H$17:$H$19
Name BUControlSheet_CurrencySelections: [2]Control!$A$19:$A$20
Name BUControlSheet_FormulaSelections: [2]Control!$A$16:$A$17
Name BUControlSheet_RevisionSelections: [2]Control!$A$21:$A$22
Name BUControlSheet_ScaleSelections: [2]Control!$J$35:$J$36
Name Coordinator_List: [1]Control!$J$20:$J$21
Name Country: [3]Control!$C$1
Name ctylist: #REF!
Name ctylist: #REF!
Name ctylist: #REF!
Name ctylist: #REF!
Name ctylist: #REF!
Name ctylist: #REF!
Name ctylist: #REF!
Name Currency_Def: [1]Control!$BA$330:$BA$487
Name DelKreditor: #REF!,#REF!
Name DelKreditor: #REF!,#REF!
Name DelKreditor: #REF!,#REF!
Name DelKreditor: #REF!,#REF!
Name delstr: #REF!,#REF!,#REF!
Name delstr: #REF!,#REF!,#REF!
Name delstr: #REF!,#REF!,#REF!
Name delstr: #REF!,#REF!,#REF!
Name DELVD: #REF!,#REF!,#REF!,#REF!,#REF!,#REF!,#REF!,#REF!,#REF!,#REF!,#REF!,#REF!,#REF!,#REF!,#REF!,#REF!,#REF!
Name DELVD: #REF!,#REF!,#REF!,#REF!,#REF!,#REF!,#REF!,#REF!,#REF!,#REF!,#REF!,#REF!,#REF!,#REF!,#REF!,#REF!,#REF!
Name DELVD: #REF!,#REF!,#REF!,#REF!,#REF!,#REF!,#REF!,#REF!,#REF!,#REF!,#REF!,#REF!,#REF!,#REF!,#REF!,#REF!,#REF!
Name DELVD: #REF!,#REF!,#REF!,#REF!,#REF!,#REF!,#REF!,#REF!,#REF!,#REF!,#REF!,#REF!,#REF!,#REF!,#REF!,#REF!,#REF!
Name DelVd1: #REF!,#REF!,#REF!,#REF!,#REF!,#REF!,#REF!,#REF!,#REF!,#REF!,#REF!,#REF!
Name DelVd1: #REF!,#REF!,#REF!,#REF!,#REF!,#REF!,#REF!,#REF!,#REF!,#REF!,#REF!,#REF!
Name DelVd1: #REF!,#REF!,#REF!,#REF!,#REF!,#REF!,#REF!,#REF!,#REF!,#REF!,#REF!,#REF!
Name DelVd1: #REF!,#REF!,#REF!,#REF!,#REF!,#REF!,#REF!,#REF!,#REF!,#REF!,#REF!,#REF!
Name DelZaim: #REF!
Name DelZaim: #REF!
Name DelZaim: #REF!
Name DelZaim: #REF!
Name fullpilot: #REF!
Name fullpilot: #REF!
Name fullpilot: #REF!
Name fullpilot: #REF!
Name fullpilot: #REF!
Name fullpilot: #REF!
Name fullpilot: #REF!
Name IIPpilot: #REF!
Name IIPpilot: #REF!
Name IIPpilot: #REF!
Name IIPpilot: #REF!
Name IIPpilot: #REF!
Name IIPpilot: #REF!
Name IIPpilot: #REF!
Name pilot: #REF!
Name pilot: #REF!
Name pilot: #REF!
Name pilot: #REF!
Name pilot: #REF!
Name pilot: #REF!
Name pilot: #REF!
Name Range_DownloadAnnual: [2]Control!$C$4
Name Range_DownloadMonth: [2]Control!$C$2
Name Range_DownloadQuarter: [2]Control!$C$3
Name Range_DSTNotes: #REF!

Sheet Sheet2
A1: Date Initialisation | B1: Date needed | C1: External Debt interpolated
A2: 36892 | B2: =TEXT(A2,"yyyy-mm-01") -> 2001-01-01 | C2: =VLOOKUP(B2,'Final Cle'!$C$2:$D$103,2,FALSE) -> 12634.572
A3: =EDATE(A2,1) -> 36923 | B3: =TEXT(A3,"yyyy-mm-01") -> 2001-02-01 | C3: {=INDEX($C:$C,MATCH(ROW()-MOD(ROW()-ROW($C$2),3),ROW($C:$C),0))+(B3-INDEX($B:$B,MATCH(ROW()-MOD(ROW()-ROW($C$2),3),ROW($C:$C),0)))/(INDEX($B:$B,MATCH(ROW()-MOD(ROW()-ROW($C$2),3),ROW($C:$C),0)+3)-INDEX($B:$B,MATCH(ROW()-MOD(ROW()-ROW($C$2),3),ROW($C:$C),0)))*(INDEX($C:$C,MATCH(ROW()-MOD(ROW()-ROW($C$2),3),ROW($C:$C),0)+3)-INDEX($C:$C,MATCH(ROW()-MOD(ROW()-ROW($C$2),3),ROW($C:$C),0)))} -> 12754.627
A4: =EDATE(A3,1) -> 36951 | B4: =TEXT(A4,"yyyy-mm-01") -> 2001-03-01 | C4: {=INDEX($C:$C,MATCH(ROW()-MOD(ROW()-ROW($C$2),3),ROW($C:$C),0))+(B4-INDEX($B:$B,MATCH(ROW()-MOD(ROW()-ROW($C$2),3),ROW($C:$C),0)))/(INDEX($B:$B,MATCH(ROW()-MOD(ROW()-ROW($C$2),3),ROW($C:$C),0)+3)-INDEX($B:$B,MATCH(ROW()-MOD(ROW()-ROW($C$2),3),ROW($C:$C),0)))*(INDEX($C:$C,MATCH(ROW()-MOD(ROW()-ROW($C$2),3),ROW($C:$C),0)+3)-INDEX($C:$C,MATCH(ROW()-MOD(ROW()-ROW($C$2),3),ROW($C:$C),0)))} -> 12863.063
A5: =EDATE(A4,1) -> 36982 | B5: =TEXT(A5,"yyyy-mm-01") -> 2001-04-01 | C5: =VLOOKUP(B5,'Final Cle'!$C$2:$D$103,2,FALSE) -> 12983.117
A6: =EDATE(A5,1) -> 37012 | B6: =TEXT(A6,"yyyy-mm-01") -> 2001-05-01 | C6: {=INDEX($C:$C,MATCH(ROW()-MOD(ROW()-ROW($C$2),3),ROW($C:$C),0))+(B6-INDEX($B:$B,MATCH(ROW()-MOD(ROW()-ROW($C$2),3),ROW($C:$C),0)))/(INDEX($B:$B,MATCH(ROW()-MOD(ROW()-ROW($C$2),3),ROW($C:$C),0)+3)-INDEX($B:$B,MATCH(ROW()-MOD(ROW()-ROW($C$2),3),ROW($C:$C),0)))*(INDEX($C:$C,MATCH(ROW()-MOD(ROW()-ROW($C$2),3),ROW($C:$C),0)+3)-INDEX($C:$C,MATCH(ROW()-MOD(ROW()-ROW($C$2),3),ROW($C:$C),0)))} -> 13167.24
A7: =EDATE(A6,1) -> 37043 | B7: =TEXT(A7,"yyyy-mm-01") -> 2001-06-01 | C7: {=INDEX($C:$C,MATCH(ROW()-MOD(ROW()-ROW($C$2),3),ROW($C:$C),0))+(B7-INDEX($B:$B,MATCH(ROW()-MOD(ROW()-ROW($C$2),3),ROW($C:$C),0)))/(INDEX($B:$B,MATCH(ROW()-MOD(ROW()-ROW($C$2),3),ROW($C:$C),0)+3)-INDEX($B:$B,MATCH(ROW()-MOD(ROW()-ROW($C$2),3),ROW($C:$C),0)))*(INDEX($C:$C,MATCH(ROW()-MOD(ROW()-ROW($C$2),3),ROW($C:$C),0)+3)-INDEX($C:$C,MATCH(ROW()-MOD(ROW()-ROW($C$2),3),ROW($C:$C),0)))} -> 13357.502
A8: =EDATE(A7,1) -> 37073 | B8: =TEXT(A8,"yyyy-mm-01") -> 2001-07-01 | C8: =VLOOKUP(B8,'Final Cle'!$C$2:$D$103,2,FALSE) -> 13541.625
A9: =EDATE(A8,1) -> 37104 | B9: =TEXT(A9,"yyyy-mm-01") -> 2001-08-01 | C9: {=INDEX($C:$C,MATCH(ROW()-MOD(ROW()-ROW($C$2),3),ROW($C:$C),0))+(B9-INDEX($B:$B,MATCH(ROW()-MOD(ROW()-ROW($C$2),3),ROW($C:$C),0)))/(INDEX($B:$B,MATCH(ROW()-MOD(ROW()-ROW($C$2),3),ROW($C:$C),0)+3)-INDEX($B:$B,MATCH(ROW()-MOD(ROW()-ROW($C$2),3),ROW($C:$C),0)))*(INDEX($C:$C,MATCH(ROW()-MOD(ROW()-ROW($C$2),3),ROW($C:$C),0)+3)-INDEX($C:$C,MATCH(ROW()-MOD(ROW()-ROW($C$2),3),ROW($C:$C),0)))} -> 13810.262
A10: =EDATE(A9,1) -> 37135 | B10: =TEXT(A10,"yyyy-mm-01") -> 2001-09-01 | C10: {=INDEX($C:$C,MATCH(ROW()-MOD(ROW()-ROW($C$2),3),ROW($C:$C),0))+(B10-INDEX($B:$B,MATCH(ROW()-MOD(ROW()-ROW($C$2),3),ROW($C:$C),0)))/(INDEX($B:$B,MATCH(ROW()-MOD(ROW()-ROW($C$2),3),ROW($C:$C),0)+3)-INDEX($B:$B,MATCH(ROW()-MOD(ROW()-ROW($C$2),3),ROW($C:$C),0)))*(INDEX($C:$C,MATCH(ROW()-MOD(ROW()-ROW($C$2),3),ROW($C:$C),0)+3)-INDEX($C:$C,MATCH(ROW()-MOD(ROW()-ROW($C$2),3),ROW($C:$C),0)))} -> 14078.899
A11: =EDATE(A10,1) -> 37165 | B11: =TEXT(A11,"yyyy-mm-01") -> 2001-10-01 | C11: =VLOOKUP(B11,'Final Cle'!$C$2:$D$103,2,FALSE) -> 14338.871
A12: =EDATE(A11,1) -> 37196 | B12: =TEXT(A12,"yyyy-mm-01") -> 2001-11-01 | C12: {=INDEX($C:$C,MATCH(ROW()-MOD(ROW()-ROW($C$2),3),ROW($C:$C),0))+(B12-INDEX($B:$B,MATCH(ROW()-MOD(ROW()-ROW($C$2),3),ROW($C:$C),0)))/(INDEX($B:$B,MATCH(ROW()-MOD(ROW()-ROW($C$2),3),ROW($C:$C),0)+3)-INDEX($B:$B,MATCH(ROW()-MOD(ROW()-ROW($C$2),3),ROW($C:$C),0)))*(INDEX($C:$C,MATCH(ROW()-MOD(ROW()-ROW($C$2),3),ROW($C:$C),0)+3)-INDEX($C:$C,MATCH(ROW()-MOD(ROW()-ROW($C$2),3),ROW($C:$C),0)))} -> 14564.401
A13: =EDATE(A12,1) -> 37226 | B13: =TEXT(A13,"yyyy-mm-01") -> 2001-12-01 | C13: {=INDEX($C:$C,MATCH(ROW()-MOD(ROW()-ROW($C$2),3),ROW($C:$C),0))+(B13-INDEX($B:$B,MATCH(ROW()-MOD(ROW()-ROW($C$2),3),ROW($C:$C),0)))/(INDEX($B:$B,MATCH(ROW()-MOD(ROW()-ROW($C$2),3),ROW($C:$C),0)+3)-INDEX($B:$B,MATCH(ROW()-MOD(ROW()-ROW($C$2),3),ROW($C:$C),0)))*(INDEX($C:$C,MATCH(ROW()-MOD(ROW()-ROW($C$2),3),ROW($C:$C),0)+3)-INDEX($C:$C,MATCH(ROW()-MOD(ROW()-ROW($C$2),3),ROW($C:$C),0)))} -> 14782.656
A14: =EDATE(A13,1) -> 37257 | B14: =TEXT(A14,"yyyy-mm-01") -> 2002-01-01 | C14: =VLOOKUP(B14,'Final Cle'!$C$2:$D$103,2,FALSE) -> 15008.185
A15: =EDATE(A14,1) -> 37288 | B15: =TEXT(A15,"yyyy-mm-01") -> 2002-02-01 | C15: {=INDEX($C:$C,MATCH(ROW()-MOD(ROW()-ROW($C$2),3),ROW($C:$C),0))+(B15-INDEX($B:$B,MATCH(ROW()-MOD(ROW()-ROW($C$2),3),ROW($C:$C),0)))/(INDEX($B:$B,MATCH(ROW()-MOD(ROW()-ROW($C$2),3),ROW($C:$C),0)+3)-INDEX($B:$B,MATCH(ROW()-MOD(ROW()-ROW($C$2),3),ROW($C:$C),0)))*(INDEX($C:$C,MATCH(ROW()-MOD(ROW()-ROW($C$2),3),ROW($C:$C),0)+3)-INDEX($C:$C,MATCH(ROW()-MOD(ROW()-ROW($C$2),3),ROW($C:$C),0)))} -> 15131.944
A16: =EDATE(A15,1) -> 37316 | B16: =TEXT(A16,"yyyy-mm-01") -> 2002-03-01 | C16: {=INDEX($C:$C,MATCH(ROW()-MOD(ROW()-ROW($C$2),3),ROW($C:$C),0))+(B16-INDEX($B:$B,MATCH(ROW()-MOD(ROW()-ROW($C$2),3),ROW($C:$C),0)))/(INDEX($B:$B,MATCH(ROW()-MOD(ROW()-ROW($C$2),3),ROW($C:$C),0)+3)-INDEX($B:$B,MATCH(ROW()-MOD(ROW()-ROW($C$2),3),ROW($C:$C),0)))*(INDEX($C:$C,MATCH(ROW()-MOD(ROW()-ROW($C$2),3),ROW($C:$C),0)+3)-INDEX($C:$C,MATCH(ROW()-MOD(ROW()-ROW($C$2),3),ROW($C:$C),0)))} -> 15243.726
A17: =EDATE(A16,1) -> 37347 | B17: =TEXT(A17,"yyyy-mm-01") -> 2002-04-01 | C17: =VLOOKUP(B17,'Final Cle'!$C$2:$D$103,2,FALSE) -> 15367.485
A18: =EDATE(A17,1) -> 37377 | B18: =TEXT(A18,"yyyy-mm-01") -> 2002-05-01 | C18: {=INDEX($C:$C,MATCH(ROW()-MOD(ROW()-ROW($C$2),3),ROW($C:$C),0))+(B18-INDEX($B:$B,MATCH(ROW()-MOD(ROW()-ROW($C$2),3),ROW($C:$C),0)))/(INDEX($B:$B,MATCH(ROW()-MOD(ROW()-ROW($C$2),3),ROW($C:$C),0)+3)-INDEX($B:$B,MATCH(ROW()-MOD(ROW()-ROW($C$2),3),ROW($C:$C),0)))*(INDEX($C:$C,MATCH(ROW()-MOD(ROW()-ROW($C$2),3),ROW($C:$C),0)+3)-INDEX($C:$C,MATCH(ROW()-MOD(ROW()-ROW($C$2),3),ROW($C:$C),0)))} -> 15658.315
A19: =EDATE(A18,1) -> 37408 | B19: =TEXT(A19,"yyyy-mm-01") -> 2002-06-01 | C19: {=INDEX($C:$C,MATCH(ROW()-MOD(ROW()-ROW($C$2),3),ROW($C:$C),0))+(B19-INDEX($B:$B,MATCH(ROW()-MOD(ROW()-ROW($C$2),3),ROW($C:$C),0)))/(INDEX($B:$B,MATCH(ROW()-MOD(ROW()-ROW($C$2),3),ROW($C:$C),0)+3)-INDEX($B:$B,MATCH(ROW()-MOD(ROW()-ROW($C$2),3),ROW($C:$C),0)))*(INDEX($C:$C,MATCH(ROW()-MOD(ROW()-ROW($C$2),3),ROW($C:$C),0)+3)-INDEX($C:$C,MATCH(ROW()-MOD(ROW()-ROW($C$2),3),ROW($C:$C),0)))} -> 15958.839
A20: =EDATE(A19,1) -> 37438 | B20: =TEXT(A20,"yyyy-mm-01") -> 2002-07-01 | C20: =VLOOKUP(B20,'Final Cle'!$C$2:$D$103,2,FALSE) -> 16249.669
A21: =EDATE(A20,1) -> 37469 | B21: =TEXT(A21,"yyyy-mm-01") -> 2002-08-01 | C21: {=INDEX($C:$C,MATCH(ROW()-MOD(ROW()-ROW($C$2),3),ROW($C:$C),0))+(B21-INDEX($B:$B,MATCH(ROW()-MOD(ROW()-ROW($C$2),3),ROW($C:$C),0)))/(INDEX($B:$B,MATCH(ROW()-MOD(ROW()-ROW($C$2),3),ROW($C:$C),0)+3)-INDEX($B:$B,MATCH(ROW()-MOD(ROW()-ROW($C$2),3),ROW($C:$C),0)))*(INDEX($C:$C,MATCH(ROW()-MOD(ROW()-ROW($C$2),3),ROW($C:$C),0)+3)-INDEX($C:$C,MATCH(ROW()-MOD(ROW()-ROW($C$2),3),ROW($C:$C),0)))} -> 16548.372
A22: =EDATE(A21,1) -> 37500 | B22: =TEXT(A22,"yyyy-mm-01") -> 2002-09-01 | C22: {=INDEX($C:$C,MATCH(ROW()-MOD(ROW()-ROW($C$2),3),ROW($C:$C),0))+(B22-INDEX($B:$B,MATCH(ROW()-MOD(ROW()-ROW($C$2),3),ROW($C:$C),0)))/(INDEX($B:$B,MATCH(ROW()-MOD(ROW()-ROW($C$2),3),ROW($C:$C),0)+3)-INDEX($B:$B,MATCH(ROW()-MOD(ROW()-ROW($C$2),3),ROW($C:$C),0)))*(INDEX($C:$C,MATCH(ROW()-MOD(ROW()-ROW($C$2),3),ROW($C:$C),0)+3)-INDEX($C:$C,MATCH(ROW()-MOD(ROW()-ROW($C$2),3),ROW($C:$C),0)))} -> 16847.075
A23: =EDATE(A22,1) -> 37530 | B23: =TEXT(A23,"yyyy-mm-01") -> 2002-10-01 | C23: =VLOOKUP(B23,'Final Cle'!$C$2:$D$103,2,FALSE) -> 17136.142
A24: =EDATE(A23,1) -> 37561 | B24: =TEXT(A24,"yyyy-mm-01") -> 2002-11-01 | C24: {=INDEX($C:$C,MATCH(ROW()-MOD(ROW()-ROW($C$2),3),ROW($C:$C),0))+(B24-INDEX($B:$B,MATCH(ROW()-MOD(ROW()-ROW($C$2),3),ROW($C:$C),0)))/(INDEX($B:$B,MATCH(ROW()-MOD(ROW()-ROW($C$2),3),ROW($C:$C),0)+3)-INDEX($B:$B,MATCH(ROW()-MOD(ROW()-ROW($C$2),3),ROW($C:$C),0)))*(INDEX($C:$C,MATCH(ROW()-MOD(ROW()-ROW($C$2),3),ROW($C:$C),0)+3)-INDEX($C:$C,MATCH(ROW()-MOD(ROW()-ROW($C$2),3),ROW($C:$C),0)))} -> 17472.64
A25: =EDATE(A24,1) -> 37591 | B25: =TEXT(A25,"yyyy-mm-01") -> 2002-12-01 | C25: {=INDEX($C:$C,MATCH(ROW()-MOD(ROW()-ROW($C$2),3),ROW($C:$C),0))+(B25-INDEX($B:$B,MATCH(ROW()-MOD(ROW()-ROW($C$2),3),ROW($C:$C),0)))/(INDEX($B:$B,MATCH(ROW()-MOD(ROW()-ROW($C$2),3),ROW($C:$C),0)+3)-INDEX($B:$B,MATCH(ROW()-MOD(ROW()-ROW($C$2),3),ROW($C:$C),0)))*(INDEX($C:$C,MATCH(ROW()-MOD(ROW()-ROW($C$2),3),ROW($C:$C),0)+3)-INDEX($C:$C,MATCH(ROW()-MOD(ROW()-ROW($C$2),3),ROW($C:$C),0)))} -> 17798.283
A26: =EDATE(A25,1) -> 37622 | B26: =TEXT(A26,"yyyy-mm-01") -> 2003-01-01 | C26: =VLOOKUP(B26,'Final Cle'!$C$2:$D$103,2,FALSE) -> 18134.781
A27: =EDATE(A26,1) -> 37653 | B27: =TEXT(A27,"yyyy-mm-01") -> 2003-02-01 | C27: {=INDEX($C:$C,MATCH(ROW()-MOD(ROW()-ROW($C$2),3),ROW($C:$C),0))+(B27-INDEX($B:$B,MATCH(ROW()-MOD(ROW()-ROW($C$2),3),ROW($C:$C),0)))/(INDEX($B:$B,MATCH(ROW()-MOD(ROW()-ROW($C$2),3),ROW($C:$C),0)+3)-INDEX($B:$B,MATCH(ROW()-MOD(ROW()-ROW($C$2),3),ROW($C:$C),0)))*(INDEX($C:$C,MATCH(ROW()-MOD(ROW()-ROW($C$2),3),ROW($C:$C),0)+3)-INDEX($C:$C,MATCH(ROW()-MOD(ROW()-ROW($C$2),3),ROW($C:$C),0)))} -> 18341.031
A28: =EDATE(A27,1) -> 37681 | B28: =TEXT(A28,"yyyy-mm-01") -> 2003-03-01 | C28: {=INDEX($C:$C,MATCH(ROW()-MOD(ROW()-ROW($C$2),3),ROW($C:$C),0))+(B28-INDEX($B:$B,MATCH(ROW()-MOD(ROW()-ROW($C$2),3),ROW($C:$C),0)))/(INDEX($B:$B,MATCH(ROW()-MOD(ROW()-ROW($C$2),3),ROW($C:$C),0)+3)-INDEX($B:$B,MATCH(ROW()-MOD(ROW()-ROW($C$2),3),ROW($C:$C),0)))*(INDEX($C:$C,MATCH(ROW()-MOD(ROW()-ROW($C$2),3),ROW($C:$C),0)+3)-INDEX($C:$C,MATCH(ROW()-MOD(ROW()-ROW($C$2),3),ROW($C:$C),0)))} -> 18527.321
A29: =EDATE(A28,1) -> 37712 | B29: =TEXT(A29,"yyyy-mm-01") -> 2003-04-01 | C29: =VLOOKUP(B29,'Final Cle'!$C$2:$D$103,2,FALSE) -> 18733.571
A30: =EDATE(A29,1) -> 37742 | B30: =TEXT(A30,"yyyy-mm-01") -> 2003-05-01 | C30: {=INDEX($C:$C,MATCH(ROW()-MOD(ROW()-ROW($C$2),3),ROW($C:$C),0))+(B30-INDEX($B:$B,MATCH(ROW()-MOD(ROW()-ROW($C$2),3),ROW($C:$C),0)))/(INDEX($B:$B,MATCH(ROW()-MOD(ROW()-ROW($C$2),3),ROW($C:$C),0)+3)-INDEX($B:$B,MATCH(ROW()-MOD(ROW()-ROW($C$2),3),ROW($C:$C),0)))*(INDEX($C:$C,MATCH(ROW()-MOD(ROW()-ROW($C$2),3),ROW($C:$C),0)+3)-INDEX($C:$C,MATCH(ROW()-MOD(ROW()-ROW($C$2),3),ROW($C:$C),0)))} -> 19165.289
A31: =EDATE(A30,1) -> 37773 | B31: =TEXT(A31,"yyyy-mm-01") -> 2003-06-01 | C31: {=INDEX($C:$C,MATCH(ROW()-MOD(ROW()-ROW($C$2),3),ROW($C:$C),0))+(B31-INDEX($B:$B,MATCH(ROW()-MOD(ROW()-ROW($C$2),3),ROW($C:$C),0)))/(INDEX($B:$B,MATCH(ROW()-MOD(ROW()-ROW($C$2),3),ROW($C:$C),0)+3)-INDEX($B:$B,MATCH(ROW()-MOD(ROW()-ROW($C$2),3),ROW($C:$C),0)))*(INDEX($C:$C,MATCH(ROW()-MOD(ROW()-ROW($C$2),3),ROW($C:$C),0)+3)-INDEX($C:$C,MATCH(ROW()-MOD(ROW()-ROW($C$2),3),ROW($C:$C),0)))} -> 19611.398
A32: =EDATE(A31,1) -> 37803 | B32: =TEXT(A32,"yyyy-mm-01") -> 2003-07-01 | C32: =VLOOKUP(B32,'Final Cle'!$C$2:$D$103,2,FALSE) -> 20043.117
A33: =EDATE(A32,1) -> 37834 | B33: =TEXT(A33,"yyyy-mm-01") -> 2003-08-01 | C33: {=INDEX($C:$C,MATCH(ROW()-MOD(ROW()-ROW($C$2),3),ROW($C:$C),0))+(B33-INDEX($B:$B,MATCH(ROW()-MOD(ROW()-ROW($C$2),3),ROW($C:$C),0)))/(INDEX($B:$B,MATCH(ROW()-MOD(ROW()-ROW($C$2),3),ROW($C:$C),0)+3)-INDEX($B:$B,MATCH(ROW()-MOD(ROW()-ROW($C$2),3),ROW($C:$C),0)))*(INDEX($C:$C,MATCH(ROW()-MOD(ROW()-ROW($C$2),3),ROW($C:$C),0)+3)-INDEX($C:$C,MATCH(ROW()-MOD(ROW()-ROW($C$2),3),ROW($C:$C),0)))} -> 20574.292
A34: =EDATE(A33,1) -> 37865 | B34: =TEXT(A34,"yyyy-mm-01") -> 2003-09-01 | C34: {=INDEX($C:$C,MATCH(ROW()-MOD(ROW()-ROW($C$2),3),ROW($C:$C),0))+(B34-INDEX($B:$B,MATCH(ROW()-MOD(ROW()-ROW($C$2),3),ROW($C:$C),0)))/(INDEX($B:$B,MATCH(ROW()-MOD(ROW()-ROW($C$2),3),ROW($C:$C),0)+3)-INDEX($B:$B,MATCH(ROW()-MOD(ROW()-ROW($C$2),3),ROW($C:$C),0)))*(INDEX($C:$C,MATCH(ROW()-MOD(ROW()-ROW($C$2),3),ROW($C:$C),0)+3)-INDEX($C:$C,MATCH(ROW()-MOD(ROW()-ROW($C$2),3),ROW($C:$C),0)))} -> 21105.468
A35: =EDATE(A34,1) -> 37895 | B35: =TEXT(A35,"yyyy-mm-01") -> 2003-10-01 | C35: =VLOOKUP(B35,'Final Cle'!$C$2:$D$103,2,FALSE) -> 21619.509
A36: =EDATE(A35,1) -> 37926 | B36: =TEXT(A36,"yyyy-mm-01") -> 2003-11-01 | C36: {=INDEX($C:$C,MATCH(ROW()-MOD(ROW()-ROW($C$2),3),ROW($C:$C),0))+(B36-INDEX($B:$B,MATCH(ROW()-MOD(ROW()-ROW($C$2),3),ROW($C:$C),0)))/(INDEX($B:$B,MATCH(ROW()-MOD(ROW()-ROW($C$2),3),ROW($C:$C),0)+3)-INDEX($B:$B,MATCH(ROW()-MOD(ROW()-ROW($C$2),3),ROW($C:$C),0)))*(INDEX($C:$C,MATCH(ROW()-MOD(ROW()-ROW($C$2),3),ROW($C:$C),0)+3)-INDEX($C:$C,MATCH(ROW()-MOD(ROW()-ROW($C$2),3),ROW($C:$C),0)))} -> 22114.762
A37: =EDATE(A36,1) -> 37956 | B37: =TEXT(A37,"yyyy-mm-01") -> 2003-12-01 | C37: {=INDEX($C:$C,MATCH(ROW()-MOD(ROW()-ROW($C$2),3),ROW($C:$C),0))+(B37-INDEX($B:$B,MATCH(ROW()-MOD(ROW()-ROW($C$2),3),ROW($C:$C),0)))/(INDEX($B:$B,MATCH(ROW()-MOD(ROW()-ROW($C$2),3),ROW($C:$C),0)+3)-INDEX($B:$B,MATCH(ROW()-MOD(ROW()-ROW($C$2),3),ROW($C:$C),0)))*(INDEX($C:$C,MATCH(ROW()-MOD(ROW()-ROW($C$2),3),ROW($C:$C),0)+3)-INDEX($C:$C,MATCH(ROW()-MOD(ROW()-ROW($C$2),3),ROW($C:$C),0)))} -> 22594.04
A38: =EDATE(A37,1) -> 37987 | B38: =TEXT(A38,"yyyy-mm-01") -> 2004-01-01 | C38: =VLOOKUP(B38,'Final Cle'!$C$2:$D$103,2,FALSE) -> 23089.293
A39: =EDATE(A38,1) -> 38018 | B39: =TEXT(A39,"yyyy-mm-01") -> 2004-02-01 | C39: {=INDEX($C:$C,MATCH(ROW()-MOD(ROW()-ROW($C$2),3),ROW($C:$C),0))+(B39-INDEX($B:$B,MATCH(ROW()-MOD(ROW()-ROW($C$2),3),ROW($C:$C),0)))/(INDEX($B:$B,MATCH(ROW()-MOD(ROW()-ROW($C$2),3),ROW($C:$C),0)+3)-INDEX($B:$B,MATCH(ROW()-MOD(ROW()-ROW($C$2),3),ROW($C:$C),0)))*(INDEX($C:$C,MATCH(ROW()-MOD(ROW()-ROW($C$2),3),ROW($C:$C),0)+3)-INDEX($C:$C,MATCH(ROW()-MOD(ROW()-ROW($C$2),3),ROW($C:$C),0)))} -> 23488.112
A40: =EDATE(A39,1) -> 38047 | B40: =TEXT(A40,"yyyy-mm-01") -> 2004-03-01 | C40: {=INDEX($C:$C,MATCH(ROW()-MOD(ROW()-ROW($C$2),3),ROW($C:$C),0))+(B40-INDEX($B:$B,MATCH(ROW()-MOD(ROW()-ROW($C$2),3),ROW($C:$C),0)))/(INDEX($B:$B,MATCH(ROW()-MOD(ROW()-ROW($C$2),3),ROW($C:$C),0)+3)-INDEX($B:$B,MATCH(ROW()-MOD(ROW()-ROW($C$2),3),ROW($C:$C),0)))*(INDEX($C:$C,MATCH(ROW()-MOD(ROW()-ROW($C$2),3),ROW($C:$C),0)+3)-INDEX($C:$C,MATCH(ROW()-MOD(ROW()-ROW($C$2),3),ROW($C:$C),0)))} -> 23861.202
A41: =EDATE(A40,1) -> 38078 | B41: =TEXT(A41,"yyyy-mm-01") -> 2004-04-01 | C41: =VLOOKUP(B41,'Final Cle'!$C$2:$D$103,2,FALSE) -> 24260.021
A42: =EDATE(A41,1) -> 38108 | B42: =TEXT(A42,"yyyy-mm-01") -> 2004-05-01 | C42: {=INDEX($C:$C,MATCH(ROW()-MOD(ROW()-ROW($C$2),3),ROW($C:$C),0))+(B42-INDEX($B:$B,MATCH(ROW()-MOD(ROW()-ROW($C$2),3),ROW($C:$C),0)))/(INDEX($B:$B,MATCH(ROW()-MOD(ROW()-ROW($C$2),3),ROW($C:$C),0)+3)-INDEX($B:$B,MATCH(ROW()-MOD(ROW()-ROW($C$2),3),ROW($C:$C),0)))*(INDEX($C:$C,MATCH(ROW()-MOD(ROW()-ROW($C$2),3),ROW($C:$C),0)+3)-INDEX($C:$C,MATCH(ROW()-MOD(ROW()-ROW($C$2),3),ROW($C:$C),0)))} -> 24745.584
A43: =EDATE(A42,1) -> 38139 | B43: =TEXT(A43,"yyyy-mm-01") -> 2004-06-01 | C43: {=INDEX($C:$C,MATCH(ROW()-MOD(ROW()-ROW($C$2),3),ROW($C:$C),0))+(B43-INDEX($B:$B,MATCH(ROW()-MOD(ROW()-ROW($C$2),3),ROW($C:$C),0)))/(INDEX($B:$B,MATCH(ROW()-MOD(ROW()-ROW($C$2),3),ROW($C:$C),0)+3)-INDEX($B:$B,MATCH(ROW()-MOD(ROW()-ROW($C$2),3),ROW($C:$C),0)))*(INDEX($C:$C,MATCH(ROW()-MOD(ROW()-ROW($C$2),3),ROW($C:$C),0)+3)-INDEX($C:$C,MATCH(ROW()-MOD(ROW()-ROW($C$2),3),ROW($C:$C),0)))} -> 25247.333
A44: =EDATE(A43,1) -> 38169 | B44: =TEXT(A44,"yyyy-mm-01") -> 2004-07-01 | C44: =VLOOKUP(B44,'Final Cle'!$C$2:$D$103,2,FALSE) -> 25732.896
A45: =EDATE(A44,1) -> 38200 | B45: =TEXT(A45,"yyyy-mm-01") -> 2004-08-01 | C45: {=INDEX($C:$C,MATCH(ROW()-MOD(ROW()-ROW($C$2),3),ROW($C:$C),0))+(B45-INDEX($B:$B,MATCH(ROW()-MOD(ROW()-ROW($C$2),3),ROW($C:$C),0)))/(INDEX($B:$B,MATCH(ROW()-MOD(ROW()-ROW($C$2),3),ROW($C:$C),0)+3)-INDEX($B:$B,MATCH(ROW()-MOD(ROW()-ROW($C$2),3),ROW($C:$C),0)))*(INDEX($C:$C,MATCH(ROW()-MOD(ROW()-ROW($C$2),3),ROW($C:$C),0)+3)-INDEX($C:$C,MATCH(ROW()-MOD(ROW()-ROW($C$2),3),ROW($C:$C),0)))} -> 26210.591
A46: =EDATE(A45,1) -> 38231 | B46: =TEXT(A46,"yyyy-mm-01") -> 2004-09-01 | C46: {=INDEX($C:$C,MATCH(ROW()-MOD(ROW()-ROW($C$2),3),ROW($C:$C),0))+(B46-INDEX($B:$B,MATCH(ROW()-MOD(ROW()-ROW($C$2),3),ROW($C:$C),0)))/(INDEX($B:$B,MATCH(ROW()-MOD(ROW()-ROW($C$2),3),ROW($C:$C),0)+3)-INDEX($B:$B,MATCH(ROW()-MOD(ROW()-ROW($C$2),3),ROW($C:$C),0)))*(INDEX($C:$C,MATCH(ROW()-MOD(ROW()-ROW($C$2),3),ROW($C:$C),0)+3)-INDEX($C:$C,MATCH(ROW()-MOD(ROW()-ROW($C$2),3),ROW($C:$C),0)))} -> 26688.285
A47: =EDATE(A46,1) -> 38261 | B47: =TEXT(A47,"yyyy-mm-01") -> 2004-10-01 | C47: =VLOOKUP(B47,'Final Cle'!$C$2:$D$103,2,FALSE) -> 27150.57
A48: =EDATE(A47,1) -> 38292 | B48: =TEXT(A48,"yyyy-mm-01") -> 2004-11-01 | C48: {=INDEX($C:$C,MATCH(ROW()-MOD(ROW()-ROW($C$2),3),ROW($C:$C),0))+(B48-INDEX($B:$B,MATCH(ROW()-MOD(ROW()-ROW($C$2),3),ROW($C:$C),0)))/(INDEX($B:$B,MATCH(ROW()-MOD(ROW()-ROW($C$2),3),ROW($C:$C),0)+3)-INDEX($B:$B,MATCH(ROW()-MOD(ROW()-ROW($C$2),3),ROW($C:$C),0)))*(INDEX($C:$C,MATCH(ROW()-MOD(ROW()-ROW($C$2),3),ROW($C:$C),0)+3)-INDEX($C:$C,MATCH(ROW()-MOD(ROW()-ROW($C$2),3),ROW($C:$C),0)))} -> 29028.483
A49: =EDATE(A48,1) -> 38322 | B49: =TEXT(A49,"yyyy-mm-01") -> 2004-12-01 | C49: {=INDEX($C:$C,MATCH(ROW()-MOD(ROW()-ROW($C$2),3),ROW($C:$C),0))+(B49-INDEX($B:$B,MATCH(ROW()-MOD(ROW()-ROW($C$2),3),ROW($C:$C),0)))/(INDEX($B:$B,MATCH(ROW()-MOD(ROW()-ROW($C$2),3),ROW($C:$C),0)+3)-INDEX($B:$B,MATCH(ROW()-MOD(ROW()-ROW($C$2),3),ROW($C:$C),0)))*(INDEX($C:$C,MATCH(ROW()-MOD(ROW()-ROW($C$2),3),ROW($C:$C),0)+3)-INDEX($C:$C,MATCH(ROW()-MOD(ROW()-ROW($C$2),3),ROW($C:$C),0)))} -> 30845.818
A50: =EDATE(A49,1) -> 38353 | B50: =TEXT(A50,"yyyy-mm-01") -> 2005-01-01 | C50: =VLOOKUP(B50,'Final Cle'!$C$2:$D$103,2,FALSE) -> 32723.731
A51: =EDATE(A50,1) -> 38384 | B51: =TEXT(A51,"yyyy-mm-01") -> 2005-02-01 | C51: {=INDEX($C:$C,MATCH(ROW()-MOD(ROW()-ROW($C$2),3),ROW($C:$C),0))+(B51-INDEX($B:$B,MATCH(ROW()-MOD(ROW()-ROW($C$2),3),ROW($C:$C),0)))/(INDEX($B:$B,MATCH(ROW()-MOD(ROW()-ROW($C$2),3),ROW($C:$C),0)+3)-INDEX($B:$B,MATCH(ROW()-MOD(ROW()-ROW($C$2),3),ROW($C:$C),0)))*(INDEX($C:$C,MATCH(ROW()-MOD(ROW()-ROW($C$2),3),ROW($C:$C),0)+3)-INDEX($C:$C,MATCH(ROW()-MOD(ROW()-ROW($C$2),3),ROW($C:$C),0)))} -> 33251.548
A52: =EDATE(A51,1) -> 38412 | B52: =TEXT(A52,"yyyy-mm-01") -> 2005-03-01 | C52: {=INDEX($C:$C,MATCH(ROW()-MOD(ROW()-ROW($C$2),3),ROW($C:$C),0))+(B52-INDEX($B:$B,MATCH(ROW()-MOD(ROW()-ROW($C$2),3),ROW($C:$C),0)))/(INDEX($B:$B,MATCH(ROW()-MOD(ROW()-ROW($C$2),3),ROW($C:$C),0)+3)-INDEX($B:$B,MATCH(ROW()-MOD(ROW()-ROW($C$2),3),ROW($C:$C),0)))*(INDEX($C:$C,MATCH(ROW()-MOD(ROW()-ROW($C$2),3),ROW($C:$C),0)+3)-INDEX($C:$C,MATCH(ROW()-MOD(ROW()-ROW($C$2),3),ROW($C:$C),0)))} -> 33728.286
A53: =EDATE(A52,1) -> 38443 | B53: =TEXT(A53,"yyyy-mm-01") -> 2005-04-01 | C53: =VLOOKUP(B53,'Final Cle'!$C$2:$D$103,2,FALSE) -> 34256.104
A54: =EDATE(A53,1) -> 38473 | B54: =TEXT(A54,"yyyy-mm-01") -> 2005-05-01 | C54: {=INDEX($C:$C,MATCH(ROW()-MOD(ROW()-ROW($C$2),3),ROW($C:$C),0))+(B54-INDEX($B:$B,MATCH(ROW()-MOD(ROW()-ROW($C$2),3),ROW($C:$C),0)))/(INDEX($B:$B,MATCH(ROW()-MOD(ROW()-ROW($C$2),3),ROW($C:$C),0)+3)-INDEX($B:$B,MATCH(ROW()-MOD(ROW()-ROW($C$2),3),ROW($C:$C),0)))*(INDEX($C:$C,MATCH(ROW()-MOD(ROW()-ROW($C$2),3),ROW($C:$C),0)+3)-INDEX($C:$C,MATCH(ROW()-MOD(ROW()-ROW($C$2),3),ROW($C:$C),0)))} -> 34740.254
A55: =EDATE(A54,1) -> 38504 | B55: =TEXT(A55,"yyyy-mm-01") -> 2005-06-01 | C55: {=INDEX($C:$C,MATCH(ROW()-MOD(ROW()-ROW($C$2),3),ROW($C:$C),0))+(B55-INDEX($B:$B,MATCH(ROW()-MOD(ROW()-ROW($C$2),3),ROW($C:$C),0)))/(INDEX($B:$B,MATCH(ROW()-MOD(ROW()-ROW($C$2),3),ROW($C:$C),0)+3)-INDEX($B:$B,MATCH(ROW()-MOD(ROW()-ROW($C$2),3),ROW($C:$C),0)))*(INDEX($C:$C,MATCH(ROW()-MOD(ROW()-ROW($C$2),3),ROW($C:$C),0)+3)-INDEX($C:$C,MATCH(ROW()-MOD(ROW()-ROW($C$2),3),ROW($C:$C),0)))} -> 35240.542
A56: =EDATE(A55,1) -> 38534 | B56: =TEXT(A56,"yyyy-mm-01") -> 2005-07-01 | C56: =VLOOKUP(B56,'Final Cle'!$C$2:$D$103,2,FALSE) -> 35724.692
A57: =EDATE(A56,1) -> 38565 | B57: =TEXT(A57,"yyyy-mm-01") -> 2005-08-01 | C57: {=INDEX($C:$C,MATCH(ROW()-MOD(ROW()-ROW($C$2),3),ROW($C:$C),0))+(B57-INDEX($B:$B,MATCH(ROW()-MOD(ROW()-ROW($C$2),3),ROW($C:$C),0)))/(INDEX($B:$B,MATCH(ROW()-MOD(ROW()-ROW($C$2),3),ROW($C:$C),0)+3)-INDEX($B:$B,MATCH(ROW()-MOD(ROW()-ROW($C$2),3),ROW($C:$C),0)))*(INDEX($C:$C,MATCH(ROW()-MOD(ROW()-ROW($C$2),3),ROW($C:$C),0)+3)-INDEX($C:$C,MATCH(ROW()-MOD(ROW()-ROW($C$2),3),ROW($C:$C),0)))} -> 36584.915
A58: =EDATE(A57,1) -> 38596 | B58: =TEXT(A58,"yyyy-mm-01") -> 2005-09-01 | C58: {=INDEX($C:$C,MATCH(ROW()-MOD(ROW()-ROW($C$2),3),ROW($C:$C),0))+(B58-INDEX($B:$B,MATCH(ROW()-MOD(ROW()-ROW($C$2),3),ROW($C:$C),0)))/(INDEX($B:$B,MATCH(ROW()-MOD(ROW()-ROW($C$2),3),ROW($C:$C),0)+3)-INDEX($B:$B,MATCH(ROW()-MOD(ROW()-ROW($C$2),3),ROW($C:$C),0)))*(INDEX($C:$C,MATCH(ROW()-MOD(ROW()-ROW($C$2),3),ROW($C:$C),0)+3)-INDEX($C:$C,MATCH(ROW()-MOD(ROW()-ROW($C$2),3),ROW($C:$C),0)))} -> 37445.138
A59: =EDATE(A58,1) -> 38626 | B59: =TEXT(A59,"yyyy-mm-01") -> 2005-10-01 | C59: =VLOOKUP(B59,'Final Cle'!$C$2:$D$103,2,FALSE) -> 38277.611
A60: =EDATE(A59,1) -> 38657 | B60: =TEXT(A60,"yyyy-mm-01") -> 2005-11-01 | C60: {=INDEX($C:$C,MATCH(ROW()-MOD(ROW()-ROW($C$2),3),ROW($C:$C),0))+(B60-INDEX($B:$B,MATCH(ROW()-MOD(ROW()-ROW($C$2),3),ROW($C:$C),0)))/(INDEX($B:$B,MATCH(ROW()-MOD(ROW()-ROW($C$2),3),ROW($C:$C),0)+3)-INDEX($B:$B,MATCH(ROW()-MOD(ROW()-ROW($C$2),3),ROW($C:$C),0)))*(INDEX($C:$C,MATCH(ROW()-MOD(ROW()-ROW($C$2),3),ROW($C:$C),0)+3)-INDEX($C:$C,MATCH(ROW()-MOD(ROW()-ROW($C$2),3),ROW($C:$C),0)))} -> 40013.246
A61: =EDATE(A60,1) -> 38687 | B61: =TEXT(A61,"yyyy-mm-01") -> 2005-12-01 | C61: {=INDEX($C:$C,MATCH(ROW()-MOD(ROW()-ROW($C$2),3),ROW($C:$C),0))+(B61-INDEX($B:$B,MATCH(ROW()-MOD(ROW()-ROW($C$2),3),ROW($C:$C),0)))/(INDEX($B:$B,MATCH(ROW()-MOD(ROW()-ROW($C$2),3),ROW($C:$C),0)+3)-INDEX($B:$B,MATCH(ROW()-MOD(ROW()-ROW($C$2),3),ROW($C:$C),0)))*(INDEX($C:$C,MATCH(ROW()-MOD(ROW()-ROW($C$2),3),ROW($C:$C),0)+3)-INDEX($C:$C,MATCH(ROW()-MOD(ROW()-ROW($C$2),3),ROW($C:$C),0)))} -> 41692.893
A62: =EDATE(A61,1) -> 38718 | B62: =TEXT(A62,"yyyy-mm-01") -> 2006-01-01 | C62: =VLOOKUP(B62,'Final Cle'!$C$2:$D$103,2,FALSE) -> 43428.528
A63: =EDATE(A62,1) -> 38749 | B63: =TEXT(A63,"yyyy-mm-01") -> 2006-02-01 | C63: {=INDEX($C:$C,MATCH(ROW()-MOD(ROW()-ROW($C$2),3),ROW($C:$C),0))+(B63-INDEX($B:$B,MATCH(ROW()-MOD(ROW()-ROW($C$2),3),ROW($C:$C),0)))/(INDEX($B:$B,MATCH(ROW()-MOD(ROW()-ROW($C$2),3),ROW($C:$C),0)+3)-INDEX($B:$B,MATCH(ROW()-MOD(ROW()-ROW($C$2),3),ROW($C:$C),0)))*(INDEX($C:$C,MATCH(ROW()-MOD(ROW()-ROW($C$2),3),ROW($C:$C),0)+3)-INDEX($C:$C,MATCH(ROW()-MOD(ROW()-ROW($C$2),3),ROW($C:$C),0)))} -> 45130.409
A64: =EDATE(A63,1) -> 38777 | B64: =TEXT(A64,"yyyy-mm-01") -> 2006-03-01 | C64: {=INDEX($C:$C,MATCH(ROW()-MOD(ROW()-ROW($C$2),3),ROW($C:$C),0))+(B64-INDEX($B:$B,MATCH(ROW()-MOD(ROW()-ROW($C$2),3),ROW($C:$C),0)))/(INDEX($B:$B,MATCH(ROW()-MOD(ROW()-ROW($C$2),3),ROW($C:$C),0)+3)-INDEX($B:$B,MATCH(ROW()-MOD(ROW()-ROW($C$2),3),ROW($C:$C),0)))*(INDEX($C:$C,MATCH(ROW()-MOD(ROW()-ROW($C$2),3),ROW($C:$C),0)+3)-INDEX($C:$C,MATCH(ROW()-MOD(ROW()-ROW($C$2),3),ROW($C:$C),0)))} -> 46667.592
A65: =EDATE(A64,1) -> 38808 | B65: =TEXT(A65,"yyyy-mm-01") -> 2006-04-01 | C65: =VLOOKUP(B65,'Final Cle'!$C$2:$D$103,2,FALSE) -> 48369.473
A66: =EDATE(A65,1) -> 38838 | B66: =TEXT(A66,"yyyy-mm-01") -> 2006-05-01 | C66: {=INDEX($C:$C,MATCH(ROW()-MOD(ROW()-ROW($C$2),3),ROW($C:$C),0))+(B66-INDEX($B:$B,MATCH(ROW()-MOD(ROW()-ROW($C$2),3),ROW($C:$C),0)))/(INDEX($B:$B,MATCH(ROW()-MOD(ROW()-ROW($C$2),3),ROW($C:$C),0)+3)-INDEX($B:$B,MATCH(ROW()-MOD(ROW()-ROW($C$2),3),ROW($C:$C),0)))*(INDEX($C:$C,MATCH(ROW()-MOD(ROW()-ROW($C$2),3),ROW($C:$C),0)+3)-INDEX($C:$C,MATCH(ROW()-MOD(ROW()-ROW($C$2),3),ROW($C:$C),0)))} -> 50215.684
A67: =EDATE(A66,1) -> 38869 | B67: =TEXT(A67,"yyyy-mm-01") -> 2006-06-01 | C67: {=INDEX($C:$C,MATCH(ROW()-MOD(ROW()-ROW($C$2),3),ROW($C:$C),0))+(B67-INDEX($B:$B,MATCH(ROW()-MOD(ROW()-ROW($C$2),3),ROW($C:$C),0)))/(INDEX($B:$B,MATCH(ROW()-MOD(ROW()-ROW($C$2),3),ROW($C:$C),0)+3)-INDEX($B:$B,MATCH(ROW()-MOD(ROW()-ROW($C$2),3),ROW($C:$C),0)))*(INDEX($C:$C,MATCH(ROW()-MOD(ROW()-ROW($C$2),3),ROW($C:$C),0)+3)-INDEX($C:$C,MATCH(ROW()-MOD(ROW()-ROW($C$2),3),ROW($C:$C),0)))} -> 52123.435
A68: =EDATE(A67,1) -> 38899 | B68: =TEXT(A68,"yyyy-mm-01") -> 2006-07-01 | C68: =VLOOKUP(B68,'Final Cle'!$C$2:$D$103,2,FALSE) -> 53969.645
A69: =EDATE(A68,1) -> 38930 | B69: =TEXT(A69,"yyyy-mm-01") -> 2006-08-01 | C69: {=INDEX($C:$C,MATCH(ROW()-MOD(ROW()-ROW($C$2),3),ROW($C:$C),0))+(B69-INDEX($B:$B,MATCH(ROW()-MOD(ROW()-ROW($C$2),3),ROW($C:$C),0)))/(INDEX($B:$B,MATCH(ROW()-MOD(ROW()-ROW($C$2),3),ROW($C:$C),0)+3)-INDEX($B:$B,MATCH(ROW()-MOD(ROW()-ROW($C$2),3),ROW($C:$C),0)))*(INDEX($C:$C,MATCH(ROW()-MOD(ROW()-ROW($C$2),3),ROW($C:$C),0)+3)-INDEX($C:$C,MATCH(ROW()-MOD(ROW()-ROW($C$2),3),ROW($C:$C),0)))} -> 56051.01
A70: =EDATE(A69,1) -> 38961 | B70: =TEXT(A70,"yyyy-mm-01") -> 2006-09-01 | C70: {=INDEX($C:$C,MATCH(ROW()-MOD(ROW()-ROW($C$2),3),ROW($C:$C),0))+(B70-INDEX($B:$B,MATCH(ROW()-MOD(ROW()-ROW($C$2),3),ROW($C:$C),0)))/(INDEX($B:$B,MATCH(ROW()-MOD(ROW()-ROW($C$2),3),ROW($C:$C),0)+3)-INDEX($B:$B,MATCH(ROW()-MOD(ROW()-ROW($C$2),3),ROW($C:$C),0)))*(INDEX($C:$C,MATCH(ROW()-MOD(ROW()-ROW($C$2),3),ROW($C:$C),0)+3)-INDEX($C:$C,MATCH(ROW()-MOD(ROW()-ROW($C$2),3),ROW($C:$C),0)))} -> 58132.375
A71: =EDATE(A70,1) -> 38991 | B71: =TEXT(A71,"yyyy-mm-01") -> 2006-10-01 | C71: =VLOOKUP(B71,'Final Cle'!$C$2:$D$103,2,FALSE) -> 60146.599
A72: =EDATE(A71,1) -> 39022 | B72: =TEXT(A72,"yyyy-mm-01") -> 2006-11-01 | C72: {=INDEX($C:$C,MATCH(ROW()-MOD(ROW()-ROW($C$2),3),ROW($C:$C),0))+(B72-INDEX($B:$B,MATCH(ROW()-MOD(ROW()-ROW($C$2),3),ROW($C:$C),0)))/(INDEX($B:$B,MATCH(ROW()-MOD(ROW()-ROW($C$2),3),ROW($C:$C),0)+3)-INDEX($B:$B,MATCH(ROW()-MOD(ROW()-ROW($C$2),3),ROW($C:$C),0)))*(INDEX($C:$C,MATCH(ROW()-MOD(ROW()-ROW($C$2),3),ROW($C:$C),0)+3)-INDEX($C:$C,MATCH(ROW()-MOD(ROW()-ROW($C$2),3),ROW($C:$C),0)))} -> 64819.341
A73: =EDATE(A72,1) -> 39052 | B73: =TEXT(A73,"yyyy-mm-01") -> 2006-12-01 | C73: {=INDEX($C:$C,MATCH(ROW()-MOD(ROW()-ROW($C$2),3),ROW($C:$C),0))+(B73-INDEX($B:$B,MATCH(ROW()-MOD(ROW()-ROW($C$2),3),ROW($C:$C),0)))/(INDEX($B:$B,MATCH(ROW()-MOD(ROW()-ROW($C$2),3),ROW($C:$C),0)+3)-INDEX($B:$B,MATCH(ROW()-MOD(ROW()-ROW($C$2),3),ROW($C:$C),0)))*(INDEX($C:$C,MATCH(ROW()-MOD(ROW()-ROW($C$2),3),ROW($C:$C),0)+3)-INDEX($C:$C,MATCH(ROW()-MOD(ROW()-ROW($C$2),3),ROW($C:$C),0)))} -> 69341.348
A74: =EDATE(A73,1) -> 39083 | B74: =TEXT(A74,"yyyy-mm-01") -> 2007-01-01 | C74: =VLOOKUP(B74,'Final Cle'!$C$2:$D$103,2,FALSE) -> 74014.09
A75: =EDATE(A74,1) -> 39114 | B75: =TEXT(A75,"yyyy-mm-01") -> 2007-02-01 | C75: {=INDEX($C:$C,MATCH(ROW()-MOD(ROW()-ROW($C$2),3),ROW($C:$C),0))+(B75-INDEX($B:$B,MATCH(ROW()-MOD(ROW()-ROW($C$2),3),ROW($C:$C),0)))/(INDEX($B:$B,MATCH(ROW()-MOD(ROW()-ROW($C$2),3),ROW($C:$C),0)+3)-INDEX($B:$B,MATCH(ROW()-MOD(ROW()-ROW($C$2),3),ROW($C:$C),0)))*(INDEX($C:$C,MATCH(ROW()-MOD(ROW()-ROW($C$2),3),ROW($C:$C),0)+3)-INDEX($C:$C,MATCH(ROW()-MOD(ROW()-ROW($C$2),3),ROW($C:$C),0)))} -> 76732.385
A76: =EDATE(A75,1) -> 39142 | B76: =TEXT(A76,"yyyy-mm-01") -> 2007-03-01 | C76: {=INDEX($C:$C,MATCH(ROW()-MOD(ROW()-ROW($C$2),3),ROW($C:$C),0))+(B76-INDEX($B:$B,MATCH(ROW()-MOD(ROW()-ROW($C$2),3),ROW($C:$C),0)))/(INDEX($B:$B,MATCH(ROW()-MOD(ROW()-ROW($C$2),3),ROW($C:$C),0)+3)-INDEX($B:$B,MATCH(ROW()-MOD(ROW()-ROW($C$2),3),ROW($C:$C),0)))*(INDEX($C:$C,MATCH(ROW()-MOD(ROW()-ROW($C$2),3),ROW($C:$C),0)+3)-INDEX($C:$C,MATCH(ROW()-MOD(ROW()-ROW($C$2),3),ROW($C:$C),0)))} -> 79187.618
A77: =EDATE(A76,1) -> 39173 | B77: =TEXT(A77,"yyyy-mm-01") -> 2007-04-01 | C77: =VLOOKUP(B77,'Final Cle'!$C$2:$D$103,2,FALSE) -> 81905.913
A78: =EDATE(A77,1) -> 39203 | B78: =TEXT(A78,"yyyy-mm-01") -> 2007-05-01 | C78: {=INDEX($C:$C,MATCH(ROW()-MOD(ROW()-ROW($C$2),3),ROW($C:$C),0))+(B78-INDEX($B:$B,MATCH(ROW()-MOD(ROW()-ROW($C$2),3),ROW($C:$C),0)))/(INDEX($B:$B,MATCH(ROW()-MOD(ROW()-ROW($C$2),3),ROW($C:$C),0)+3)-INDEX($B:$B,MATCH(ROW()-MOD(ROW()-ROW($C$2),3),ROW($C:$C),0)))*(INDEX($C:$C,MATCH(ROW()-MOD(ROW()-ROW($C$2),3),ROW($C:$C),0)+3)-INDEX($C:$C,MATCH(ROW()-MOD(ROW()-ROW($C$2),3),ROW($C:$C),0)))} -> 85354.922
A79: =EDATE(A78,1) -> 39234 | B79: =TEXT(A79,"yyyy-mm-01") -> 2007-06-01 | C79: {=INDEX($C:$C,MATCH(ROW()-MOD(ROW()-ROW($C$2),3),ROW($C:$C),0))+(B79-INDEX($B:$B,MATCH(ROW()-MOD(ROW()-ROW($C$2),3),ROW($C:$C),0)))/(INDEX($B:$B,MATCH(ROW()-MOD(ROW()-ROW($C$2),3),ROW($C:$C),0)+3)-INDEX($B:$B,MATCH(ROW()-MOD(ROW()-ROW($C$2),3),ROW($C:$C),0)))*(INDEX($C:$C,MATCH(ROW()-MOD(ROW()-ROW($C$2),3),ROW($C:$C),0)+3)-INDEX($C:$C,MATCH(ROW()-MOD(ROW()-ROW($C$2),3),ROW($C:$C),0)))} -> 88918.899
A80: =EDATE(A79,1) -> 39264 | B80: =TEXT(A80,"yyyy-mm-01") -> 2007-07-01 | C80: =VLOOKUP(B80,'Final Cle'!$C$2:$D$103,2,FALSE) -> 92367.909
A81: =EDATE(A80,1) -> 39295 | B81: =TEXT(A81,"yyyy-mm-01") -> 2007-08-01 | C81: {=INDEX($C:$C,MATCH(ROW()-MOD(ROW()-ROW($C$2),3),ROW($C:$C),0))+(B81-INDEX($B:$B,MATCH(ROW()-MOD(ROW()-ROW($C$2),3),ROW($C:$C),0)))/(INDEX($B:$B,MATCH(ROW()-MOD(ROW()-ROW($C$2),3),ROW($C:$C),0)+3)-INDEX($B:$B,MATCH(ROW()-MOD(ROW()-ROW($C$2),3),ROW($C:$C),0)))*(INDEX($C:$C,MATCH(ROW()-MOD(ROW()-ROW($C$2),3),ROW($C:$C),0)+3)-INDEX($C:$C,MATCH(ROW()-MOD(ROW()-ROW($C$2),3),ROW($C:$C),0)))} -> 93001.533
A82: =EDATE(A81,1) -> 39326 | B82: =TEXT(A82,"yyyy-mm-01") -> 2007-09-01 | C82: {=INDEX($C:$C,MATCH(ROW()-MOD(ROW()-ROW($C$2),3),ROW($C:$C),0))+(B82-INDEX($B:$B,MATCH(ROW()-MOD(ROW()-ROW($C$2),3),ROW($C:$C),0)))/(INDEX($B:$B,MATCH(ROW()-MOD(ROW()-ROW($C$2),3),ROW($C:$C),0)+3)-INDEX($B:$B,MATCH(ROW()-MOD(ROW()-ROW($C$2),3),ROW($C:$C),0)))*(INDEX($C:$C,MATCH(ROW()-MOD(ROW()-ROW($C$2),3),ROW($C:$C),0)+3)-INDEX($C:$C,MATCH(ROW()-MOD(ROW()-ROW($C$2),3),ROW($C:$C),0)))} -> 93635.158
A83: =EDATE(A82,1) -> 39356 | B83: =TEXT(A83,"yyyy-mm-01") -> 2007-10-01 | C83: =VLOOKUP(B83,'Final Cle'!$C$2:$D$103,2,FALSE) -> 94248.343
A84: =EDATE(A83,1) -> 39387 | B84: =TEXT(A84,"yyyy-mm-01") -> 2007-11-01 | C84: {=INDEX($C:$C,MATCH(ROW()-MOD(ROW()-ROW($C$2),3),ROW($C:$C),0))+(B84-INDEX($B:$B,MATCH(ROW()-MOD(ROW()-ROW($C$2),3),ROW($C:$C),0)))/(INDEX($B:$B,MATCH(ROW()-MOD(ROW()-ROW($C$2),3),ROW($C:$C),0)+3)-INDEX($B:$B,MATCH(ROW()-MOD(ROW()-ROW($C$2),3),ROW($C:$C),0)))*(INDEX($C:$C,MATCH(ROW()-MOD(ROW()-ROW($C$2),3),ROW($C:$C),0)+3)-INDEX($C:$C,MATCH(ROW()-MOD(ROW()-ROW($C$2),3),ROW($C:$C),0)))} -> 95139.479
A85: =EDATE(A84,1) -> 39417 | B85: =TEXT(A85,"yyyy-mm-01") -> 2007-12-01 | C85: {=INDEX($C:$C,MATCH(ROW()-MOD(ROW()-ROW($C$2),3),ROW($C:$C),0))+(B85-INDEX($B:$B,MATCH(ROW()-MOD(ROW()-ROW($C$2),3),ROW($C:$C),0)))/(INDEX($B:$B,MATCH(ROW()-MOD(ROW()-ROW($C$2),3),ROW($C:$C),0)+3)-INDEX($B:$B,MATCH(ROW()-MOD(ROW()-ROW($C$2),3),ROW($C:$C),0)))*(INDEX($C:$C,MATCH(ROW()-MOD(ROW()-ROW($C$2),3),ROW($C:$C),0)+3)-INDEX($C:$C,MATCH(ROW()-MOD(ROW()-ROW($C$2),3),ROW($C:$C),0)))} -> 96001.868
A86: =EDATE(A85,1) -> 39448 | B86: =TEXT(A86,"yyyy-mm-01") -> 2008-01-01 | C86: =VLOOKUP(B86,'Final Cle'!$C$2:$D$103,2,FALSE) -> 96893.004
A87: =EDATE(A86,1) -> 39479 | B87: =TEXT(A87,"yyyy-mm-01") -> 2008-02-01 | C87: {=INDEX($C:$C,MATCH(ROW()-MOD(ROW()-ROW($C$2),3),ROW($C:$C),0))+(B87-INDEX($B:$B,MATCH(ROW()-MOD(ROW()-ROW($C$2),3),ROW($C:$C),0)))/(INDEX($B:$B,MATCH(ROW()-MOD(ROW()-ROW($C$2),3),ROW($C:$C),0)+3)-INDEX($B:$B,MATCH(ROW()-MOD(ROW()-ROW($C$2),3),ROW($C:$C),0)))*(INDEX($C:$C,MATCH(ROW()-MOD(ROW()-ROW($C$2),3),ROW($C:$C),0)+3)-INDEX($C:$C,MATCH(ROW()-MOD(ROW()-ROW($C$2),3),ROW($C:$C),0)))} -> 97568.983
A88: =EDATE(A87,1) -> 39508 | B88: =TEXT(A88,"yyyy-mm-01") -> 2008-03-01 | C88: {=INDEX($C:$C,MATCH(ROW()-MOD(ROW()-ROW($C$2),3),ROW($C:$C),0))+(B88-INDEX($B:$B,MATCH(ROW()-MOD(ROW()-ROW($C$2),3),ROW($C:$C),0)))/(INDEX($B:$B,MATCH(ROW()-MOD(ROW()-ROW($C$2),3),ROW($C:$C),0)+3)-INDEX($B:$B,MATCH(ROW()-MOD(ROW()-ROW($C$2),3),ROW($C:$C),0)))*(INDEX($C:$C,MATCH(ROW()-MOD(ROW()-ROW($C$2),3),ROW($C:$C),0)+3)-INDEX($C:$C,MATCH(ROW()-MOD(ROW()-ROW($C$2),3),ROW($C:$C),0)))} -> 98201.349
A89: =EDATE(A88,1) -> 39539 | B89: =TEXT(A89,"yyyy-mm-01") -> 2008-04-01 | C89: =VLOOKUP(B89,'Final Cle'!$C$2:$D$103,2,FALSE) -> 98877.328
A90: =EDATE(A89,1) -> 39569 | B90: =TEXT(A90,"yyyy-mm-01") -> 2008-05-01 | C90: {=INDEX($C:$C,MATCH(ROW()-MOD(ROW()-ROW($C$2),3),ROW($C:$C),0))+(B90-INDEX($B:$B,MATCH(ROW()-MOD(ROW()-ROW($C$2),3),ROW($C:$C),0)))/(INDEX($B:$B,MATCH(ROW()-MOD(ROW()-ROW($C$2),3),ROW($C:$C),0)+3)-INDEX($B:$B,MATCH(ROW()-MOD(ROW()-ROW($C$2),3),ROW($C:$C),0)))*(INDEX($C:$C,MATCH(ROW()-MOD(ROW()-ROW($C$2),3),ROW($C:$C),0)+3)-INDEX($C:$C,MATCH(ROW()-MOD(ROW()-ROW($C$2),3),ROW($C:$C),0)))} -> 99644.581
A91: =EDATE(A90,1) -> 39600 | B91: =TEXT(A91,"yyyy-mm-01") -> 2008-06-01 | C91: {=INDEX($C:$C,MATCH(ROW()-MOD(ROW()-ROW($C$2),3),ROW($C:$C),0))+(B91-INDEX($B:$B,MATCH(ROW()-MOD(ROW()-ROW($C$2),3),ROW($C:$C),0)))/(INDEX($B:$B,MATCH(ROW()-MOD(ROW()-ROW($C$2),3),ROW($C:$C),0)+3)-INDEX($B:$B,MATCH(ROW()-MOD(ROW()-ROW($C$2),3),ROW($C:$C),0)))*(INDEX($C:$C,MATCH(ROW()-MOD(ROW()-ROW($C$2),3),ROW($C:$C),0)+3)-INDEX($C:$C,MATCH(ROW()-MOD(ROW()-ROW($C$2),3),ROW($C:$C),0)))} -> 100437.41
A92: =EDATE(A91,1) -> 39630 | B92: =TEXT(A92,"yyyy-mm-01") -> 2008-07-01 | C92: =VLOOKUP(B92,'Final Cle'!$C$2:$D$103,2,FALSE) -> 101204.66
A93: =EDATE(A92,1) -> 39661 | B93: =TEXT(A93,"yyyy-mm-01") -> 2008-08-01 | C93: {=INDEX($C:$C,MATCH(ROW()-MOD(ROW()-ROW($C$2),3),ROW($C:$C),0))+(B93-INDEX($B:$B,MATCH(ROW()-MOD(ROW()-ROW($C$2),3),ROW($C:$C),0)))/(INDEX($B:$B,MATCH(ROW()-MOD(ROW()-ROW($C$2),3),ROW($C:$C),0)+3)-INDEX($B:$B,MATCH(ROW()-MOD(ROW()-ROW($C$2),3),ROW($C:$C),0)))*(INDEX($C:$C,MATCH(ROW()-MOD(ROW()-ROW($C$2),3),ROW($C:$C),0)+3)-INDEX($C:$C,MATCH(ROW()-MOD(ROW()-ROW($C$2),3),ROW($C:$C),0)))} -> 102818.91
A94: =EDATE(A93,1) -> 39692 | B94: =TEXT(A94,"yyyy-mm-01") -> 2008-09-01 | C94: {=INDEX($C:$C,MATCH(ROW()-MOD(ROW()-ROW($C$2),3),ROW($C:$C),0))+(B94-INDEX($B:$B,MATCH(ROW()-MOD(ROW()-ROW($C$2),3),ROW($C:$C),0)))/(INDEX($B:$B,MATCH(ROW()-MOD(ROW()-ROW($C$2),3),ROW($C:$C),0)+3)-INDEX($B:$B,MATCH(ROW()-MOD(ROW()-ROW($C$2),3),ROW($C:$C),0)))*(INDEX($C:$C,MATCH(ROW()-MOD(ROW()-ROW($C$2),3),ROW($C:$C),0)+3)-INDEX($C:$C,MATCH(ROW()-MOD(ROW()-ROW($C$2),3),ROW($C:$C),0)))} -> 104433.16
A95: =EDATE(A94,1) -> 39722 | B95: =TEXT(A95,"yyyy-mm-01") -> 2008-10-01 | C95: =VLOOKUP(B95,'Final Cle'!$C$2:$D$103,2,FALSE) -> 105995.33
A96: =EDATE(A95,1) -> 39753 | B96: =TEXT(A96,"yyyy-mm-01") -> 2008-11-01 | C96: {=INDEX($C:$C,MATCH(ROW()-MOD(ROW()-ROW($C$2),3),ROW($C:$C),0))+(B96-INDEX($B:$B,MATCH(ROW()-MOD(ROW()-ROW($C$2),3),ROW($C:$C),0)))/(INDEX($B:$B,MATCH(ROW()-MOD(ROW()-ROW($C$2),3),ROW($C:$C),0)+3)-INDEX($B:$B,MATCH(ROW()-MOD(ROW()-ROW($C$2),3),ROW($C:$C),0)))*(INDEX($C:$C,MATCH(ROW()-MOD(ROW()-ROW($C$2),3),ROW($C:$C),0)+3)-INDEX($C:$C,MATCH(ROW()-MOD(ROW()-ROW($C$2),3),ROW($C:$C),0)))} -> 106648.37
A97: =EDATE(A96,1) -> 39783 | B97: =TEXT(A97,"yyyy-mm-01") -> 2008-12-01 | C97: {=INDEX($C:$C,MATCH(ROW()-MOD(ROW()-ROW($C$2),3),ROW($C:$C),0))+(B97-INDEX($B:$B,MATCH(ROW()-MOD(ROW()-ROW($C$2),3),ROW($C:$C),0)))/(INDEX($B:$B,MATCH(ROW()-MOD(ROW()-ROW($C$2),3),ROW($C:$C),0)+3)-INDEX($B:$B,MATCH(ROW()-MOD(ROW()-ROW($C$2),3),ROW($C:$C),0)))*(INDEX($C:$C,MATCH(ROW()-MOD(ROW()-ROW($C$2),3),ROW($C:$C),0)+3)-INDEX($C:$C,MATCH(ROW()-MOD(ROW()-ROW($C$2),3),ROW($C:$C),0)))} -> 107280.34
A98: =EDATE(A97,1) -> 39814 | B98: =TEXT(A98,"yyyy-mm-01") -> 2009-01-01 | C98: =VLOOKUP(B98,'Final Cle'!$C$2:$D$103,2,FALSE) -> 107933.38
A99: =EDATE(A98,1) -> 39845 | B99: =TEXT(A99,"yyyy-mm-01") -> 2009-02-01 | C99: {=INDEX($C:$C,MATCH(ROW()-MOD(ROW()-ROW($C$2),3),ROW($C:$C),0))+(B99-INDEX($B:$B,MATCH(ROW()-MOD(ROW()-ROW($C$2),3),ROW($C:$C),0)))/(INDEX($B:$B,MATCH(ROW()-MOD(ROW()-ROW($C$2),3),ROW($C:$C),0)+3)-INDEX($B:$B,MATCH(ROW()-MOD(ROW()-ROW($C$2),3),ROW($C:$C),0)))*(INDEX($C:$C,MATCH(ROW()-MOD(ROW()-ROW($C$2),3),ROW($C:$C),0)+3)-INDEX($C:$C,MATCH(ROW()-MOD(ROW()-ROW($C$2),3),ROW($C:$C),0)))} -> 106855.37
A100: =EDATE(A99,1) -> 39873 | B100: =TEXT(A100,"yyyy-mm-01") -> 2009-03-01 | C100: {=INDEX($C:$C,MATCH(ROW()-MOD(ROW()-ROW($C$2),3),ROW($C:$C),0))+(B100-INDEX($B:$B,MATCH(ROW()-MOD(ROW()-ROW($C$2),3),ROW($C:$C),0)))/(INDEX($B:$B,MATCH(ROW()-MOD(ROW()-ROW($C$2),3),ROW($C:$C),0)+3)-INDEX($B:$B,MATCH(ROW()-MOD(ROW()-ROW($C$2),3),ROW($C:$C),0)))*(INDEX($C:$C,MATCH(ROW()-MOD(ROW()-ROW($C$2),3),ROW($C:$C),0)+3)-INDEX($C:$C,MATCH(ROW()-MOD(ROW()-ROW($C$2),3),ROW($C:$C),0)))} -> 105881.68
...

Sheet Final Cle
A1: Date | B1: ='1. standard presentation'!A4 -> External debt | C1: Date | D1: =B1 -> External debt
A2: 36892 | B2: {=TRANSPOSE('1. standard presentation'!C4:CZ4)} -> 12634.572 | C2: =TEXT(A2,"yyyy-mm-01") -> 2001-01-01 | D2: =B2 -> 12634.572
A3: 36982 | B3: 12983.117 | C3: =TEXT(A3,"yyyy-mm-01") -> 2001-04-01 | D3: =B3 -> 12983.117
A4: 37073 | B4: 13541.625 | C4: =TEXT(A4,"yyyy-mm-01") -> 2001-07-01 | D4: =B4 -> 13541.625
A5: 37165 | B5: 14338.871 | C5: =TEXT(A5,"yyyy-mm-01") -> 2001-10-01 | D5: =B5 -> 14338.871
A6: 37257 | B6: 15008.185 | C6: =TEXT(A6,"yyyy-mm-01") -> 2002-01-01 | D6: =B6 -> 15008.185
A7: 37347 | B7: 15367.485 | C7: =TEXT(A7,"yyyy-mm-01") -> 2002-04-01 | D7: =B7 -> 15367.485
A8: 37438 | B8: 16249.669 | C8: =TEXT(A8,"yyyy-mm-01") -> 2002-07-01 | D8: =B8 -> 16249.669
A9: 37530 | B9: 17136.142 | C9: =TEXT(A9,"yyyy-mm-01") -> 2002-10-01 | D9: =B9 -> 17136.142
A10: 37622 | B10: 18134.781 | C10: =TEXT(A10,"yyyy-mm-01") -> 2003-01-01 | D10: =B10 -> 18134.781
A11: 37712 | B11: 18733.571 | C11: =TEXT(A11,"yyyy-mm-01") -> 2003-04-01 | D11: =B11 -> 18733.571
A12: 37803 | B12: 20043.117 | C12: =TEXT(A12,"yyyy-mm-01") -> 2003-07-01 | D12: =B12 -> 20043.117
A13: 37895 | B13: 21619.509 | C13: =TEXT(A13,"yyyy-mm-01") -> 2003-10-01 | D13: =B13 -> 21619.509
A14: 37987 | B14: 23089.293 | C14: =TEXT(A14,"yyyy-mm-01") -> 2004-01-01 | D14: =B14 -> 23089.293
... A103: 46113 | B103: 182778.24 | C103: =TEXT(A103,"yyyy-mm-01") -> 2026-04-01 | D103: =B103 -> 182778.24

Sheet Final Cleaned
A1: date | B1: kz_extdebt_m
A2: ='Final Cle'!C2 -> 2001-01-01 | B2: ='Final Cle'!D2 -> 12634.572
A3: ='Final Cle'!C3 -> 2001-04-01 | B3: ='Final Cle'!D3 -> 12983.117
A4: ='Final Cle'!C4 -> 2001-07-01 | B4: ='Final Cle'!D4 -> 13541.625
A5: ='Final Cle'!C5 -> 2001-10-01 | B5: ='Final Cle'!D5 -> 14338.871
A6: ='Final Cle'!C6 -> 2002-01-01 | B6: ='Final Cle'!D6 -> 15008.185
A7: ='Final Cle'!C7 -> 2002-04-01 | B7: ='Final Cle'!D7 -> 15367.485
A8: ='Final Cle'!C8 -> 2002-07-01 | B8: ='Final Cle'!D8 -> 16249.669
A9: ='Final Cle'!C9 -> 2002-10-01 | B9: ='Final Cle'!D9 -> 17136.142
A10: ='Final Cle'!C10 -> 2003-01-01 | B10: ='Final Cle'!D10 -> 18134.781
A11: ='Final Cle'!C11 -> 2003-04-01 | B11: ='Final Cle'!D11 -> 18733.571
A12: ='Final Cle'!C12 -> 2003-07-01 | B12: ='Final Cle'!D12 -> 20043.117
A13: ='Final Cle'!C13 -> 2003-10-01 | B13: ='Final Cle'!D13 -> 21619.509
... A103: ='Final Cle'!C103 -> 2026-04-01 | B103: ='Final Cle'!D103 -> 182778.24

Sheet Metadata
A1: Name of the Statistical Indicator | B1: External Debt of Kazakhstan
A2: Responsible institution | B2: The National Bank of the Republic of Kazakhstan
A3: Unit of measurement | B3: Million US dollars
A4: Frequency | B4: Quarterly
A5: History of the Indicator | B5: Since 2001
A6: Definition of the Indicator | B6: External Debt indicators
A7: Data | B7: Aggregated statistical and administrative data
A8: Methodology for Calculation | B8: The methodological and conceptual framework for the compilation of external debt statistics is the joint document of international organizations "External Debt Statistics: a Guide for compilers and users", "Public Sector Debt Statistics in an expanded definition: a guide for compilers and users", as well as the sixth edition of the "Balance of Payments and International Investment Position Guide" of the International Monetary Fund (BPM6)
A9: Source of the Indicator | B9: Statistical and administrative reports of banks, professional participants of the securities market, other financial and non-financial organizations, including branches of foreign companies and government agencies, administrative reports of individuals, financial statements of individual organizations, accounting data of the National Bank of Kazakhstan and reports of the global custodian on the assets of the National Fund.
A10: Methodological Explanations | B10: https://nationalbank.kz/en/news/metodologicheskiy-kommentariy/7348
A11: Related Publications | B11: https://nationalbank.kz/en/news/platezhnyy-balans/rubrics/2358
A12: Useful Links | B12: https://nationalbank.kz/en/news/vneshniy-dolg https://data.nationalbank.kz/
A13: Date of Last Update | B13: 46213
A14: Date of Next Update | B14: 46295
A15: Responsible Structural Division | B15: Balance of Payments Department
A16: Responsible Officer | B16: Aigul Kassymova
A17: Telephone Number | B17: +7 (7172) 77 55 10
A18: E-mail | B18: kasimova@nationalbank.kz
A19: Terms of use | B19: Users without conclusion of the contract with the National Bank of the Republic of Kazakhstan have the right to use official statistical information Use of data, including its reuse, is permitted free of charge, in perpetuity, and without territorial restrictions. Users are granted the right to: - reproduce, copy, and distribute information, subject to mandatory citation of the source; - publish and integrate data with other information; - use data for software development and other applications.

Sheet Content
A2: External Debt of the Republic of Kazakhstan as of April 1st, 2026
A4: Content:
A5: Sheet 1. | B5: Standard presentation
A6: Sheet 2. | B6: Analytical presentation
A7: Sheet 3. | B7: Absolute and comparative indicators
A8: Sheet 4. | B8: Reconciliation of positions and flows of the external debt
A9: Sheet 5. | B9: Net external debt
A10: Sheet 6. | B10: Debt securities (issued by residents and belonging to non-residents) by the location of the issue

Sheet 1. standard presentation
A1: External debt: standard presentation
A2: mln.US dollars
B3: Row's code | C3: 01.01.2001 | D3: 01.04.2001 | E3: 01.07.2001 | F3: 01.10.2001 | G3: 01.01.2002 | H3: 01.04.2002 | I3: 01.07.2002 | J3: 01.10.2002 | K3: 01.01.2003 | L3: 01.04.2003 | M3: 01.07.2003 | N3: 01.10.2003 | O3: 01.01.2004 | P3: 01.04.2004 | Q3: 01.07.2004 | R3: 01.10.2004 | S3: 01.01.2005 | T3: 01.04.2005 | U3: 01.07.2005 | V3: 01.10.2005 | W3: 01.01.2006 | X3: 01.04.2006 | Y3: 01.07.2006 | Z3: 01.10.2006 | AA3: 01.01.2007 | AB3: 01.04.2007 | AC3: 01.07.2007 | AD3: 01.10.2007 | AE3: 01.01.2008 | AF3: 01.04.2008 | AG3: 01.07.2008 | AH3: 01.10.2008 | AI3: 01.01.2009 | AJ3: 01.04.2009 | AK3: 01.07.2009 | AL3: 01.10.2009 | AM3: 01.01.2010 | AN3: 01.04.2010 | AO3: 01.07.2010 | AP3: 01.10.2010 | AQ3: 01.01.2011 | AR3: 01.04.2011 | AS3: 01.07.2011 | AT3: 01.10.2011 | AU3: 01.01.2012 | AV3: 01.04.2012 | AW3: 01.07.2012 | AX3: 01.10.2012 | AY3: 01.01.2013 | AZ3: 01.04.2013 | BA3: 01.07.2013 | BB3: 01.10.2013 | BC3: 01.01.2014 | BD3: 01.04.2014 | BE3: 01.07.2014 | BF3: 01.10.2014 | BG3: 01.01.2015 | BH3: 01.04.2015 | BI3: 01.07.2015 | BJ3: 01.10.2015 | BK3: 01.01.2016 | BL3: 01.04.2016 | BM3: 01.07.2016 | BN3: 01.10.2016 | BO3: 01.01.2017 | BP3: 01.04.2017 | BQ3: 01.07.2017 | BR3: 01.10.2017 | BS3: 01.01.2018 | BT3: 01.04.2018 | BU3: 01.07.2018 | BV3: 01.10.2018 | BW3: 01.01.2019 | BX3: 01.04.2019 | BY3: 01.07.2019 | BZ3: 01.10.2019 | CA3: 01.01.2020 | CB3: 01.04.2020 | CC3: 01.07.2020 | CD3: 01.10.2020 | CE3: 01.01.2021 | CF3: 01.04.2021 | CG3: 01.07.2021 | CH3: 01.10.2021 | CI3: 01.01.2022 | CJ3: 01.04.2022 | CK3: 01.07.2022 | CL3: 01.10.2022 | CM3: 01.01.2023 | CN3: 01.04.2023 | CO3: 01.07.2023 | CP3: 01.10.2023 | CQ3: 01.01.2024 | CR3: 01.04.2024 | CS3: 01.07.2024 | CT3: 01.10.2024 | CU3: 01.01.2025 | CV3: 01.04.2025 | CW3: 01.07.2025 | CX3: 01.10.2025 | CY3: 01.01.2026 | CZ3: 01.04.2026
A4: External debt | B4: 1=2+3= 4+18+32+45+65 | C4: 12634.572 | D4: 12983.117 | E4: 13541.625 | F4: 14338.871 | G4: 15008.185 | H4: 15367.485 | I4: 16249.669 | J4: 17136.142 | K4: 18134.781 | L4: 18733.571 | M4: 20043.117 | N4: 21619.509 | O4: 23089.293 | P4: 24260.021 | Q4: 25732.896 | R4: 27150.57 | S4: 32723.731 | T4: 34256.104 | U4: 35724.692 | V4: 38277.611 | W4: 43428.528 | X4: 48369.473 | Y4: 53969.645 | Z4: 60146.599 | AA4: 74014.09 | AB4: 81905.913 | AC4: 92367.909 | AD4: 94248.343 | AE4: 96893.004 | AF4: 98877.328 | AG4: 101204.66 | AH4: 105995.33 | AI4: 107933.38 | AJ4: 104803.67 | AK4: 106675.74 | AL4: 111527.94 | AM4: 112866.89 | AN4: 110861.49 | AO4: 113619.66 | AP4: 111518.69 | AQ4: 118222.76 | AR4: 123359.16 | AS4: 124897.28 | AT4: 123708.36 | AU4: 125320.78 | AV4: 129154.05 | AW4: 132535.86 | AX4: 134414.12 | AY4: 136918.22 | AZ4: 139691.46 | BA4: 145554.8 | BB4: 148162.71 | BC4: 150032.87 | BD4: 151504.68 | BE4: 155583.92 | BF4: 155674.88 | BG4: 157114.53 | BH4: 154065.71 | BI4: 155281.01 | BJ4: 155284.28 | BK4: 153006.61 | BL4: 153335.14 | BM4: 159864.39 | BN4: 164849.21 | BO4: 163528.49 | BP4: 165292.7 | BQ4: 167774.33 | BR4: 168847.75 | BS4: 167482.72 | BT4: 167755.6 | BU4: 165679.6 | BV4: 162643.83 | BW4: 160331.29 | BX4: 160238.82 | BY4: 160393.97 | BZ4: 160328.62 | CA4: 159544.22 | CB4: 155466.74 | CC4: 160585.79 | CD4: 161706.54 | CE4: 163980.07 | CF4: 163955.09 | CG4: 166483.08 | CH4: 165761.72 | CI4: 164131.07 | CJ4: 159896.77 | CK4: 164152.25 | CL4: 161096.2 | CM4: 161144.27 | CN4: 162813.97 | CO4: 162802.62 | CP4: 163809.5 | CQ4: 163711.96 | CR4: 163952.93 | CS4: 166853.1 | CT4: 166367.06 | CU4: 164677.5 | CV4: 170037.8 | CW4: 172547.08 | CX4: 171558.26 | CY4: 181841.59 | CZ4: 182778.24
A5: Short-term | B5: 2=5+19+33+47 | C5: 960.83644 | D5: 911.25592 | E5: 1138.6412 | F5: 1175.2842 | G5: 1340.1748 | H5: 1286.2567 | I5: 1302.8472 | J5: 1574.6118 | K5: 2046.2267 | L5: 2010.2172 | M5: 2072.5811 | N5: 2377.8123 | O5: 3170.7262 | P5: 2987.7319 | Q5: 3183.6475 | R5: 3286.6231 | S5: 3864.49 | T5: 4200.7061 | U5: 4631.3713 | V5: 5606.5683 | W5: 8102.4299 | X5: 8501.9101 | Y5: 9323.9373 | Z5: 8500.6954 | AA5: 12445.218 | AB5: 11304.022 | AC5: 14887.811 | AD5: 10631.068 | AE5: 11529.681 | AF5: 11483.766 | AG5: 10399.217 | AH5: 10318.871 | AI5: 9486.7669 | AJ5: 7645.767 | AK5: 8165.2547 | AL5: 7713.4861 | AM5: 6985.1371 | AN5: 7559.4129 | AO5: 6952.0543 | AP5: 7087.0754 | AQ5: 8864.4948 | AR5: 11006.615 | AS5: 9619.8061 | AT5: 7689.5421 | AU5: 7867.2054 | AV5: 7533.4188 | AW5: 8079.0231 | AX5: 7922.3727 | AY5: 9086.3352 | AZ5: 8322.4151 | BA5: 8328.2724 | BB5: 9186.0426 | BC5: 9468.0696 | BD5: 9277.9631 | BE5: 9867.1725 | BF5: 9291.2238 | BG5: 9713.7711 | BH5: 8085.0413 | BI5: 7796.8116 | BJ5: 6429.2748 | BK5: 6260.3316 | BL5: 6238.1279 | BM5: 6326.146 | BN5: 6733.0899 | BO5: 6560.2863 | BP5: 7052.3174 | BQ5: 7193.6603 | BR5: 7407.5321 | BS5: 7489.1819 | BT5: 8306.197 | BU5: 8085.9598 | BV5: 8157.0621 | BW5: 8150.4561 | BX5: 8197.3064 | BY5: 8290.6416 | BZ5: 8225.3025 | CA5: 8801.1863 | CB5: 8347.7253 | CC5: 8894.1643 | CD5: 9151.283 | CE5: 9481.0146 | CF5: 10955.212 | CG5: 12243.771 | CH5: 11585.003 | CI5: 12009.62 | CJ5: 11720.057 | CK5: 14150.405 | CL5: 15527.76 | CM5: 16335.689 | CN5: 17256.953 | CO5: 17200.649 | CP5: 18225.459 | CQ5: 19389.554 | CR5: 19132.3 | CS5: 20633.718 | CT5: 21269.029 | CU5: 19468.737 | CV5: 21617.707 | CW5: 22418.968 | CX5: 20927.888 | CY5: 21688.322 | CZ5: 23576.213
A6: Long-term | B6: 3=11+25+39+53+65 | C6: 11673.736 | D6: 12071.861 | E6: 12402.984 | F6: 13163.587 | G6: 13668.011 | H6: 14081.229 | I6: 14946.821 | J6: 15561.53 | K6: 16088.554 | L6: 16723.354 | M6: 17970.536 | N6: 19241.697 | O6: 19918.566 | P6: 21272.289 | Q6: 22549.248 | R6: 23863.947 | S6: 28859.241 | T6: 30055.397 | U6: 31093.321 | V6: 32671.043 | W6: 35326.098 | X6: 39867.563 | Y6: 44645.708 | Z6: 51645.904 | AA6: 61568.872 | AB6: 70601.891 | AC6: 77480.097 | AD6: 83617.275 | AE6: 85363.323 | AF6: 87393.562 | AG6: 90805.446 | AH6: 95676.459 | AI6: 98446.611 | AJ6: 97157.906 | AK6: 98510.486 | AL6: 103814.45 | AM6: 105881.75 | AN6: 103302.08 | AO6: 106667.6 | AP6: 104431.62 | AQ6: 109358.27 | AR6: 112352.54 | AS6: 115277.47 | AT6: 116018.82 | AU6: 117453.57 | AV6: 121620.64 | AW6: 124456.84 | AX6: 126491.74 | AY6: 127831.88 | AZ6: 131369.05 | BA6: 137226.53 | BB6: 138976.67 | BC6: 140564.8 | BD6: 142226.72 | BE6: 145716.75 | BF6: 146383.66 | BG6: 147400.76 | BH6: 145980.66 | BI6: 147484.19 | BJ6: 148855 | BK6: 146746.28 | BL6: 147097.02 | BM6: 153538.25 | BN6: 158116.12 | BO6: 156968.21 | BP6: 158240.38 | BQ6: 160580.67 | BR6: 161440.22 | BS6: 159993.53 | BT6: 159449.4 | BU6: 157593.64 | BV6: 154486.76 | BW6: 152180.84 | BX6: 152041.51 | BY6: 152103.33 | BZ6: 152103.32 | CA6: 150743.03 | CB6: 147119.02 | CC6: 151691.63 | CD6: 152555.25 | CE6: 154499.06 | CF6: 152999.88 | CG6: 154239.31 | CH6: 154176.72 | CI6: 152121.45 | CJ6: 148176.72 | CK6: 150001.84 | CL6: 145568.44 | CM6: 144808.58 | CN6: 145557.02 | CO6: 145601.97 | CP6: 145584.04 | CQ6: 144322.41 | CR6: 144820.63 | CS6: 146219.38 | CT6: 145098.04 | CU6: 145208.76 | CV6: 148420.09 | CW6: 150128.12 | CX6: 150630.37 | CY6: 160153.27 | CZ6: 159202.03
A7: General Government | B7: 4=5+11 | C7: 2825.1976 | D7: 2744.974 | E7: 2712.002 | F7: 2727.47 | G7: 2694.025 | H7: 2490.5336 | I7: 2472.8143 | J7: 2439.4797 | K7: 2334.0095 | L7: 2400.7822 | M7: 2404.6542 | N7: 2459.0988 | O7: 2552.3441 | P7: 2704.8274 | Q7: 2702.0244 | R7: 2716.7994 | S7: 2496.1174 | T7: 2348.1019 | U7: 2062.4565 | V7: 2058.5873 | W7: 1478.9213 | X7: 1495.2886 | Y7: 1507.0701 | Z7: 1450.3088 | AA7: 1495.1813 | AB7: 1468.0315 | AC7: 1422.5411 | AD7: 1483.659 | AE7: 1491.5012 | AF7: 1559.5994 | AG7: 1541.9171 | AH7: 1603.6395 | AI7: 1641.9025 | AJ7: 1572.43 | AK7: 1584.5043 | AL7: 1639.3944 | AM7: 2218.0983 | AN7: 2264.2314 | AO7: 2352.0124 | AP7: 3492.2507 | AQ7: 3800.2919 | AR7: 3797.4067 | AS7: 3975.9498 | AT7: 4223.0944 | AU7: 4487.4154 | AV7: 4418.6391 | AW7: 4450.1104 | AX7: 4554.0234 | AY7: 4855.1224 | AZ7: 4756.4511 | BA7: 4827.6286 | BB7: 4978.8035 | BC7: 5217.5756 | BD7: 5066.2462 | BE7: 5045.1768 | BF7: 5116.6368 | BG7: 7333.7497 | BH7: 7105.9885 | BI7: 7005.6957 | BJ7: 10319.729 | BK7: 11313.193 | BL7: 11337.067 | BM7: 12696.818 | BN7: 12698.964 | BO7: 12092.075 | BP7: 12170.192 | BQ7: 12145.184 | BR7: 12313.301 | BS7: 12067.476 | BT7: 11137.89 | BU7: 10690.4 | BV7: 10651.472 | BW7: 11554.788 | BX7: 11488.784 | BY7: 11888.719 | BZ7: 12793.613 | CA7: 12417.6 | CB7: 11428.362 | CC7: 11834.52 | CD7: 12295.063 | CE7: 13885.041 | CF7: 14471.581 | CG7: 15682.086 | CH7: 15936.662 | CI7: 15859.324 | CJ7: 14153.244 | CK7: 14283.313 | CL7: 12939.095 | CM7: 13389.992 | CN7: 12857.149 | CO7: 12686.181 | CP7: 12610.291 | CQ7: 11809.413 | CR7: 11227.058 | CS7: 10883.271 | CT7: 11660.378 | CU7: 12773.497 | CV7: 12526.665 | CW7: 12475.636 | CX7: 14035.644 | CY7: 15999.525 | CZ7: 16541.489
A8: Short-term | B8: 5=6+7+8+9+10 | C8: 0.4876 | D8: 0 | E8: 0 | F8: 0 | G8: 0 | H8: 0 | I8: 0 | J8: 0 | K8: 0 | L8: 0 | M8: 0 | N8: 0 | O8: 0 | P8: 0 | Q8: 0 | R8: 0 | S8: 0 | T8: 0 | U8: 0 | V8: 0 | W8: 0 | X8: 0 | Y8: 0 | Z8: 0 | AA8: 0 | AB8: 0 | AC8: 0 | AD8: 0 | AE8: 0 | AF8: 0 | AG8: 18.778108 | AH8: 35.336123 | AI8: 9.0254202e-05 | AJ8: 0 | AK8: 0 | AL8: 0 | AM8: 0 | AN8: 0 | AO8: 0 | AP8: 0 | AQ8: 0 | AR8: 8.0159595 | AS8: 55.584976 | AT8: 99.675935 | AU8: 7.8760593 | AV8: 0.10207803 | AW8: 0.10164985 | AX8: 0.101 | AY8: 0.101 | AZ8: 0.101 | BA8: 0 | BB8: 0 | BC8: 0 | BD8: 0 | BE8: 0 | BF8: 0.905 | BG8: 1.23 | BH8: 25.615611 | BI8: 25.207576 | BJ8: 16.096868 | BK8: 21.651824 | BL8: 21.632227 | BM8: 15.877645 | BN8: 15.880973 | BO8: 13.61159 | BP8: 11.598057 | BQ8: 14.030109 | BR8: 16.915808 | BS8: 19.309576 | BT8: 17.587462 | BU8: 21.548471 | BV8: 23.058446 | BW8: 17.908613 | BX8: 17.773797 | BY8: 17.441582 | BZ8: 15.606123 | CA8: 14.929188 | CB8: 16.917969 | CC8: 18.888595 | CD8: 22.039426 | CE8: 24.613437 | CF8: 29.455581 | CG8: 32.246166 | CH8: 28.994734 | CI8: 24.301409 | CJ8: 30.411785 | CK8: 35.659143 | CL8: 35.089092 | CM8: 55.365297 | CN8: 59.579994 | CO8: 54.364503 | CP8: 114.65215 | CQ8: 115.77272 | CR8: 121.67959 | CS8: 120.49025 | CT8: 245.2924 | CU8: 183.63558 | CV8: 185.62672 | CW8: 157.56755 | CX8: 145.88062 | CY8: 118.60584 | CZ8: 127.4558
A9: Currency and deposits | B9: 6 | C9: 0 | D9: 0 | E9: 0 | F9: 0 | G9: 0 | H9: 0 | I9: 0 | J9: 0 | K9: 0 | L9: 0 | M9: 0 | N9: 0 | O9: 0 | P9: 0 | Q9: 0 | R9: 0 | S9: 0 | T9: 0 | U9: 0 | V9: 0 | W9: 0 | X9: 0 | Y9: 0 | Z9: 0 | AA9: 0 | AB9: 0 | AC9: 0 | AD9: 0 | AE9: 0 | AF9: 0 | AG9: 0 | AH9: 0 | AI9: 0 | AJ9: 0 | AK9: 0 | AL9: 0 | AM9: 0 | AN9: 0 | AO9: 0 | AP9: 0 | AQ9: 0 | AR9: 0 | AS9: 0 | AT9: 0 | AU9: 0 | AV9: 0 | AW9: 0 | AX9: 0 | AY9: 0 | AZ9: 0 | BA9: 0 | BB9: 0 | BC9: 0 | BD9: 0 | BE9: 0 | BF9: 0 | BG9: 0 | BH9: 0 | BI9: 0 | BJ9: 0 | BK9: 0 | BL9: 0 | BM9: 0 | BN9: 0 | BO9: 0 | BP9: 0 | BQ9: 0 | BR9: 0 | BS9: 0 | BT9: 0 | BU9: 0 | BV9: 0 | BW9: 0 | BX9: 0 | BY9: 0 | BZ9: 0 | CA9: 0 | CB9: 0 | CC9: 0 | CD9: 0 | CE9: 0 | CF9: 0 | CG9: 0 | CH9: 0 | CI9: 0 | CJ9: 0 | CK9: 0 | CL9: 0 | CM9: 0 | CN9: 0 | CO9: 0 | CP9: 0 | CQ9: 0 | CR9: 0 | CS9: 0 | CT9: 0 | CU9: 0 | CV9: 0 | CW9: 0 | CX9: 0 | CY9: 0 | CZ9: 0
A10: Debt securities1 | B10: 7 | C10: 0.4876 | D10: 0 | E10: 0 | F10: 0 | G10: 0 | H10: 0 | I10: 0 | J10: 0 | K10: 0 | L10: 0 | M10: 0 | N10: 0 | O10: 0 | P10: 0 | Q10: 0 | R10: 0 | S10: 0 | T10: 0 | U10: 0 | V10: 0 | W10: 0 | X10: 0 | Y10: 0 | Z10: 0 | AA10: 0 | AB10: 0 | AC10: 0 | AD10: 0 | AE10: 0 | AF10: 0 | AG10: 18.778108 | AH10: 35.336123 | AI10: 9.0254202e-05 | AJ10: 0 | AK10: 0 | AL10: 0 | AM10: 0 | AN10: 0 | AO10: 0 | AP10: 0 | AQ10: 0 | AR10: 7.9149595 | AS10: 55.483976 | AT10: 99.574935 | AU10: 7.7750593 | AV10: 0.0010780267 | AW10: 0.00064984607 | AX10: 0 | AY10: 0 | AZ10: 0 | BA10: 0 | BB10: 0 | BC10: 0 | BD10: 0 | BE10: 0 | BF10: 0 | BG10: 0 | BH10: 0 | BI10: 0 | BJ10: 0 | BK10: 0 | BL10: 0 | BM10: 0 | BN10: 0 | BO10: 0 | BP10: 0 | BQ10: 0 | BR10: 0 | BS10: 0 | BT10: 0 | BU10: 0 | BV10: 0 | BW10: 0 | BX10: 0 | BY10: 0 | BZ10: 0 | CA10: 0 | CB10: 0 | CC10: 0 | CD10: 0 | CE10: 0 | CF10: 0 | CG10: 0 | CH10: 0 | CI10: 0 | CJ10: 0 | CK10: 0 | CL10: 0 | CM10: 0 | CN10: 0 | CO10: 0 | CP10: 0 | CQ10: 0 | CR10: 0 | CS10: 0 | CT10: 0 | CU10: 0 | CV10: 0 | CW10: 0 | CX10: 0 | CY10: 0 | CZ10: 0
A11: Loans | B11: 8 | C11: 0 | D11: 0 | E11: 0 | F11: 0 | G11: 0 | H11: 0 | I11: 0 | J11: 0 | K11: 0 | L11: 0 | M11: 0 | N11: 0 | O11: 0 | P11: 0 | Q11: 0 | R11: 0 | S11: 0 | T11: 0 | U11: 0 | V11: 0 | W11: 0 | X11: 0 | Y11: 0 | Z11: 0 | AA11: 0 | AB11: 0 | AC11: 0 | AD11: 0 | AE11: 0 | AF11: 0 | AG11: 0 | AH11: 0 | AI11: 0 | AJ11: 0 | AK11: 0 | AL11: 0 | AM11: 0 | AN11: 0 | AO11: 0 | AP11: 0 | AQ11: 0 | AR11: 0 | AS11: 0 | AT11: 0 | AU11: 0 | AV11: 0 | AW11: 0 | AX11: 0 | AY11: 0 | AZ11: 0 | BA11: 0 | BB11: 0 | BC11: 0 | BD11: 0 | BE11: 0 | BF11: 0 | BG11: 0 | BH11: 0 | BI11: 0 | BJ11: 0 | BK11: 0 | BL11: 0 | BM11: 0 | BN11: 0 | BO11: 0 | BP11: 0 | BQ11: 0 | BR11: 0 | BS11: 0 | BT11: 0 | BU11: 0 | BV11: 0 | BW11: 0 | BX11: 0 | BY11: 0 | BZ11: 0 | CA11: 0 | CB11: 0 | CC11: 0 | CD11: 0 | CE11: 0 | CF11: 0 | CG11: 0 | CH11: 0 | CI11: 0 | CJ11: 0 | CK11: 0 | CL11: 0 | CM11: 0 | CN11: 0 | CO11: 0 | CP11: 0 | CQ11: 0 | CR11: 0 | CS11: 0 | CT11: 0 | CU11: 0 | CV11: 0 | CW11: 0 | CX11: 0 | CY11: 0 | CZ11: 0
A12: Trade credit and advances | B12: 9 | C12: 0 | D12: 0 | E12: 0 | F12: 0 | G12: 0 | H12: 0 | I12: 0 | J12: 0 | K12: 0 | L12: 0 | M12: 0 | N12: 0 | O12: 0 | P12: 0 | Q12: 0 | R12: 0 | S12: 0 | T12: 0 | U12: 0 | V12: 0 | W12: 0 | X12: 0 | Y12: 0 | Z12: 0 | AA12: 0 | AB12: 0 | AC12: 0 | AD12: 0 | AE12: 0 | AF12: 0 | AG12: 0 | AH12: 0 | AI12: 0 | AJ12: 0 | AK12: 0 | AL12: 0 | AM12: 0 | AN12: 0 | AO12: 0 | AP12: 0 | AQ12: 0 | AR12: 0.101 | AS12: 0.101 | AT12: 0.101 | AU12: 0.101 | AV12: 0.101 | AW12: 0.101 | AX12: 0.101 | AY12: 0.101 | AZ12: 0.101 | BA12: 0 | BB12: 0 | BC12: 0 | BD12: 0 | BE12: 0 | BF12: 0.905 | BG12: 1.23 | BH12: 25.615611 | BI12: 25.207576 | BJ12: 16.096868 | BK12: 21.651824 | BL12: 21.632227 | BM12: 15.877645 | BN12: 15.880973 | BO12: 13.61159 | BP12: 11.598057 | BQ12: 14.030109 | BR12: 16.915808 | BS12: 19.309576 | BT12: 17.587462 | BU12: 21.548471 | BV12: 23.058446 | BW12: 17.908613 | BX12: 17.773797 | BY12: 17.441582 | BZ12: 15.606123 | CA12: 14.929188 | CB12: 16.917969 | CC12: 18.888595 | CD12: 22.039426 | CE12: 24.613437 | CF12: 29.455581 | CG12: 32.246166 | CH12: 28.994734 | CI12: 24.301409 | CJ12: 30.287085 | CK12: 35.606903 | CL12: 34.896362 | CM12: 55.126057 | CN12: 59.434404 | CO12: 54.363893 | CP12: 49.501147 | CQ12: 50.621716 | CR12: 56.528585 | CS12: 55.339245 | CT12: 131.2894 | CU12: 69.772582 | CV12: 71.763715 | CW12: 43.704551 | CX12: 63.648616 | CY12: 39.030835 | CZ12: 47.8808
A13: Other debt liabilities | B13: 10 | C13: 0 | D13: 0 | E13: 0 | F13: 0 | G13: 0 | H13: 0 | I13: 0 | J13: 0 | K13: 0 | L13: 0 | M13: 0 | N13: 0 | O13: 0 | P13: 0 | Q13: 0 | R13: 0 | S13: 0 | T13: 0 | U13: 0 | V13: 0 | W13: 0 | X13: 0 | Y13: 0 | Z13: 0 | AA13: 0 | AB13: 0 | AC13: 0 | AD13: 0 | AE13: 0 | AF13: 0 | AG13: 0 | AH13: 0 | AI13: 0 | AJ13: 0 | AK13: 0 | AL13: 0 | AM13: 0 | AN13: 0 | AO13: 0 | AP13: 0 | AQ13: 0 | AR13: 0 | AS13: 0 | AT13: 0 | AU13: 0 | AV13: 0 | AW13: 0 | AX13: 0 | AY13: 0 | AZ13: 0 | BA13: 0 | BB13: 0 | BC13: 0 | BD13: 0 | BE13: 0 | BF13: 0 | BG13: 0 | BH13: 0 | BI13: 0 | BJ13: 0 | BK13: 0 | BL13: 0 | BM13: 0 | BN13: 0 | BO13: 0 | BP13: 0 | BQ13: 0 | BR13: 0 | BS13: 0 | BT13: 0 | BU13: 0 | BV13: 0 | BW13: 0 | BX13: 0 | BY13: 0 | BZ13: 0 | CA13: 0 | CB13: 0 | CC13: 0 | CD13: 0 | CE13: 0 | CF13: 0 | CG13: 0 | CH13: 0 | CI13: 0 | CJ13: 0.1247 | CK13: 0.05224 | CL13: 0.19273 | CM13: 0.23924 | CN13: 0.14559 | CO13: 0.00061 | CP13: 65.151 | CQ13: 65.151 | CR13: 65.151 | CS13: 65.151 | CT13: 114.003 | CU13: 113.863 | CV13: 113.863 | CW13: 113.863 | CX13: 82.232 | CY13: 79.575 | CZ13: 79.575
A14: Long-term | B14: 11=12+13+14+15+16+17 | C14: 2824.71 | D14: 2744.974 | E14: 2712.002 | F14: 2727.47 | G14: 2694.025 | H14: 2490.5336 | I14: 2472.8143 | J14: 2439.4797 | K14: 2334.0095 | L14: 2400.7822 | M14: 2404.6542 | N14: 2459.0988 | O14: 2552.3441 | P14: 2704.8274 | Q14: 2702.0244 | R14: 2716.7994 | S14: 2496.1174 | T14: 2348.1019 | U14: 2062.4565 | V14: 2058.5873 | W14: 1478.9213 | X14: 1495.2886 | Y14: 1507.0701 | Z14: 1450.3088 | AA14: 1495.1813 | AB14: 1468.0315 | AC14: 1422.5411 | AD14: 1483.659 | AE14: 1491.5012 | AF14: 1559.5994 | AG14: 1523.139 | AH14: 1568.3033 | AI14: 1641.9024 | AJ14: 1572.43 | AK14: 1584.5043 | AL14: 1639.3944 | AM14: 2218.0983 | AN14: 2264.2314 | AO14: 2352.0124 | AP14: 3492.2507 | AQ14: 3800.2919 | AR14: 3789.3908 | AS14: 3920.3648 | AT14: 4123.4184 | AU14: 4479.5393 | AV14: 4418.5371 | AW14: 4450.0088 | AX14: 4553.9224 | AY14: 4855.0214 | AZ14: 4756.3501 | BA14: 4827.6286 | BB14: 4978.8035 | BC14: 5217.5756 | BD14: 5066.2462 | BE14: 5045.1768 | BF14: 5115.7318 | BG14: 7332.5197 | BH14: 7080.3729 | BI14: 6980.4881 | BJ14: 10303.633 | BK14: 11291.541 | BL14: 11315.435 | BM14: 12680.941 | BN14: 12683.083 | BO14: 12078.463 | BP14: 12158.594 | BQ14: 12131.154 | BR14: 12296.385 | BS14: 12048.166 | BT14: 11120.303 | BU14: 10668.851 | BV14: 10628.414 | BW14: 11536.88 | BX14: 11471.01 | BY14: 11871.277 | BZ14: 12778.007 | CA14: 12402.671 | CB14: 11411.444 | CC14: 11815.631 | CD14: 12273.023 | CE14: 13860.428 | CF14: 14442.126 | CG14: 15649.84 | CH14: 15907.667 | CI14: 15835.023 | CJ14: 14122.832 | CK14: 14247.654 | CL14: 12904.006 | CM14: 13334.626 | CN14: 12797.569 | CO14: 12631.817 | CP14: 12495.639 | CQ14: 11693.64 | CR14: 11105.379 | CS14: 10762.781 | CT14: 11415.086 | CU14: 12589.862 | CV14: 12341.038 | CW14: 12318.068 | CX14: 13889.763 | CY14: 15880.919 | CZ14: 16414.033
A15: Special Drawing Rights | B15: 12 | C15: 0 | D15: 0 | E15: 0 | F15: 0 | G15: 0 | H15: 0 | I15: 0 | J15: 0 | K15: 0 | L15: 0 | M15: 0 | N15: 0 | O15: 0 | P15: 0 | Q15: 0 | R15: 0 | S15: 0 | T15: 0 | U15: 0 | V15: 0 | W15: 0 | X15: 0 | Y15: 0 | Z15: 0 | AA15: 0 | AB15: 0 | AC15: 0 | AD15: 0 | AE15: 0 | AF15: 0 | AG15: 0 | AH15: 0 | AI15: 0 | AJ15: 0 | AK15: 0 | AL15: 0 | AM15: 0 | AN15: 0 | AO15: 0 | AP15: 0 | AQ15: 0 | AR15: 0 | AS15: 0 | AT15: 0 | AU15: 0 | AV15: 0 | AW15: 0 | AX15: 0 | AY15: 0 | AZ15: 0 | BA15: 0 | BB15: 0 | BC15: 0 | BD15: 0 | BE15: 0 | BF15: 0 | BG15: 0 | BH15: 0 | BI15: 0 | BJ15: 0 | BK15: 0 | BL15: 0 | BM15: 0 | BN15: 0 | BO15: 0 | BP15: 0 | BQ15: 0 | BR15: 0 | BS15: 0 | BT15: 0 | BU15: 0 | BV15: 0 | BW15: 0 | BX15: 0 | BY15: 0 | BZ15: 0 | CA15: 0 | CB15: 0 | CC15: 0 | CD15: 0 | CE15: 0 | CF15: 0 | CG15: 0 | CH15: 0 | CI15: 0 | CJ15: 0 | CK15: 0 | CL15: 0 | CM15: 0 | CN15: 0 | CO15: 0 | CP15: 0 | CQ15: 0 | CR15: 0 | CS15: 0 | CT15: 0 | CU15: 0 | CV15: 0 | CW15: 0 | CX15: 0 | CY15: 0 | CZ15: 0
A16: Currency and deposits | B16: 13 | C16: 0 | D16: 0 | E16: 0 | F16: 0 | G16: 0 | H16: 0 | I16: 0 | J16: 0 | K16: 0 | L16: 0 | M16: 0 | N16: 0 | O16: 0 | P16: 0 | Q16: 0 | R16: 0 | S16: 0 | T16: 0 | U16: 0 | V16: 0 | W16: 0 | X16: 0 | Y16: 0 | Z16: 0 | AA16: 0 | AB16: 0 | AC16: 0 | AD16: 0 | AE16: 0 | AF16: 0 | AG16: 0 | AH16: 0 | AI16: 0 | AJ16: 0 | AK16: 0 | AL16: 0 | AM16: 0 | AN16: 0 | AO16: 0 | AP16: 0 | AQ16: 0 | AR16: 0 | AS16: 0 | AT16: 0 | AU16: 0 | AV16: 0 | AW16: 0 | AX16: 0 | AY16: 0 | AZ16: 0 | BA16: 0 | BB16: 0 | BC16: 0 | BD16: 0 | BE16: 0 | BF16: 0 | BG16: 0 | BH16: 0 | BI16: 0 | BJ16: 0 | BK16: 0 | BL16: 0 | BM16: 0 | BN16: 0 | BO16: 0 | BP16: 0 | BQ16: 0 | BR16: 0 | BS16: 0 | BT16: 0 | BU16: 0 | BV16: 0 | BW16: 0 | BX16: 0 | BY16: 0 | BZ16: 0 | CA16: 0 | CB16: 0 | CC16: 0 | CD16: 0 | CE16: 0 | CF16: 0 | CG16: 0 | CH16: 0 | CI16: 0 | CJ16: 0 | CK16: 0 | CL16: 0 | CM16: 0 | CN16: 0 | CO16: 0 | CP16: 0 | CQ16: 0 | CR16: 0 | CS16: 0 | CT16: 0 | CU16: 0 | CV16: 0 | CW16: 0 | CX16: 0 | CY16: 0 | CZ16: 0
A17: Debt securities1 | B17: 14 | C17: 547.74695 | D17: 512.43295 | E17: 483.29695 | F17: 459.16395 | G17: 445.01995 | H17: 254.7956 | I17: 217.52367 | J17: 180.25788 | K17: 39.959364 | L17: 79.414107 | M17: 82.632462 | N17: 70.697765 | O17: 129.09901 | P17: 298.18191 | Q17: 326.56373 | R17: 334.59686 | S17: 113.41741 | T17: 114.15187 | U17: 78.625291 | V17: 67.924 | W17: 52.296113 | X17: 49.458611 | Y17: 32.034055 | Z17: 36.643762 | AA17: 53.099314 | AB17: 116.83855 | AC17: 68.750061 | AD17: 93.575008 | AE17: 60.305237 | AF17: 54.272434 | AG17: 53.579967 | AH17: 65.681337 | AI17: 23.758383 | AJ17: 0.04002642 | AK17: 0.040276577 | AL17: 0.053381915 | AM17: 0.020275007 | AN17: 0.020447284 | AO17: 13.583399 | AP17: 41.198712 | AQ17: 49.128928 | AR17: 49.682772 | AS17: 120.97278 | AT17: 94.633416 | AU17: 23.84531 | AV17: 38.966055 | AW17: 21.20079 | AX17: 21.126852 | AY17: 14.082394 | AZ17: 14.073058 | BA17: 13.997626 | BB17: 13.818123 | BC17: 14.670562 | BD17: 0.67424742 | BE17: 0.66880994 | BF17: 0.7237915 | BG17: 1887.6487 | BH17: 1870.0769 | BI17: 1768.8731 | BJ17: 5007.8306 | BK17: 5038.0111 | BL17: 5074.1779 | BM17: 5367.7023 | BN17: 5330.8793 | BO17: 4713.741 | BP17: 4836.9393 | BQ17: 4862.3772 | BR17: 5062.5497 | BS17: 4799.689 | BT17: 3935.6645 | BU17: 3576.3571 | BV17: 3620.4005 | BW17: 4554.2838 | BX17: 4832.8628 | BY17: 5250.1014 | BZ17: 6466.8687 | CA17: 6133.3972 | CB17: 5479.4081 | CC17: 5941.8814 | CD17: 6728.7103 | CE17: 7202.6667 | CF17: 7108.6939 | CG17: 8361.3753 | CH17: 8739.0258 | CI17: 8748.7327 | CJ17: 7187.6953 | CK17: 7527.4053 | CL17: 6417.2894 | CM17: 6336.2198 | CN17: 5843.9892 | CO17: 5765.5349 | CP17: 5909.3294 | CQ17: 5135.1758 | CR17: 4852.5003 | CS17: 4618.3102 | CT17: 5371.279 | CU17: 5537.9237 | CV17: 5458.1685 | CW17: 5407.2427 | CX17: 7168.8222 | CY17: 9311.9151 | CZ17: 10078.12
A18: Loans | B18: 15 | C18: 2271.963 | D18: 2227.541 | E18: 2223.705 | F18: 2263.306 | G18: 2247.335 | H18: 2235.738 | I18: 2255.2906 | J18: 2259.2219 | K18: 2294.0501 | L18: 2321.3681 | M18: 2322.0217 | N18: 2388.401 | O18: 2423.2451 | P18: 2406.6455 | Q18: 2375.4607 | R18: 2382.2025 | S18: 2382.7 | T18: 2233.95 | U18: 1983.8312 | V18: 1990.6633 | W18: 1426.6252 | X18: 1445.83 | Y18: 1475.036 | Z18: 1413.665 | AA18: 1442.082 | AB18: 1351.193 | AC18: 1353.791 | AD18: 1390.084 | AE18: 1431.196 | AF18: 1505.327 | AG18: 1469.559 | AH18: 1502.622 | AI18: 1618.144 | AJ18: 1572.39 | AK18: 1584.464 | AL18: 1639.341 | AM18: 2218.078 | AN18: 2264.211 | AO18: 2338.429 | AP18: 3451.052 | AQ18: 3751.163 | AR18: 3739.708 | AS18: 3799.392 | AT18: 4028.785 | AU18: 4455.694 | AV18: 4379.571 | AW18: 4428.808 | AX18: 4532.7955 | AY18: 4840.939 | AZ18: 4642.204 | BA18: 4712.937 | BB18: 4863.6864 | BC18: 5101.001 | BD18: 4997.238 | BE18: 4968.992 | BF18: 5039.636 | BG18: 5369.667 | BH18: 5168.858 | BI18: 5169.326 | BJ18: 5256.45 | BK18: 6214.542 | BL18: 6238.422 | BM18: 7310.97 | BN18: 7350.505 | BO18: 7363.583 | BP18: 7321.655 | BQ18: 7268.777 | BR18: 7233.8352 | BS18: 7248.477 | BT18: 7184.638 | BU18: 7092.494 | BV18: 7008.013 | BW18: 6982.596 | BX18: 6638.147 | BY18: 6621.176 | BZ18: 6311.138 | CA18: 6269.274 | CB18: 5932.036 | CC18: 5873.75 | CD18: 5544.313 | CE18: 6657.761 | CF18: 7333.432 | CG18: 7288.465 | CH18: 7168.641 | CI18: 7086.2901 | CJ18: 6935.137 | CK18: 6720.249 | CL18: 6486.7168 | CM18: 6998.4066 | CN18: 6953.5798 | CO18: 6866.282 | CP18: 6586.3095 | CQ18: 6558.4647 | CR18: 6252.8784 | CS18: 6144.4705 | CT18: 6043.8068 | CU18: 7051.9381 | CV18: 6882.8699 | CW18: 6910.8256 | CX18: 6720.9407 | CY18: 6569.0038 | CZ18: 6335.9127
A19: Trade credit and advances | B19: 16 | C19: 0 | D19: 0 | E19: 0 | F19: 0 | G19: 0 | H19: 0 | I19: 0 | J19: 0 | K19: 0 | L19: 0 | M19: 0 | N19: 0 | O19: 0 | P19: 0 | Q19: 0 | R19: 0 | S19: 0 | T19: 0 | U19: 0 | V19: 0 | W19: 0 | X19: 0 | Y19: 0 | Z19: 0 | AA19: 0 | AB19: 0 | AC19: 0 | AD19: 0 | AE19: 0 | AF19: 0 | AG19: 0 | AH19: 0 | AI19: 0 | AJ19: 0 | AK19: 0 | AL19: 0 | AM19: 0 | AN19: 0 | AO19: 0 | AP19: 0 | AQ19: 0 | AR19: 0 | AS19: 0 | AT19: 0 | AU19: 0 | AV19: 0 | AW19: 0 | AX19: 0 | AY19: 0 | AZ19: 0 | BA19: 0 | BB19: 0 | BC19: 0 | BD19: 0 | BE19: 0 | BF19: 0 | BG19: 0 | BH19: 1.361 | BI19: 2.49 | BJ19: 0 | BK19: 0 | BL19: 0 | BM19: 0 | BN19: 0 | BO19: 0 | BP19: 0 | BQ19: 0 | BR19: 0 | BS19: 0 | BT19: 0 | BU19: 0 | BV19: 0 | BW19: 0 | BX19: 0 | BY19: 0 | BZ19: 0 | CA19: 0 | CB19: 0 | CC19: 0 | CD19: 0 | CE19: 0 | CF19: 0 | CG19: 0 | CH19: 0 | CI19: 0 | CJ19: 0 | CK19: 0 | CL19: 0 | CM19: 0 | CN19: 0 | CO19: 0 | CP19: 0 | CQ19: 0 | CR19: 0 | CS19: 0 | CT19: 0 | CU19: 0 | CV19: 0 | CW19: 0 | CX19: 0 | CY19: 0 | CZ19: 0
A20: Other debt liabilities | B20: 17 | C20: 5 | D20: 5 | E20: 5 | F20: 5 | G20: 1.67 | H20: 0 | I20: 0 | J20: 0 | K20: 0 | L20: 0 | M20: 0 | N20: 0 | O20: 0 | P20: 0 | Q20: 0 | R20: 0 | S20: 0 | T20: 0 | U20: 0 | V20: 0 | W20: 0 | X20: 0 | Y20: 0 | Z20: 0 | AA20: 0 | AB20: 0 | AC20: 0 | AD20: 0 | AE20: 0 | AF20: 0 | AG20: 0 | AH20: 0 | AI20: 0 | AJ20: 0 | AK20: 0 | AL20: 0 | AM20: 0 | AN20: 0 | AO20: 0 | AP20: 0 | AQ20: 0 | AR20: 0 | AS20: 0 | AT20: 0 | AU20: 0 | AV20: 0 | AW20: 0 | AX20: 0 | AY20: 0 | AZ20: 100.073 | BA20: 100.694 | BB20: 101.299 | BC20: 101.904 | BD20: 68.334 | BE20: 75.516 | BF20: 75.372 | BG20: 75.204 | BH20: 40.077 | BI20: 39.799 | BJ20: 39.352 | BK20: 38.98834 | BL20: 2.83534 | BM20: 2.26834 | BN20: 1.699 | BO20: 1.139 | BP20: 0 | BQ20: 0 | BR20: 0 | BS20: 0 | BT20: 0 | BU20: 0 | BV20: 0 | BW20: 0 | BX20: 0 | BY20: 0 | BZ20: 0 | CA20: 0 | CB20: 0 | CC20: 0 | CD20: 0 | CE20: 0 | CF20: 0 | CG20: 0 | CH20: 0 | CI20: 0 | CJ20: 0 | CK20: 0 | CL20: 0 | CM20: 0 | CN20: 0 | CO20: 0 | CP20: 0 | CQ20: 0 | CR20: 0 | CS20: 0 | CT20: 0 | CU20: 0 | CV20: 0 | CW20: 0 | CX20: 0 | CY20: 0 | CZ20: 0
A21: Central Bank | B21: 18=19+25 | C21: 1.9033932 | D21: 2.2474933 | E21: 2.1631109 | F21: 2.2500286 | G21: 2.2576278 | H21: 2.2348776 | I21: 2.2502304 | J21: 2.4100151 | K21: 2.4799209 | L21: 2.3697076 | M21: 2.5523562 | N21: 2.7067686 | O21: 2.3852402 | P21: 2.4832399 | Q21: 3.9371407 | R21: 3.5785977 | S21: 3.4659552 | T21: 14.893957 | U21: 86.050029 | V21: 132.3594 | W21: 103.54233 | X21: 244.2004 | Y21: 115.76938 | Z21: 193.55753 | AA21: 1076.8435 | AB21: 2081.2404 | AC21: 3144.1831 | AD21: 934.49078 | AE21: 106.89344 | AF21: 106.9963 | AG21: 32.379064 | AH21: 36.622303 | AI21: 12.127684 | AJ21: 2.4714349 | AK21: 175.72762 | AL21: 607.08723 | AM21: 1017.4874 | AN21: 1355.8633 | AO21: 1016.6219 | AP21: 693.58583 | AQ21: 1000.6498 | AR21: 3501.4632 | AS21: 2547.7319 | AT21: 684.29285 | AU21: 563.25744 | AV21: 657.80673 | AW21: 539.19785 | AX21: 549.96369 | AY21: 618.884 | AZ21: 537.84997 | BA21: 535.60042 | BB21: 557.76952 | BC21: 546.7 | BD21: 870.42072 | BE21: 805.71878 | BF21: 857.4888 | BG21: 953.65208 | BH21: 760.26513 | BI21: 779.21428 | BJ21: 875.29489 | BK21: 898.82369 | BL21: 892.03691 | BM21: 893.99357 | BN21: 739.38577 | BO21: 756.29982 | BP21: 1120.3822 | BQ21: 1097.8499 | BR21: 869.73808 | BS21: 926.31534 | BT21: 1899.1809 | BU21: 1188.5697 | BV21: 774.57793 | BW21: 770.39637 | BX21: 938.78931 | BY21: 759.41161 | BZ21: 634.03784 | CA21: 891.10116 | CB21: 949.8852 | CC21: 825.9092 | CD21: 805.59551 | CE21: 1329.3693 | CF21: 1835.9915 | CG21: 1714.6907 | CH21: 3051.342 | CI21: 2535.7666 | CJ21: 2519.3343 | CK21: 2214.3143 | CL21: 2043.6277 | CM21: 2171.8023 | CN21: 2217.8953 | CO21: 2065.0931 | CP21: 2097.6294 | CQ21: 2233.0697 | CR21: 2094.1758 | CS21: 2035.9904 | CT21: 2204.0123 | CU21: 2469.9652 | CV21: 2212.7413 | CW21: 2205.8534 | CX21: 2165.8445 | CY21: 2594.4324 | CZ21: 2381.7913
A22: Short-term | B22: 19=20+21+22+23+24 | C22: 0.00067820069 | D22: 0.34477827 | E22: 0.2603959 | F22: 0.34731359 | G22: 0.35491278 | H22: 0.33216264 | I22: 0.34751538 | J22: 0.50730013 | K22: 0.57720587 | L22: 0.46699263 | M22: 0.64964117 | N22: 0.80405357 | O22: 0.49800151 | P22: 0.58052494 | Q22: 2.0344257 | R22: 1.6758827 | S22: 1.5632402 | T22: 12.991242 | U22: 84.147314 | V22: 130.45669 | W22: 101.63961 | X22: 242.29769 | Y22: 113.86667 | Z22: 191.65481 | AA22: 1074.9408 | AB22: 2079.3377 | AC22: 3142.2804 | AD22: 932.58806 | AE22: 104.99072 | AF22: 105.09359 | AG22: 30.476349 | AH22: 34.719588 | AI22: 10.224969 | AJ22: 0.56871988 | AK22: 173.82491 | AL22: 63.969698 | AM22: 479.72176 | AN22: 832.21661 | AO22: 508.68771 | AP22: 159.14999 | AQ22: 470.43413 | AR22: 2957.5946 | AS22: 1997.8349 | AT22: 144.65787 | AU22: 36.329465 | AV22: 123.74641 | AW22: 15.326959 | AX22: 18.109901 | AY22: 88.063119 | AZ22: 20.453459 | BA22: 16.21121 | BB22: 28.447459 | BC22: 10.695178 | BD22: 333.09817 | BE22: 268.29026 | BF22: 115.90368 | BG22: 215.57358 | BH22: 12.532547 | BI22: 10.929881 | BJ22: 79.911277 | BK22: 75.954131 | BL22: 104.73457 | BM22: 169.3658 | BN22: 178.52901 | BO22: 242.53662 | BP22: 626.94322 | BQ22: 593.74221 | BR22: 368.29924 | BS22: 421.75315 | BT22: 1388.1652 | BU22: 694.51427 | BV22: 286.4923 | BW22: 286.24097 | BX22: 455.5703 | BY22: 275.48976 | BZ22: 159.09733 | CA22: 409.70703 | CB22: 472.75556 | CC22: 345.58138 | CD22: 315.71116 | CE22: 828.02566 | CF22: 1342.7691 | CG22: 1218.0262 | CH22: 989.87803 | CI22: 494.63373 | CJ22: 501.93911 | CK22: 270.38519 | CL22: 182.81149 | CM22: 230.88555 | CN22: 255.29493 | CO22: 119.74808 | CP22: 185.16305 | CQ22: 276.35476 | CR22: 164.0574 | CS22: 118.15329 | CT22: 227.87528 | CU22: 567.97818 | CV22: 279.38265 | CW22: 202.92557 | CX22: 168.50423 | CY22: 595.37327 | CZ22: 401.57727
A23: Currency and deposits | B23: 20 | C23: 0.00067820069 | D23: 0.34477827 | E23: 0.2603959 | F23: 0.2582803 | G23: 0.1732344 | H23: 0.040352246 | I23: 0.11829737 | J23: 0.11720569 | K23: 0.11634905 | L23: 0.11943731 | M23: 0.11943731 | N23: 0.11943731 | O23: 0.11943731 | P23: 0.10105687 | Q23: 0.17614348 | R23: 0.077985859 | S23: 0.31388906 | T23: 0.08149617 | U23: 0.83146959 | V23: 0 | W23: 1.0001249 | X23: 0.75513222 | Y23: 19.749069 | Z23: 0.30014091 | AA23: 0.77467723 | AB23: 0.24030479 | AC23: 0.048959815 | AD23: 0.0015720404 | AE23: 0.010947184 | AF23: 0.0092259439 | AG23: 0.022352953 | AH23: 0.022693149 | AI23: 0.27273972 | AJ23: 0.56871988 | AK23: 169.14639 | AL23: 63.969698 | AM23: 103.59101 | AN23: 91.01704 | AO23: 41.115525 | AP23: 73.73935 | AQ23: 239.54028 | AR23: 432.94524 | AS23: 140.21561 | AT23: 13.538227 | AU23: 16.484451 | AV23: 119.67325 | AW23: 11.899516 | AX23: 15.348304 | AY23: 88.051092 | AZ23: 16.790878 | BA23: 11.721053 | BB23: 24.389399 | BC23: 6.6751331 | BD23: 327.05747 | BE23: 258.96951 | BF23: 110.309 | BG23: 209.2746 | BH23: 6.1969299 | BI23: 3.980762 | BJ23: 73.504304 | BK23: 70.916354 | BL23: 99.662189 | BM23: 105.22314 | BN23: 50.195931 | BO23: 17.186079 | BP23: 16.837046 | BQ23: 18.406813 | BR23: 15.343369 | BS23: 10.575614 | BT23: 7.1823114 | BU23: 4.9193451 | BV23: 5.7710657 | BW23: 6.9245681 | BX23: 5.5473189 | BY23: 4.1301489 | BZ23: 4.660437 | CA23: 3.8512206 | CB23: 4.8349365 | CC23: 4.4461222 | CD23: 5.3882441 | CE23: 2.6300656 | CF23: 4.8996795 | CG23: 72.970479 | CH23: 4.2893759 | CI23: 7.8965182 | CJ23: 255.14151 | CK23: 11.266757 | CL23: 11.148138 | CM23: 12.802021 | CN23: 10.388588 | CO23: 13.577331 | CP23: 13.022969 | CQ23: 249.74479 | CR23: 13.372578 | CS23: 113.22014 | CT23: 98.15124 | CU23: 365.413 | CV23: 96.865134 | CW23: 191.52151 | CX23: 162.20343 | CY23: 294.142 | CZ23: 140.88421
A24: Debt securities1 | B24: 21 | C24: 0 | D24: 0 | E24: 0 | F24: 0.033649289 | G24: 0 | H24: 0 | I24: 0 | J24: 0 | K24: 0 | L24: 0 | M24: 0 | N24: 0 | O24: 0 | P24: 0 | Q24: 0 | R24: 0 | S24: 0 | T24: 10.181763 | U24: 82.273446 | V24: 127.15004 | W24: 99.77385 | X24: 240.4823 | Y24: 91.85036 | Z24: 190.16858 | AA24: 1072.9653 | AB24: 2077.9874 | AC24: 3141.7294 | AD24: 932.31864 | AE24: 104.77186 | AF24: 104.86823 | AG24: 30.260612 | AH24: 34.550747 | AI24: 9.9522293 | AJ24: 0 | AK24: 4.6785159 | AL24: 0 | AM24: 376.13075 | AN24: 741.19957 | AO24: 467.57218 | AP24: 85.41064 | AQ24: 230.89384 | AR24: 2524.6494 | AS24: 1857.6193 | AT24: 131.11965 | AU24: 19.845013 | AV24: 0 | AW24: 0 | AX24: 0 | AY24: 0 | AZ24: 0 | BA24: 1.3188262 | BB24: 0 | BC24: 0 | BD24: 0 | BE24: 0 | BF24: 0 | BG24: 0 | BH24: 0 | BI24: 0 | BJ24: 0 | BK24: 0 | BL24: 0 | BM24: 60.421529 | BN24: 120.83496 | BO24: 220.78125 | BP24: 605.96871 | BQ24: 572.70106 | BR24: 350.21461 | BS24: 408.12084 | BT24: 1376.9217 | BU24: 685.46183 | BV24: 276.30602 | BW24: 275.3117 | BX24: 445.75856 | BY24: 267.28404 | BZ24: 150.62053 | CA24: 401.60773 | CB24: 463.17143 | CC24: 335.57822 | CD24: 305.18777 | CE24: 821.18942 | CF24: 1333.183 | CG24: 1140.3331 | CH24: 980.7527 | CI24: 483.30177 | CJ24: 242.91583 | CK24: 254.41541 | CL24: 166.54201 | CM24: 214.42808 | CN24: 240.80188 | CO24: 101.92158 | CP24: 168.17438 | CQ24: 22.865471 | CR24: 146.51904 | CS24: 0 | CT24: 124.88023 | CU24: 198.65563 | CV24: 178.05088 | CW24: 6.1657771 | CX24: 0 | CY24: 295.69847 | CZ24: 253.8005
A25: Loans | B25: 22 | C25: 0 | D25: 0 | E25: 0 | F25: 0 | G25: 0 | H25: 0 | I25: 0 | J25: 0 | K25: 0 | L25: 0 | M25: 0 | N25: 0 | O25: 0 | P25: 0 | Q25: 0 | R25: 0 | S25: 0 | T25: 0 | U25: 0 | V25: 0 | W25: 0 | X25: 0 | Y25: 0 | Z25: 0 | AA25: 0 | AB25: 0 | AC25: 0 | AD25: 0 | AE25: 0 | AF25: 0 | AG25: 0 | AH25: 0 | AI25: 0 | AJ25: 0 | AK25: 0 | AL25: 0 | AM25: 0 | AN25: 0 | AO25: 0 | AP25: 0 | AQ25: 0 | AR25: 0 | AS25: 0 | AT25: 0 | AU25: 0 | AV25: 0 | AW25: 0 | AX25: 0 | AY25: 0 | AZ25: 0 | BA25: 0 | BB25: 0 | BC25: 0 | BD25: 0 | BE25: 0 | BF25: 0 | BG25: 0 | BH25: 0 | BI25: 0 | BJ25: 0 | BK25: 0 | BL25: 0 | BM25: 0 | BN25: 0 | BO25: 0 | BP25: 0 | BQ25: 0 | BR25: 0 | BS25: 0 | BT25: 0 | BU25: 0 | BV25: 0 | BW25: 0 | BX25: 0 | BY25: 0 | BZ25: 0 | CA25: 0 | CB25: 0 | CC25: 0 | CD25: 0 | CE25: 0 | CF25: 0 | CG25: 0 | CH25: 0 | CI25: 0 | CJ25: 0 | CK25: 0 | CL25: 0 | CM25: 0 | CN25: 0 | CO25: 0 | CP25: 0 | CQ25: 0 | CR25: 0 | CS25: 0 | CT25: 0 | CU25: 0 | CV25: 0 | CW25: 0 | CX25: 0 | CY25: 0 | CZ25: 0
A26: Trade credit and advances | B26: 23 | C26: 0 | D26: 0 | E26: 0 | F26: 0 | G26: 0 | H26: 0 | I26: 0 | J26: 0 | K26: 0 | L26: 0 | M26: 0 | N26: 0 | O26: 0 | P26: 0 | Q26: 0 | R26: 0 | S26: 0 | T26: 0 | U26: 0 | V26: 0 | W26: 0 | X26: 0 | Y26: 0 | Z26: 0 | AA26: 0 | AB26: 0 | AC26: 0 | AD26: 0 | AE26: 0 | AF26: 0 | AG26: 0 | AH26: 0 | AI26: 0 | AJ26: 0 | AK26: 0 | AL26: 0 | AM26: 0 | AN26: 0 | AO26: 0 | AP26: 0 | AQ26: 0 | AR26: 0 | AS26: 0 | AT26: 0 | AU26: 0 | AV26: 4.073155 | AW26: 3.4274431 | AX26: 2.7615975 | AY26: 0.012026682 | AZ26: 0 | BA26: 0 | BB26: 0 | BC26: 0 | BD26: 0 | BE26: 0 | BF26: 0 | BG26: 0 | BH26: 0 | BI26: 0 | BJ26: 0 | BK26: 0 | BL26: 0 | BM26: 0 | BN26: 0 | BO26: 0 | BP26: 4.1374662 | BQ26: 2.6343374 | BR26: 2.7412522 | BS26: 3.0566954 | BT26: 4.0611806 | BU26: 4.133103 | BV26: 4.4152113 | BW26: 4.0047021 | BX26: 4.2644172 | BY26: 4.0755653 | BZ26: 3.8163618 | CA26: 4.248081 | CB26: 4.7491982 | CC26: 5.5570325 | CD26: 5.135151 | CE26: 4.2061706 | CF26: 4.6863834 | CG26: 4.7226225 | CH26: 4.835949 | CI26: 3.4354432 | CJ26: 3.881775 | CK26: 4.703022 | CL26: 5.1213407 | CM26: 3.6554498 | CN26: 4.1044663 | CO26: 4.2491632 | CP26: 3.9657061 | CQ26: 3.744495 | CR26: 4.1657809 | CS26: 4.9331472 | CT26: 4.8438047 | CU26: 3.9095495 | CV26: 4.4666437 | CW26: 5.2382857 | CX26: 6.3008034 | CY26: 5.5327994 | CZ26: 6.8925595
A27: Other debt liabilities | B27: 24 | C27: 0 | D27: 0 | E27: 0 | F27: 0.055384 | G27: 0.18167838 | H27: 0.29181039 | I27: 0.229218 | J27: 0.39009444 | K27: 0.46085682 | L27: 0.34755532 | M27: 0.53020387 | N27: 0.68461626 | O27: 0.37856421 | P27: 0.47946807 | Q27: 1.8582822 | R27: 1.5978969 | S27: 1.2493511 | T27: 2.7279822 | U27: 1.0423986 | V27: 3.3066452 | W27: 0.86563863 | X27: 1.0602599 | Y27: 2.2672402 | Z27: 1.1860901 | AA27: 1.2007778 | AB27: 1.1099426 | AC27: 0.50204387 | AD27: 0.26785095 | AE27: 0.20791816 | AF27: 0.21613463 | AG27: 0.19338334 | AH27: 0.14614862 | AI27: 0 | AJ27: 0 | AK27: 0 | AL27: 0 | AM27: 0 | AN27: 0 | AO27: 0 | AP27: 0 | AQ27: 0 | AR27: 0 | AS27: 0 | AT27: 0 | AU27: 0 | AV27: 0 | AW27: 0 | AX27: 0 | AY27: 0 | AZ27: 3.662581 | BA27: 3.1713307 | BB27: 4.0580594 | BC27: 4.020045 | BD27: 6.040697 | BE27: 9.3207539 | BF27: 5.5946833 | BG27: 6.2989781 | BH27: 6.3356168 | BI27: 6.9491187 | BJ27: 6.4069727 | BK27: 5.0377767 | BL27: 5.0723777 | BM27: 3.7211367 | BN27: 7.4981189 | BO27: 4.5692991 | BP27: 0 | BQ27: 0 | BR27: 0 | BS27: 0 | BT27: 0 | BU27: 0 | BV27: 0 | BW27: 0 | BX27: 0 | BY27: 0 | BZ27: 0 | CA27: 0 | CB27: 0 | CC27: 0 | CD27: 0 | CE27: 0 | CF27: 0 | CG27: 0 | CH27: 0 | CI27: 0 | CJ27: 0 | CK27: 0 | CL27: 0 | CM27: 0 | CN27: 0 | CO27: 0 | CP27: 0 | CQ27: 0 | CR27: 0 | CS27: 0 | CT27: 0 | CU27: 0 | CV27: 0 | CW27: 0 | CX27: 0 | CY27: 0 | CZ27: 0
A28: Long-term | B28: 25=26+27+28+29+30+31 | C28: 1.902715 | D28: 1.902715 | E28: 1.902715 | F28: 1.902715 | G28: 1.902715 | H28: 1.902715 | I28: 1.902715 | J28: 1.902715 | K28: 1.902715 | L28: 1.902715 | M28: 1.902715 | N28: 1.902715 | O28: 1.8872386 | P28: 1.902715 | Q28: 1.902715 | R28: 1.902715 | S28: 1.902715 | T28: 1.902715 | U28: 1.902715 | V28: 1.902715 | W28: 1.902715 | X28: 1.902715 | Y28: 1.902715 | Z28: 1.902715 | AA28: 1.902715 | AB28: 1.902715 | AC28: 1.902715 | AD28: 1.902715 | AE28: 1.902715 | AF28: 1.902715 | AG28: 1.902715 | AH28: 1.902715 | AI28: 1.902715 | AJ28: 1.902715 | AK28: 1.902715 | AL28: 543.11753 | AM28: 537.76559 | AN28: 523.64673 | AO28: 507.93424 | AP28: 534.43584 | AQ28: 530.21568 | AR28: 543.86856 | AS28: 549.89699 | AT28: 539.63498 | AU28: 526.92797 | AV28: 534.06032 | AW28: 523.87089 | AX28: 531.85379 | AY28: 530.82088 | AZ28: 517.39651 | BA28: 519.38921 | BB28: 529.32206 | BC28: 536.00482 | BD28: 537.32255 | BE28: 537.42852 | BF28: 741.58512 | BG28: 738.0785 | BH28: 747.73258 | BI28: 768.2844 | BJ28: 795.38361 | BK28: 822.86956 | BL28: 787.30234 | BM28: 724.62776 | BN28: 560.85676 | BO28: 513.7632 | BP28: 493.43899 | BQ28: 504.10769 | BR28: 501.43884 | BS28: 504.56219 | BT28: 511.01574 | BU28: 494.05547 | BV28: 488.08563 | BW28: 484.15541 | BX28: 483.21901 | BY28: 483.92185 | BZ28: 474.94051 | CA28: 481.39413 | CB28: 477.12964 | CC28: 480.32782 | CD28: 489.88435 | CE28: 501.3436 | CF28: 493.22239 | CG28: 496.66444 | CH28: 2061.464 | CI28: 2041.1329 | CJ28: 2017.3952 | CK28: 1943.9291 | CL28: 1860.8162 | CM28: 1940.9168 | CN28: 1962.6003 | CO28: 1945.345 | CP28: 1912.4664 | CQ28: 1956.715 | CR28: 1930.1184 | CS28: 1917.8371 | CT28: 1976.137 | CU28: 1901.987 | CV28: 1933.3586 | CW28: 2002.9279 | CX28: 1997.3402 | CY28: 1999.0591 | CZ28: 1980.2141
A29: Special Drawing Rights | B29: 26 | C29: 0 | D29: 0 | E29: 0 | F29: 0 | G29: 0 | H29: 0 | I29: 0 | J29: 0 | K29: 0 | L29: 0 | M29: 0 | N29: 0 | O29: 0 | P29: 0 | Q29: 0 | R29: 0 | S29: 0 | T29: 0 | U29: 0 | V29: 0 | W29: 0 | X29: 0 | Y29: 0 | Z29: 0 | AA29: 0 | AB29: 0 | AC29: 0 | AD29: 0 | AE29: 0 | AF29: 0 | AG29: 0 | AH29: 0 | AI29: 0 | AJ29: 0 | AK29: 0 | AL29: 542.12802 | AM29: 536.77642 | AN29: 522.1907 | AO29: 506.94433 | AP29: 533.44666 | AQ29: 529.2265 | AR29: 542.86414 | AS29: 548.90781 | AT29: 538.59727 | AU29: 525.92428 | AV29: 530.95721 | AW29: 519.11423 | AX29: 529.14761 | AY29: 529.83103 | AZ29: 516.40733 | BA29: 518.40003 | BB29: 528.33288 | BC29: 535.01565 | BD29: 536.33317 | BE29: 536.43935 | BF29: 516.71247 | BG29: 503.20584 | BH29: 480.65645 | BI29: 487.50227 | BJ29: 488.05516 | BK29: 481.83176 | BL29: 488.67988 | BM29: 484.963 | BN29: 485.78832 | BO29: 465.57053 | BP29: 472.44981 | BQ29: 483.11851 | BR29: 490.44966 | BS29: 493.57301 | BT29: 505.04204 | BU29: 488.08177 | BV29: 487.11193 | BW29: 483.1817 | BX29: 482.2453 | BY29: 482.94815 | BZ29: 473.9668 | CA29: 480.42043 | CB29: 476.15593 | CC29: 479.35412 | CD29: 488.91064 | CE29: 500.36989 | CF29: 492.24868 | CG29: 495.69073 | CH29: 2060.4903 | CI29: 2040.1591 | CJ29: 2016.4027 | CK29: 1942.9366 | CL29: 1859.8237 | CM29: 1939.9431 | CN29: 1961.6266 | CO29: 1944.3713 | CP29: 1911.4927 | CQ29: 1955.7413 | CR29: 1929.1447 | CS29: 1916.8634 | CT29: 1975.1633 | CU29: 1901.0133 | CV29: 1932.3849 | CW29: 2001.9541 | CX29: 1996.3665 | CY29: 1998.0854 | CZ29: 1979.2404
A30: Currency and deposits | B30: 27 | C30: 0 | D30: 0 | E30: 0 | F30: 0 | G30: 0 | H30: 0 | I30: 0 | J30: 0 | K30: 0 | L30: 0 | M30: 0 | N30: 0 | O30: 0 | P30: 0 | Q30: 0 | R30: 0 | S30: 0 | T30: 0 | U30: 0 | V30: 0 | W30: 0 | X30: 0 | Y30: 0 | Z30: 0 | AA30: 0 | AB30: 0 | AC30: 0 | AD30: 0 | AE30: 0 | AF30: 0 | AG30: 0 | AH30: 0 | AI30: 0 | AJ30: 0 | AK30: 0 | AL30: 0 | AM30: 0 | AN30: 0 | AO30: 0 | AP30: 0 | AQ30: 0 | AR30: 0 | AS30: 0 | AT30: 0 | AU30: 0 | AV30: 0 | AW30: 0 | AX30: 0 | AY30: 0 | AZ30: 0 | BA30: 0 | BB30: 0 | BC30: 0 | BD30: 0 | BE30: 0 | BF30: 223.88348 | BG30: 233.88348 | BH30: 266.08696 | BI30: 279.79295 | BJ30: 306.33927 | BK30: 340.04862 | BL30: 297.63328 | BM30: 238.67559 | BN30: 73.749805 | BO30: 47.203482 | BP30: 20 | BQ30: 20 | BR30: 10 | BS30: 10 | BT30: 5 | BU30: 5 | BV30: 0 | BW30: 0 | BX30: 0 | BY30: 0 | BZ30: 0 | CA30: 0 | CB30: 0 | CC30: 0 | CD30: 0 | CE30: 0 | CF30: 0 | CG30: 0 | CH30: 0 | CI30: 0 | CJ30: 0 | CK30: 0 | CL30: 0 | CM30: 0 | CN30: 0 | CO30: 0 | CP30: 0 | CQ30: 0 | CR30: 0 | CS30: 0 | CT30: 0 | CU30: 0 | CV30: 0 | CW30: 0 | CX30: 0 | CY30: 0 | CZ30: 0
A31: Debt securities1 | B31: 28 | C31: 0 | D31: 0 | E31: 0 | F31: 0 | G31: 0 | H31: 0 | I31: 0 | J31: 0 | K31: 0 | L31: 0 | M31: 0 | N31: 0 | O31: 0 | P31: 0 | Q31: 0 | R31: 0 | S31: 0 | T31: 0 | U31: 0 | V31: 0 | W31: 0 | X31: 0 | Y31: 0 | Z31: 0 | AA31: 0 | AB31: 0 | AC31: 0 | AD31: 0 | AE31: 0 | AF31: 0 | AG31: 0 | AH31: 0 | AI31: 0 | AJ31: 0 | AK31: 0 | AL31: 0 | AM31: 0 | AN31: 0 | AO31: 0 | AP31: 0 | AQ31: 0 | AR31: 0 | AS31: 0 | AT31: 0 | AU31: 0 | AV31: 0 | AW31: 0 | AX31: 0 | AY31: 0 | AZ31: 0 | BA31: 0 | BB31: 0 | BC31: 0 | BD31: 0 | BE31: 0 | BF31: 0 | BG31: 0 | BH31: 0 | BI31: 0 | BJ31: 0 | BK31: 0 | BL31: 0 | BM31: 0 | BN31: 0 | BO31: 0 | BP31: 0 | BQ31: 0 | BR31: 0 | BS31: 0 | BT31: 0 | BU31: 0 | BV31: 0 | BW31: 0 | BX31: 0 | BY31: 0 | BZ31: 0 | CA31: 0 | CB31: 0 | CC31: 0 | CD31: 0 | CE31: 0 | CF31: 0 | CG31: 0 | CH31: 0 | CI31: 0 | CJ31: 0 | CK31: 0 | CL31: 0 | CM31: 0 | CN31: 0 | CO31: 0 | CP31: 0 | CQ31: 0 | CR31: 0 | CS31: 0 | CT31: 0 | CU31: 0 | CV31: 0 | CW31: 0 | CX31: 0 | CY31: 0 | CZ31: 0
A32: Loans | B32: 29 | C32: 0 | D32: 0 | E32: 0 | F32: 0 | G32: 0 | H32: 0 | I32: 0 | J32: 0 | K32: 0 | L32: 0 | M32: 0 | N32: 0 | O32: 0 | P32: 0 | Q32: 0 | R32: 0 | S32: 0 | T32: 0 | U32: 0 | V32: 0 | W32: 0 | X32: 0 | Y32: 0 | Z32: 0 | AA32: 0 | AB32: 0 | AC32: 0 | AD32: 0 | AE32: 0 | AF32: 0 | AG32: 0 | AH32: 0 | AI32: 0 | AJ32: 0 | AK32: 0 | AL32: 0 | AM32: 0 | AN32: 0 | AO32: 0 | AP32: 0 | AQ32: 0 | AR32: 0 | AS32: 0 | AT32: 0 | AU32: 0 | AV32: 0 | AW32: 0 | AX32: 0 | AY32: 0 | AZ32: 0 | BA32: 0 | BB32: 0 | BC32: 0 | BD32: 0 | BE32: 0 | BF32: 0 | BG32: 0 | BH32: 0 | BI32: 0 | BJ32: 0 | BK32: 0 | BL32: 0 | BM32: 0 | BN32: 0 | BO32: 0 | BP32: 0 | BQ32: 0 | BR32: 0 | BS32: 0 | BT32: 0 | BU32: 0 | BV32: 0 | BW32: 0 | BX32: 0 | BY32: 0 | BZ32: 0 | CA32: 0 | CB32: 0 | CC32: 0 | CD32: 0 | CE32: 0 | CF32: 0 | CG32: 0 | CH32: 0 | CI32: 0 | CJ32: 0 | CK32: 0 | CL32: 0 | CM32: 0 | CN32: 0 | CO32: 0 | CP32: 0 | CQ32: 0 | CR32: 0 | CS32: 0 | CT32: 0 | CU32: 0 | CV32: 0 | CW32: 0 | CX32: 0 | CY32: 0 | CZ32: 0
A33: Trade credit and advances | B33: 30 | C33: 0 | D33: 0 | E33: 0 | F33: 0 | G33: 0 | H33: 0 | I33: 0 | J33: 0 | K33: 0 | L33: 0 | M33: 0 | N33: 0 | O33: 0 | P33: 0 | Q33: 0 | R33: 0 | S33: 0 | T33: 0 | U33: 0 | V33: 0 | W33: 0 | X33: 0 | Y33: 0 | Z33: 0 | AA33: 0 | AB33: 0 | AC33: 0 | AD33: 0 | AE33: 0 | AF33: 0 | AG33: 0 | AH33: 0 | AI33: 0 | AJ33: 0 | AK33: 0 | AL33: 0 | AM33: 0 | AN33: 0 | AO33: 0 | AP33: 0 | AQ33: 0 | AR33: 0 | AS33: 0 | AT33: 0 | AU33: 0 | AV33: 0 | AW33: 0 | AX33: 0 | AY33: 0 | AZ33: 0 | BA33: 0 | BB33: 0 | BC33: 0 | BD33: 0 | BE33: 0 | BF33: 0 | BG33: 0 | BH33: 0 | BI33: 0 | BJ33: 0 | BK33: 0 | BL33: 0 | BM33: 0 | BN33: 0 | BO33: 0 | BP33: 0 | BQ33: 0 | BR33: 0 | BS33: 0 | BT33: 0 | BU33: 0 | BV33: 0 | BW33: 0 | BX33: 0 | BY33: 0 | BZ33: 0 | CA33: 0 | CB33: 0 | CC33: 0 | CD33: 0 | CE33: 0 | CF33: 0 | CG33: 0 | CH33: 0 | CI33: 0 | CJ33: 0 | CK33: 0 | CL33: 0 | CM33: 0 | CN33: 0 | CO33: 0 | CP33: 0 | CQ33: 0 | CR33: 0 | CS33: 0 | CT33: 0 | CU33: 0 | CV33: 0 | CW33: 0 | CX33: 0 | CY33: 0 | CZ33: 0
A34: Other debt liabilities | B34: 31 | C34: 1.902715 | D34: 1.902715 | E34: 1.902715 | F34: 1.902715 | G34: 1.902715 | H34: 1.902715 | I34: 1.902715 | J34: 1.902715 | K34: 1.902715 | L34: 1.902715 | M34: 1.902715 | N34: 1.902715 | O34: 1.8872386 | P34: 1.902715 | Q34: 1.902715 | R34: 1.902715 | S34: 1.902715 | T34: 1.902715 | U34: 1.902715 | V34: 1.902715 | W34: 1.902715 | X34: 1.902715 | Y34: 1.902715 | Z34: 1.902715 | AA34: 1.902715 | AB34: 1.902715 | AC34: 1.902715 | AD34: 1.902715 | AE34: 1.902715 | AF34: 1.902715 | AG34: 1.902715 | AH34: 1.902715 | AI34: 1.902715 | AJ34: 1.902715 | AK34: 1.902715 | AL34: 0.98950699 | AM34: 0.98917906 | AN34: 1.4560361 | AO34: 0.98990473 | AP34: 0.98917906 | AQ34: 0.98917906 | AR34: 1.0044135 | AS34: 0.98917906 | AT34: 1.0377135 | AU34: 1.0036962 | AV34: 3.1031083 | AW34: 4.7566634 | AX34: 2.7061771 | AY34: 0.98985291 | AZ34: 0.98917906 | BA34: 0.98917906 | BB34: 0.98917906 | BC34: 0.98917906 | BD34: 0.98937755 | BE34: 0.98917906 | BF34: 0.98917906 | BG34: 0.98917906 | BH34: 0.98917906 | BI34: 0.98917906 | BJ34: 0.98917906 | BK34: 0.98917906 | BL34: 0.98917906 | BM34: 0.98917906 | BN34: 1.3186322 | BO34: 0.98917906 | BP34: 0.98917906 | BQ34: 0.98917906 | BR34: 0.98917906 | BS34: 0.98917906 | BT34: 0.97370271 | BU34: 0.97370271 | BV34: 0.97370271 | BW34: 0.97370271 | BX34: 0.97370271 | BY34: 0.97370271 | BZ34: 0.97370271 | CA34: 0.97370271 | CB34: 0.97370271 | CC34: 0.97370271 | CD34: 0.97370271 | CE34: 0.97370271 | CF34: 0.97370271 | CG34: 0.97370271 | CH34: 0.97370271 | CI34: 0.97370271 | CJ34: 0.9925027 | CK34: 0.99250271 | CL34: 0.9925027 | CM34: 0.97370271 | CN34: 0.97370271 | CO34: 0.97370271 | CP34: 0.97370271 | CQ34: 0.97370271 | CR34: 0.97370271 | CS34: 0.97370271 | CT34: 0.97370271 | CU34: 0.97370271 | CV34: 0.97370271 | CW34: 0.97370271 | CX34: 0.97370271 | CY34: 0.97370271 | CZ34: 0.97370271
A35: Banks | B35: 32=33+39 | C35: 423.5045 | D35: 422.24492 | E35: 556.01769 | F35: 702.58429 | G35: 859.53433 | H35: 860.52926 | I35: 1201.4134 | J35: 1407.576 | K35: 1848.9731 | L35: 1890.8388 | M35: 2556.9331 | N35: 3163.9127 | O35: 4119.3063 | P35: 4463.5604 | Q35: 5214.6455 | R35: 6000.3496 | S35: 7681.5259 | T35: 8631.8377 | U35: 9751.0949 | V35: 10582.96 | W35: 15316.301 | X35: 17416.625 | Y35: 20417.345 | Z35: 23763.336 | AA35: 33323.358 | AB35: 38395 | AC35: 45905.933 | AD35: 45875.865 | AE35: 45946.193 | AF35: 45110.45 | AG35: 45064.447 | AH35: 41597.482 | AI35: 39221.177 | AJ35: 34105.771 | AK35: 32219.302 | AL35: 31387.199 | AM35: 30190.082 | AN35: 26177.646 | AO35: 24787.093 | AP35: 19041.736 | AQ35: 19947.873 | AR35: 19859.346 | AS35: 18820.25 | AT35: 16469.058 | AU35: 14604.765 | AV35: 14840.185 | AW35: 14421.727 | AX35: 13959.898 | AY35: 13524.904 | AZ35: 12736.188 | BA35: 11555.101 | BB35: 11529.585 | BC35: 11160.439 | BD35: 10571.265 | BE35: 10679.937 | BF35: 10556.523 | BG35: 10119.481 | BH35: 9292.8033 | BI35: 9666.474 | BJ35: 8575.4406 | BK35: 7972.7792 | BL35: 7697.6335 | BM35: 7667.0987 | BN35: 7562.138 | BO35: 7153.2613 | BP35: 6662.2755 | BQ35: 6168.0824 | BR35: 6289.0029 | BS35: 6501.874 | BT35: 5933.7993 | BU35: 6067.2627 | BV35: 5750.1249 | BW35: 5752.027 | BX35: 5248.5359 | BY35: 5112.6818 | BZ35: 4590.2035 | CA35: 4818.126 | CB35: 4649.2102 | CC35: 5068.0528 | CD35: 5053.4719 | CE35: 4837.4289 | CF35: 4978.7574 | CG35: 5975.1364 | CH35: 5735.0681 | CI35: 5493.8196 | CJ35: 8225.2913 | CK35: 9675.5996 | CL35: 8006.333 | CM35: 9675.4202 | CN35: 10616.682 | CO35: 10162.586 | CP35: 10631.119 | CQ35: 11202.252 | CR35: 12530.813 | CS35: 14323.072 | CT35: 14724.93 | CU35: 13120.393 | CV35: 14570.022 | CW35: 15634.157 | CX35: 15977.332 | CY35: 18287.41 | CZ35: 19152.14
A36: Short-term | B36: 33=34+35+36+37+38 | C36: 267.73575 | D36: 246.70054 | E36: 334.97418 | F36: 431.67845 | G36: 624.89825 | H36: 602.94116 | I36: 513.38118 | J36: 713.58103 | K36: 1005.0806 | L36: 966.48475 | M36: 1069.4511 | N36: 1191.4784 | O36: 1807.8277 | P36: 1697.7282 | Q36: 1840.6832 | R36: 2030.2 | S36: 2290.2086 | T36: 2560.8504 | U36: 2965.8371 | V36: 3841.5882 | W36: 6297.182 | X36: 6203.0006 | Y36: 6412.2314 | Z36: 4922.37 | AA36: 7465.4753 | AB36: 5271.6101 | AC36: 7353.0449 | AD36: 5061.5531 | AE36: 6102.7553 | AF36: 6027.5018 | AG36: 4802.1386 | AH36: 3354.2484 | AI36: 3093.3594 | AJ36: 2227.7796 | AK36: 2098.9531 | AL36: 1633.259 | AM36: 1646.201 | AN36: 1730.38 | AO36: 1324.443 | AP36: 1108.611 | AQ36: 1622.524 | AR36: 2372.654 | AS36: 1712.591 | AT36: 1212.2364 | AU36: 1046.6201 | AV36: 898.13 | AW36: 1223.379 | AX36: 939.735 | AY36: 1647.608 | AZ36: 1371.424 | BA36: 960.777 | BB36: 962.294 | BC36: 1227.598 | BD36: 1024.158 | BE36: 1103.331 | BF36: 1021.078 | BG36: 1467.555 | BH36: 837.507 | BI36: 802.418 | BJ36: 775.491 | BK36: 764.381 | BL36: 766.119 | BM36: 751.09 | BN36: 739.915 | BO36: 583.29 | BP36: 646.658 | BQ36: 662.672 | BR36: 771.02529 | BS36: 701.56575 | BT36: 714.78354 | BU36: 857.548 | BV36: 955.021 | BW36: 997.055 | BX36: 1208.129 | BY36: 1188.06 | BZ36: 934.943 | CA36: 1097.659 | CB36: 942.524 | CC36: 1187.562 | CD36: 1373.43 | CE36: 1312.4138 | CF36: 1562.7198 | CG36: 2204.7378 | CH36: 1975.038 | CI36: 1837.71 | CJ36: 2659.46 | CK36: 3409.0581 | CL36: 4199.0856 | CM36: 5658.2939 | CN36: 6004.1966 | CO36: 5224.6073 | CP36: 5329.967 | CQ36: 6333.4108 | CR36: 6923.5565 | CS36: 7961.6168 | CT36: 8384.2217 | CU36: 6633.5454 | CV36: 7830.2334 | CW36: 7922.1852 | CX36: 7448.0315 | CY36: 7926.9043 | CZ36: 9052.6743
A37: Currency and deposits | B37: 34 | C37: 165.15127 | D37: 143.00129 | E37: 182.87778 | F37: 290.51716 | G37: 308.22334 | H37: 265.12632 | I37: 147.16617 | J37: 178.83151 | K37: 328.07251 | L37: 284.48392 | M37: 359.99845 | N37: 402.09 | O37: 430.51221 | P37: 412.18233 | Q37: 328.38682 | R37: 555.685 | S37: 386.53542 | T37: 545.018 | U37: 638.262 | V37: 646.282 | W37: 804.18213 | X37: 725.65028 | Y37: 780.09053 | Z37: 742.20202 | AA37: 1297.9038 | AB37: 805.1473 | AC37: 1412.991 | AD37: 907.82569 | AE37: 1863.865 | AF37: 2153.9758 | AG37: 1669.0319 | AH37: 790.685 | AI37: 702.69208 | AJ37: 501.32235 | AK37: 476.60608 | AL37: 450.814 | AM37: 837.608 | AN37: 1129.993 | AO37: 743.344 | AP37: 796.808 | AQ37: 1275.372 | AR37: 1805.715 | AS37: 1236.306 | AT37: 769.4914 | AU37: 772.0811 | AV37: 499.826 | AW37: 932.606 | AX37: 547.651 | AY37: 1203.346 | AZ37: 1016.384 | BA37: 734.563 | BB37: 695.213 | BC37: 829.525 | BD37: 652.98 | BE37: 864.004 | BF37: 833.834 | BG37: 987.959 | BH37: 690.799 | BI37: 647.743 | BJ37: 625.845 | BK37: 575.126 | BL37: 591.399 | BM37: 600.11 | BN37: 603.75 | BO37: 473.799 | BP37: 515.644 | BQ37: 496.58 | BR37: 567.777 | BS37: 505.44 | BT37: 508.247 | BU37: 584.905 | BV37: 614.878 | BW37: 704.199 | BX37: 687.752 | BY37: 938.111 | BZ37: 687.228 | CA37: 863.592 | CB37: 757.565 | CC37: 916.275 | CD37: 1148.941 | CE37: 1149.3548 | CF37: 1203.3578 | CG37: 1731.7298 | CH37: 1509.5 | CI37: 1612.268 | CJ37: 1366.184 | CK37: 1991.111 | CL37: 3348.847 | CM37: 4456.55 | CN37: 4434.3745 | CO37: 4159.0026 | CP37: 4037.9077 | CQ37: 4700.6806 | CR37: 4813.6861 | CS37: 5261.0968 | CT37: 5166.2063 | CU37: 5174.9443 | CV37: 6302.3258 | CW37: 6286.4074 | CX37: 5981.9437 | CY37: 6376.9208 | CZ37: 6118.0949
A38: Debt securities1 | B38: 35 | C38: 0 | D38: 0 | E38: 0 | F38: 0 | G38: 0 | H38: 0 | I38: 0 | J38: 0 | K38: 0 | L38: 0 | M38: 0 | N38: 0 | O38: 0 | P38: 0 | Q38: 0 | R38: 0 | S38: 0 | T38: 0 | U38: 0 | V38: 0 | W38: 0 | X38: 0 | Y38: 0 | Z38: 0 | AA38: 0 | AB38: 0 | AC38: 0 | AD38: 0 | AE38: 0 | AF38: 0 | AG38: 0 | AH38: 0 | AI38: 0 | AJ38: 0 | AK38: 0 | AL38: 0 | AM38: 0 | AN38: 0 | AO38: 0 | AP38: 0 | AQ38: 0 | AR38: 0 | AS38: 0 | AT38: 0 | AU38: 0 | AV38: 0 | AW38: 0 | AX38: 0 | AY38: 0 | AZ38: 0 | BA38: 0 | BB38: 0 | BC38: 0 | BD38: 0 | BE38: 0 | BF38: 0 | BG38: 0 | BH38: 0 | BI38: 0 | BJ38: 0 | BK38: 0 | BL38: 0 | BM38: 0 | BN38: 0 | BO38: 0 | BP38: 0 | BQ38: 0 | BR38: 0.017292418 | BS38: 0.017753438 | BT38: 0.01853539 | BU38: 0 | BV38: 0 | BW38: 0 | BX38: 0 | BY38: 0 | BZ38: 0 | CA38: 0 | CB38: 0 | CC38: 0 | CD38: 0 | CE38: 0 | CF38: 0 | CG38: 0 | CH38: 0 | CI38: 0 | CJ38: 0 | CK38: 0 | CL38: 0 | CM38: 0 | CN38: 0 | CO38: 0 | CP38: 0 | CQ38: 0 | CR38: 0 | CS38: 0 | CT38: 0.012875 | CU38: 2.8218285 | CV38: 4.32638 | CW38: 9.02348 | CX38: 11.125273 | CY38: 10.137081 | CZ38: 30.110499
A39: Loans | B39: 36 | C39: 98.216385 | D39: 101.13875 | E39: 148.2574 | F39: 138.13328 | G39: 310.44531 | H39: 334.52225 | I39: 361.80021 | J39: 531.58872 | K39: 673.11261 | L39: 671.48147 | M39: 683.89033 | N39: 764.15341 | O39: 1359.6885 | P39: 1265.9349 | Q39: 1486.8181 | R39: 1363.1997 | S39: 1728.7489 | T39: 1958.0504 | U39: 2274.8691 | V39: 3047.6509 | W39: 5318.2172 | X39: 5303.2142 | Y39: 5377.2534 | Z39: 3974.2739 | AA39: 5801.3554 | AB39: 3873.167 | AC39: 5406.89 | AD39: 3801.856 | AE39: 3747.49 | AF39: 3444.58 | AG39: 2654.03 | AH39: 2079.6454 | AI39: 2010.9293 | AJ39: 1506.081 | AK39: 1129.356 | AL39: 807.011 | AM39: 353.076 | AN39: 399.643 | AO39: 422.804 | AP39: 151.568 | AQ39: 227.74 | AR39: 408.34501 | AS39: 356.269 | AT39: 289.73 | AU39: 130.833 | AV39: 275.338 | AW39: 196.164 | AX39: 319.266 | AY39: 360.945 | AZ39: 284.835 | BA39: 156.923 | BB39: 205.912 | BC39: 316.588 | BD39: 272.913 | BE39: 165.218 | BF39: 120.315 | BG39: 351.77 | BH39: 66.938 | BI39: 93.78 | BJ39: 89.73 | BK39: 149.098 | BL39: 101.391 | BM39: 98.956 | BN39: 96.801 | BO39: 69.886 | BP39: 85.948 | BQ39: 92.911 | BR39: 88.155 | BS39: 116.652 | BT39: 110.482 | BU39: 160.858 | BV39: 165.559 | BW39: 132.063 | BX39: 101.838 | BY39: 25.957 | BZ39: 33.66 | CA39: 95.479 | CB39: 30.741 | CC39: 61.818 | CD39: 0.435 | CE39: 23.938 | CF39: 80.45 | CG39: 194.085 | CH39: 210.675 | CI39: 9.266 | CJ39: 1022.077 | CK39: 987.31833 | CL39: 555.83132 | CM39: 797.594 | CN39: 1120.2 | CO39: 569.724 | CP39: 766.559 | CQ39: 743.707 | CR39: 1108.136 | CS39: 1843.54 | CT39: 2287.391 | CU39: 1045.408 | CV39: 1040.001 | CW39: 841.939 | CX39: 825.09033 | CY39: 785.032 | CZ39: 2201.99
A40: Trade credit and advances | B40: 37 | C40: 0 | D40: 0 | E40: 0 | F40: 0 | G40: 0 | H40: 0 | I40: 0 | J40: 0 | K40: 0 | L40: 0 | M40: 0 | N40: 0 | O40: 0 | P40: 0 | Q40: 0 | R40: 0 | S40: 0 | T40: 0 | U40: 0 | V40: 0 | W40: 0 | X40: 0 | Y40: 0 | Z40: 0 | AA40: 0 | AB40: 0 | AC40: 0 | AD40: 0 | AE40: 0 | AF40: 0 | AG40: 0 | AH40: 0 | AI40: 0 | AJ40: 0 | AK40: 0 | AL40: 0 | AM40: 0 | AN40: 0 | AO40: 0 | AP40: 0 | AQ40: 0 | AR40: 0 | AS40: 0 | AT40: 0 | AU40: 0 | AV40: 0 | AW40: 0 | AX40: 0 | AY40: 0 | AZ40: 0 | BA40: 0 | BB40: 0 | BC40: 0 | BD40: 0 | BE40: 0 | BF40: 0 | BG40: 0 | BH40: 0 | BI40: 0 | BJ40: 0 | BK40: 0 | BL40: 0 | BM40: 0 | BN40: 0 | BO40: 0 | BP40: 0 | BQ40: 0 | BR40: 0 | BS40: 0 | BT40: 0 | BU40: 0 | BV40: 0 | BW40: 0 | BX40: 0 | BY40: 0 | BZ40: 0 | CA40: 0 | CB40: 0 | CC40: 0 | CD40: 0 | CE40: 0 | CF40: 0 | CG40: 0 | CH40: 0 | CI40: 0 | CJ40: 0 | CK40: 0 | CL40: 0 | CM40: 0 | CN40: 0 | CO40: 0 | CP40: 0 | CQ40: 0 | CR40: 0 | CS40: 0 | CT40: 0 | CU40: 0 | CV40: 0 | CW40: 0 | CX40: 0 | CY40: 0 | CZ40: 0
A41: Other debt liabilities | B41: 38 | C41: 4.3681 | D41: 2.5605 | E41: 3.839 | F41: 3.028 | G41: 6.2296 | H41: 3.292583 | I41: 4.414799 | J41: 3.160796 | K41: 3.89544 | L41: 10.51936 | M41: 25.5623 | N41: 25.235 | O41: 17.627 | P41: 19.611 | Q41: 25.47832 | R41: 111.3153 | S41: 174.9243 | T41: 57.782 | U41: 52.706 | V41: 147.6553 | W41: 174.7827 | X41: 174.13605 | Y41: 254.8875 | Z41: 205.89409 | AA41: 366.21618 | AB41: 593.2958 | AC41: 533.16384 | AD41: 351.87142 | AE41: 491.4003 | AF41: 428.94608 | AG41: 479.07676 | AH41: 483.918 | AI41: 379.73799 | AJ41: 220.37621 | AK41: 492.991 | AL41: 375.434 | AM41: 455.517 | AN41: 200.744 | AO41: 158.295 | AP41: 160.235 | AQ41: 119.412 | AR41: 158.594 | AS41: 120.016 | AT41: 153.015 | AU41: 143.706 | AV41: 122.966 | AW41: 94.609 | AX41: 72.818 | AY41: 83.317 | AZ41: 70.205 | BA41: 69.291 | BB41: 61.169 | BC41: 81.485 | BD41: 98.265 | BE41: 74.109 | BF41: 66.929 | BG41: 127.826 | BH41: 79.77 | BI41: 60.895 | BJ41: 59.916 | BK41: 40.157 | BL41: 73.329 | BM41: 52.024 | BN41: 39.364 | BO41: 39.605 | BP41: 45.066 | BQ41: 73.181 | BR41: 115.076 | BS41: 79.456 | BT41: 96.036 | BU41: 111.785 | BV41: 174.584 | BW41: 160.793 | BX41: 418.539 | BY41: 223.992 | BZ41: 214.055 | CA41: 138.588 | CB41: 154.218 | CC41: 209.469 | CD41: 224.054 | CE41: 139.121 | CF41: 278.912 | CG41: 278.923 | CH41: 254.863 | CI41: 216.176 | CJ41: 271.199 | CK41: 430.62877 | CL41: 294.40725 | CM41: 404.14994 | CN41: 449.62212 | CO41: 495.88074 | CP41: 525.50031 | CQ41: 889.02322 | CR41: 1001.7345 | CS41: 856.97996 | CT41: 930.61157 | CU41: 410.37133 | CV41: 483.58018 | CW41: 784.81537 | CX41: 629.87223 | CY41: 754.81443 | CZ41: 702.47888
A42: Long-term | B42: 39=40+41+42+43+44 | C42: 155.76874 | D42: 175.54438 | E42: 221.0435 | F42: 270.90584 | G42: 234.63608 | H42: 257.5881 | I42: 688.03219 | J42: 693.99494 | K42: 843.89249 | L42: 924.35406 | M42: 1487.482 | N42: 1972.4343 | O42: 2311.4785 | P42: 2765.8322 | Q42: 3373.9622 | R42: 3970.1496 | S42: 5391.3172 | T42: 6070.9873 | U42: 6785.2577 | V42: 6741.3721 | W42: 9019.1186 | X42: 11213.625 | Y42: 14005.114 | Z42: 18840.966 | AA42: 25857.883 | AB42: 33123.39 | AC42: 38552.888 | AD42: 40814.311 | AE42: 39843.438 | AF42: 39082.948 | AG42: 40262.308 | AH42: 38243.234 | AI42: 36127.817 | AJ42: 31877.992 | AK42: 30120.349 | AL42: 29753.94 | AM42: 28543.881 | AN42: 24447.266 | AO42: 23462.65 | AP42: 17933.125 | AQ42: 18325.349 | AR42: 17486.692 | AS42: 17107.659 | AT42: 15256.822 | AU42: 13558.145 | AV42: 13942.055 | AW42: 13198.348 | AX42: 13020.163 | AY42: 11877.296 | AZ42: 11364.764 | BA42: 10594.324 | BB42: 10567.291 | BC42: 9932.841 | BD42: 9547.1065 | BE42: 9576.6063 | BF42: 9535.4447 | BG42: 8651.9262 | BH42: 8455.2963 | BI42: 8864.056 | BJ42: 7799.9496 | BK42: 7208.3982 | BL42: 6931.5145 | BM42: 6916.0087 | BN42: 6822.223 | BO42: 6569.9713 | BP42: 6015.6175 | BQ42: 5505.4104 | BR42: 5517.9776 | BS42: 5800.3082 | BT42: 5219.0158 | BU42: 5209.7147 | BV42: 4795.1039 | BW42: 4754.972 | BX42: 4040.4069 | BY42: 3924.6218 | BZ42: 3655.2605 | CA42: 3720.467 | CB42: 3706.6862 | CC42: 3880.4908 | CD42: 3680.0419 | CE42: 3525.0151 | CF42: 3416.0376 | CG42: 3770.3986 | CH42: 3760.0301 | CI42: 3656.1096 | CJ42: 5565.8313 | CK42: 6266.5415 | CL42: 3807.2474 | CM42: 4017.1262 | CN42: 4612.4856 | CO42: 4937.9784 | CP42: 5301.1525 | CQ42: 4868.8414 | CR42: 5607.2561 | CS42: 6361.4552 | CT42: 6340.7087 | CU42: 6486.8479 | CV42: 6739.7884 | CW42: 7711.972 | CX42: 8529.3002 | CY42: 10360.506 | CZ42: 10099.466
A43: Currency and deposits | B43: 40 | C43: 0.183458 | D43: 0.308098 | E43: 1.052496 | F43: 1.490795 | G43: 1.847301 | H43: 12.909815 | I43: 197.46872 | J43: 198.44025 | K43: 137.3743 | L43: 123.33165 | M43: 63.08414 | N43: 103.368 | O43: 146.85303 | P43: 195.034 | Q43: 187.563 | R43: 186.652 | S43: 200.779 | T43: 183.797 | U43: 179.726 | V43: 219.764 | W43: 308.33296 | X43: 316.57169 | Y43: 257.7798 | Z43: 268.19068 | AA43: 487.26063 | AB43: 611.791 | AC43: 647.05201 | AD43: 724.27296 | AE43: 701.39 | AF43: 586.151 | AG43: 590.85 | AH43: 581.283 | AI43: 527.596 | AJ43: 298.077 | AK43: 313.516 | AL43: 298.88 | AM43: 289.652 | AN43: 252.937 | AO43: 260.564 | AP43: 268.647 | AQ43: 275.122 | AR43: 278.862 | AS43: 277.674 | AT43: 254.968 | AU43: 262.202 | AV43: 549.865 | AW43: 590.911 | AX43: 550.1 | AY43: 428.534 | AZ43: 440.808 | BA43: 868.501 | BB43: 917.9 | BC43: 944.619 | BD43: 904.077 | BE43: 931.533 | BF43: 826.381 | BG43: 815.956 | BH43: 795.158 | BI43: 788.018 | BJ43: 110.631 | BK43: 149.402 | BL43: 125.036 | BM43: 129.38 | BN43: 130.463 | BO43: 158.433 | BP43: 162.2 | BQ43: 171.421 | BR43: 184.717 | BS43: 193.41 | BT43: 231.572 | BU43: 165.942 | BV43: 165.69 | BW43: 306.108 | BX43: 246.787 | BY43: 209.669 | BZ43: 224.303 | CA43: 237.435 | CB43: 203.164 | CC43: 256.232 | CD43: 188.935 | CE43: 244.042 | CF43: 430.629 | CG43: 350.881 | CH43: 255.252 | CI43: 226.176 | CJ43: 396.678 | CK43: 459.137 | CL43: 748.949 | CM43: 1462.594 | CN43: 2141.2663 | CO43: 2685.2411 | CP43: 3158.7 | CQ43: 2811.0182 | CR43: 3630.0939 | CS43: 3768.77 | CT43: 3632.489 | CU43: 3041.689 | CV43: 3078.295 | CW43: 2758.371 | CX43: 2683.125 | CY43: 2767.601 | CZ43: 2712.39
A44: Debt securities1 | B44: 41 | C44: 31.332 | D44: 47.192 | E44: 27.195 | F44: 0.202 | G44: 0.208 | H44: 0.2024 | I44: 2.7978 | J44: 2.7978 | K44: 57.1715 | L44: 45.2816 | M44: 39.3229 | N44: 40.571141 | O44: 120.2219 | P44: 149.78617 | Q44: 235.96662 | R44: 280.48548 | S44: 754.06716 | T44: 891.22558 | U44: 1482.0569 | V44: 1548.9899 | W44: 1824.8497 | X44: 2081.4989 | Y44: 2523.3896 | Z44: 2543.7965 | AA44: 2984.1211 | AB44: 3212.5731 | AC44: 3560.0337 | AD44: 3648.8375 | AE44: 3266.1967 | AF44: 3145.2071 | AG44: 3253.8924 | AH44: 3320.2027 | AI44: 2518.2609 | AJ44: 1845.2617 | AK44: 2797.9676 | AL44: 2911.2566 | AM44: 2905.4593 | AN44: 6846.3601 | AO44: 6513.5056 | AP44: 10510.147 | AQ44: 10695.485 | AR44: 11070.579 | AS44: 10556.036 | AT44: 9199.8934 | AU44: 7916.3193 | AV44: 8140.0971 | AW44: 7603.0074 | AX44: 7814.7081 | AY44: 6639.7603 | AZ44: 7240.8494 | BA44: 6271.1579 | BB44: 6247.4664 | BC44: 5739.695 | BD44: 5353.8115 | BE44: 5463.3733 | BF44: 5508.8167 | BG44: 4704.1142 | BH44: 4594.0623 | BI44: 4812.51 | BJ44: 4589.2546 | BK44: 3999.8882 | BL44: 3832.3995 | BM44: 3793.1357 | BN44: 3787.282 | BO44: 3316.1823 | BP44: 3044.0575 | BQ44: 2567.9084 | BR44: 2532.3996 | BS44: 2780.7612 | BT44: 2627.5588 | BU44: 2607.0357 | BV44: 2577.0149 | BW44: 2441.929 | BX44: 2154.7918 | BY44: 2112.1157 | BZ44: 2001.9144 | CA44: 1875.8529 | CB44: 1870.7721 | CC44: 1841.1997 | CD44: 1779.3938 | CE44: 1568.211 | CF44: 1434.2515 | CG44: 1859.7075 | CH44: 1885.003 | CI44: 1888.7624 | CJ44: 1758.0502 | CK44: 1403.2474 | CL44: 1361.2223 | CM44: 752.64712 | CN44: 742.69316 | CO44: 553.59613 | CP44: 511.73617 | CQ44: 516.81206 | CR44: 510.06002 | CS44: 1005.1921 | CT44: 970.02857 | CU44: 1342.0338 | CV44: 1808.5803 | CW44: 1950.6789 | CX44: 2242.3851 | CY44: 3593.9938 | CZ44: 3631.5857
A45: Loans | B45: 42 | C45: 124.25328 | D45: 128.04428 | E45: 192.79601 | F45: 269.21305 | G45: 232.58078 | H45: 244.47588 | I45: 487.76567 | J45: 492.75689 | K45: 649.34669 | L45: 755.74082 | M45: 1385.075 | N45: 1828.4952 | O45: 2044.4036 | P45: 2421.012 | Q45: 2950.4326 | R45: 3503.0121 | S45: 4436.4711 | T45: 4995.9647 | U45: 5123.4748 | V45: 4972.6182 | W45: 6885.9359 | X45: 8815.5542 | Y45: 11223.944 | Z45: 16028.978 | AA45: 22386.501 | AB45: 29299.026 | AC45: 34345.802 | AD45: 36441.201 | AE45: 35875.851 | AF45: 35351.59 | AG45: 36417.565 | AH45: 34341.748 | AI45: 33081.96 | AJ45: 29734.653 | AK45: 27008.865 | AL45: 26543.803 | AM45: 25348.77 | AN45: 17347.968 | AO45: 16688.58 | AP45: 7154.3309 | AQ45: 7354.7411 | AR45: 6137.2507 | AS45: 6273.9494 | AT45: 5801.9604 | AU45: 5379.6238 | AV45: 5252.093 | AW45: 5004.43 | AX45: 4655.355 | AY45: 4809.002 | AZ45: 3683.107 | BA45: 3454.665 | BB45: 3401.925 | BC45: 3248.527 | BD45: 3289.218 | BE45: 3181.7 | BF45: 3200.247 | BG45: 3131.856 | BH45: 3066.076 | BI45: 3263.528 | BJ45: 3100.064 | BK45: 3059.108 | BL45: 2974.079 | BM45: 2993.493 | BN45: 2904.478 | BO45: 3095.356 | BP45: 2809.36 | BQ45: 2766.081 | BR45: 2800.861 | BS45: 2826.137 | BT45: 2359.885 | BU45: 2436.737 | BV45: 2052.399 | BW45: 2006.935 | BX45: 1638.8281 | BY45: 1602.8371 | BZ45: 1429.0431 | CA45: 1607.1791 | CB45: 1632.7501 | CC45: 1783.0591 | CD45: 1711.7131 | CE45: 1712.7621 | CF45: 1551.1571 | CG45: 1559.8101 | CH45: 1619.7751 | CI45: 1541.1711 | CJ45: 3411.1031 | CK45: 4404.1571 | CL45: 1697.0761 | CM45: 1801.8851 | CN45: 1728.5261 | CO45: 1699.1411 | CP45: 1630.7164 | CQ45: 1541.0111 | CR45: 1467.1021 | CS45: 1587.4931 | CT45: 1738.1911 | CU45: 2103.1251 | CV45: 1852.9131 | CW45: 3002.9221 | CX45: 3603.7901 | CY45: 3998.9111 | CZ45: 3755.4901
A46: Trade credit and advances | B46: 43 | C46: 0 | D46: 0 | E46: 0 | F46: 0 | G46: 0 | H46: 0 | I46: 0 | J46: 0 | K46: 0 | L46: 0 | M46: 0 | N46: 0 | O46: 0 | P46: 0 | Q46: 0 | R46: 0 | S46: 0 | T46: 0 | U46: 0 | V46: 0 | W46: 0 | X46: 0 | Y46: 0 | Z46: 0 | AA46: 0 | AB46: 0 | AC46: 0 | AD46: 0 | AE46: 0 | AF46: 0 | AG46: 0 | AH46: 0 | AI46: 0 | AJ46: 0 | AK46: 0 | AL46: 0 | AM46: 0 | AN46: 0 | AO46: 0 | AP46: 0 | AQ46: 0 | AR46: 0 | AS46: 0 | AT46: 0 | AU46: 0 | AV46: 0 | AW46: 0 | AX46: 0 | AY46: 0 | AZ46: 0 | BA46: 0 | BB46: 0 | BC46: 0 | BD46: 0 | BE46: 0 | BF46: 0 | BG46: 0 | BH46: 0 | BI46: 0 | BJ46: 0 | BK46: 0 | BL46: 0 | BM46: 0 | BN46: 0 | BO46: 0 | BP46: 0 | BQ46: 0 | BR46: 0 | BS46: 0 | BT46: 0 | BU46: 0 | BV46: 0 | BW46: 0 | BX46: 0 | BY46: 0 | BZ46: 0 | CA46: 0 | CB46: 0 | CC46: 0 | CD46: 0 | CE46: 0 | CF46: 0 | CG46: 0 | CH46: 0 | CI46: 0 | CJ46: 0 | CK46: 0 | CL46: 0 | CM46: 0 | CN46: 0 | CO46: 0 | CP46: 0 | CQ46: 0 | CR46: 0 | CS46: 0 | CT46: 0 | CU46: 0 | CV46: 0 | CW46: 0 | CX46: 0 | CY46: 0 | CZ46: 0
A47: Other debt liabilities | B47: 44 | C47: 0 | D47: 0 | E47: 0 | F47: 0 | G47: 0 | H47: 0 | I47: 0 | J47: 0 | K47: 0 | L47: 0 | M47: 0 | N47: 0 | O47: 0 | P47: 0 | Q47: 0 | R47: 0 | S47: 0 | T47: 0 | U47: 0 | V47: 0 | W47: 0 | X47: 0 | Y47: 0 | Z47: 0 | AA47: 0 | AB47: 0 | AC47: 0 | AD47: 0 | AE47: 0 | AF47: 0 | AG47: 0 | AH47: 0 | AI47: 0 | AJ47: 0 | AK47: 0 | AL47: 0 | AM47: 0 | AN47: 0 | AO47: 0 | AP47: 0 | AQ47: 0 | AR47: 0 | AS47: 0 | AT47: 0 | AU47: 0 | AV47: 0 | AW47: 0 | AX47: 0 | AY47: 0 | AZ47: 0 | BA47: 0 | BB47: 0 | BC47: 0 | BD47: 0 | BE47: 0 | BF47: 0 | BG47: 0 | BH47: 0 | BI47: 0 | BJ47: 0 | BK47: 0 | BL47: 0 | BM47: 0 | BN47: 0 | BO47: 0 | BP47: 0 | BQ47: 0 | BR47: 0 | BS47: 0 | BT47: 0 | BU47: 0 | BV47: 0 | BW47: 0 | BX47: 0 | BY47: 0 | BZ47: 0 | CA47: 0 | CB47: 0 | CC47: 0 | CD47: 0 | CE47: 0 | CF47: 0 | CG47: 0 | CH47: 0 | CI47: 0 | CJ47: 0 | CK47: 0 | CL47: 0 | CM47: 0 | CN47: 0 | CO47: 0 | CP47: 0 | CQ47: 0 | CR47: 0 | CS47: 0 | CT47: 0 | CU47: 0 | CV47: 0 | CW47: 0 | CX47: 0 | CY47: 0 | CZ47: 0
A48: Other Sectors | B48: 45=47+53=59+62 | C48: 2297.0645 | D48: 2312.6611 | E48: 2469.2985 | F48: 2648.717 | G48: 2573.0748 | H48: 2701.0706 | I48: 2863.1384 | J48: 3088.5563 | K48: 3239.6338 | L48: 3597.6805 | M48: 3716.5785 | N48: 4164.7536 | O48: 4432.2552 | P48: 4398.9481 | Q48: 4725.6804 | R48: 4827.5083 | S48: 5867.6467 | T48: 6070.5036 | U48: 6683.8505 | V48: 7322.1164 | W48: 7307.8066 | X48: 8132.0034 | Y48: 9601.7053 | Z48: 10569.72 | AA48: 12605.675 | AB48: 13450.094 | AC48: 15148.893 | AD48: 17315.152 | AE48: 19267.795 | AF48: 20921.288 | AG48: 21719.957 | AH48: 24542.069 | AI48: 26859.413 | AJ48: 27605.714 | AK48: 29577.325 | AL48: 30584.606 | AM48: 29809.199 | AN48: 29894.769 | AO48: 30913.981 | AP48: 31772.102 | AQ48: 41199.207 | AR48: 39615.02 | AS48: 40257.242 | AT48: 40185.497 | AU48: 43089.142 | AV48: 43959.516 | AW48: 46588.743 | AX48: 47735.88 | AY48: 50311.044 | AZ48: 51115.396 | BA48: 56262.516 | BB48: 57539.52 | BC48: 58928.661 | BD48: 59077.474 | BE48: 63052.08 | BF48: 58350.072 | BG48: 59572.82 | BH48: 41918.559 | BI48: 41133.124 | BJ48: 39180.161 | BK48: 36558.306 | BL48: 36473.819 | BM48: 39102.781 | BN48: 39528.624 | BO48: 38838.814 | BP48: 40080.948 | BQ48: 42163.073 | BR48: 43310.002 | BS48: 43614.363 | BT48: 43202.996 | BU48: 42884.045 | BV48: 41306.005 | BW48: 39661.679 | BX48: 39020.335 | BY48: 39661.846 | BZ48: 41013.029 | CA48: 41040.547 | CB48: 37404.81 | CC48: 39737.738 | CD48: 40701.02 | CE48: 41388.027 | CF48: 41412.256 | CG48: 42662.134 | CH48: 42908.383 | CI48: 44013.396 | CJ48: 40543.965 | CK48: 43591.511 | CL48: 43752.173 | CM48: 42227.302 | CN48: 43265.504 | CO48: 43768.614 | CP48: 45004.55 | CQ48: 45463.463 | CR48: 45172.156 | CS48: 45898.563 | CT48: 45701.476 | CU48: 45172.717 | CV48: 48210.282 | CW48: 50150.66 | CX48: 50671.649 | CY48: 55062.847 | CZ48: 57324.442
A49: Short-term | B49: 47=48+49+50+51+52= 60+63 | C49: 692.61241 | D49: 664.2106 | E49: 803.40659 | F49: 743.25845 | G49: 714.92164 | H49: 682.98339 | I49: 789.1185 | J49: 860.52346 | K49: 1040.5689 | L49: 1043.2655 | M49: 1002.4804 | N49: 1185.5298 | O49: 1362.4004 | P49: 1289.4232 | Q49: 1340.9299 | R49: 1254.7472 | S49: 1572.7181 | T49: 1626.8645 | U49: 1581.3869 | V49: 1634.5234 | W49: 1703.6083 | X49: 2056.6119 | Y49: 2797.8392 | Z49: 3386.6706 | AA49: 3904.8016 | AB49: 3953.0741 | AC49: 4392.4862 | AD49: 4636.9272 | AE49: 5321.935 | AF49: 5351.1707 | AG49: 5547.8235 | AH49: 6894.5669 | AI49: 6383.1825 | AJ49: 5417.4187 | AK49: 5892.4767 | AL49: 6016.2575 | AM49: 4859.2143 | AN49: 4996.8163 | AO49: 5118.9236 | AP49: 5819.3144 | AQ49: 6771.5367 | AR49: 5668.3505 | AS49: 5853.7953 | AT49: 6232.9719 | AU49: 6776.3798 | AV49: 6511.4403 | AW49: 6840.2155 | AX49: 6964.4268 | AY49: 7350.5631 | AZ49: 6930.4366 | BA49: 7351.2842 | BB49: 8195.3011 | BC49: 8229.7764 | BD49: 7920.7069 | BE49: 8495.5513 | BF49: 8153.3371 | BG49: 8029.4125 | BH49: 7209.3862 | BI49: 6958.2561 | BJ49: 5557.7756 | BK49: 5398.3447 | BL49: 5345.6421 | BM49: 5389.8125 | BN49: 5798.7649 | BO49: 5720.8481 | BP49: 5767.1182 | BQ49: 5923.2159 | BR49: 6251.2918 | BS49: 6346.5534 | BT49: 6185.6608 | BU49: 6512.349 | BV49: 6892.4904 | BW49: 6849.2516 | BX49: 6515.8333 | BY49: 6809.6502 | BZ49: 7115.6561 | CA49: 7278.8911 | CB49: 6915.5277 | CC49: 7342.1323 | CD49: 7440.1024 | CE49: 7315.9617 | CF49: 8020.2671 | CG49: 8788.7609 | CH49: 8591.0918 | CI49: 9652.9752 | CJ49: 8528.2459 | CK49: 10435.303 | CL49: 11110.774 | CM49: 10391.145 | CN49: 10937.881 | CO49: 11801.929 | CP49: 12595.676 | CQ49: 12664.016 | CR49: 11923.006 | CS49: 12433.458 | CT49: 12411.64 | CU49: 12083.578 | CV49: 13322.464 | CW49: 14136.289 | CX49: 13165.472 | CY49: 13047.439 | CZ49: 13994.506
A50: Currency and deposits | B50: 48 | C50: 0 | D50: 0 | E50: 0 | F50: 0 | G50: 0 | H50: 0 | I50: 0 | J50: 0 | K50: 0 | L50: 0 | M50: 0 | N50: 0 | O50: 0 | P50: 0 | Q50: 0 | R50: 0 | S50: 0 | T50: 0 | U50: 0 | V50: 0 | W50: 0 | X50: 0 | Y50: 0 | Z50: 0 | AA50: 0 | AB50: 0 | AC50: 0 | AD50: 0 | AE50: 0 | AF50: 0 | AG50: 0 | AH50: 0 | AI50: 0 | AJ50: 0 | AK50: 0 | AL50: 0 | AM50: 0 | AN50: 0 | AO50: 0 | AP50: 0 | AQ50: 0 | AR50: 0 | AS50: 0 | AT50: 0 | AU50: 0 | AV50: 0 | AW50: 0 | AX50: 0 | AY50: 0 | AZ50: 0 | BA50: 0 | BB50: 0 | BC50: 0 | BD50: 0 | BE50: 0 | BF50: 0 | BG50: 0 | BH50: 0 | BI50: 0 | BJ50: 0 | BK50: 0 | BL50: 0 | BM50: 0 | BN50: 0 | BO50: 0 | BP50: 0 | BQ50: 0 | BR50: 0 | BS50: 0 | BT50: 0 | BU50: 0 | BV50: 0 | BW50: 0 | BX50: 0 | BY50: 0 | BZ50: 0 | CA50: 0 | CB50: 0 | CC50: 0 | CD50: 0 | CE50: 0 | CF50: 0 | CG50: 0 | CH50: 0 | CI50: 0 | CJ50: 0 | CK50: 0 | CL50: 0 | CM50: 0 | CN50: 0 | CO50: 0 | CP50: 0 | CQ50: 0 | CR50: 0 | CS50: 0 | CT50: 0 | CU50: 0 | CV50: 0 | CW50: 0 | CX50: 0 | CY50: 0 | CZ50: 0
A51: Debt securities1 | B51: 49 | C51: 0 | D51: 0 | E51: 0 | F51: 0 | G51: 0 | H51: 0 | I51: 0 | J51: 0 | K51: 0.021 | L51: 0.021 | M51: 0.021 | N51: 0.021 | O51: 0.021 | P51: 3.495 | Q51: 2.3051 | R51: 1.5038 | S51: 3.9784 | T51: 4.48331 | U51: 4.74831 | V51: 3.7936 | W51: 4.1543 | X51: 3.6796 | Y51: 2.019 | Z51: 1.386 | AA51: 1.594 | AB51: 0.782 | AC51: 0.684 | AD51: 0.475 | AE51: 0.296 | AF51: 0.208 | AG51: 0.113 | AH51: 0.116 | AI51: 0.089 | AJ51: 0.042 | AK51: 0.299 | AL51: 0 | AM51: 0.09 | AN51: 0.09 | AO51: 0.09 | AP51: 0 | AQ51: 0 | AR51: 0 | AS51: 0 | AT51: 0 | AU51: 0 | AV51: 0 | AW51: 0 | AX51: 0 | AY51: 0 | AZ51: 0 | BA51: 0 | BB51: 0 | BC51: 0 | BD51: 0 | BE51: 0 | BF51: 0 | BG51: 0 | BH51: 0 | BI51: 0 | BJ51: 0 | BK51: 0 | BL51: 0 | BM51: 0 | BN51: 0 | BO51: 0 | BP51: 0 | BQ51: 0 | BR51: 0 | BS51: 0 | BT51: 0 | BU51: 0 | BV51: 0 | BW51: 0 | BX51: 0 | BY51: 0 | BZ51: 0 | CA51: 0 | CB51: 0 | CC51: 0 | CD51: 0 | CE51: 0 | CF51: 0 | CG51: 0 | CH51: 0 | CI51: 0 | CJ51: 0 | CK51: 0 | CL51: 0 | CM51: 0 | CN51: 0 | CO51: 0 | CP51: 0 | CQ51: 0 | CR51: 0 | CS51: 0 | CT51: 0 | CU51: 0 | CV51: 0 | CW51: 0 | CX51: 0 | CY51: 0 | CZ51: 0
A52: Loans | B52: 50 | C52: 38.7985 | D52: 39.91441 | E52: 38.22804 | F52: 55.49685 | G52: 36.09045 | H52: 30.08423 | I52: 51.13347 | J52: 66.62974 | K52: 141.05671 | L52: 129.99445 | M52: 126.97777 | N52: 191.96887 | O52: 212.85176 | P52: 261.92745 | Q52: 245.70737 | R52: 151.04366 | S52: 274.95292 | T52: 0 | U52: 0 | V52: 0 | W52: 369.17366 | X52: 565.40184 | Y52: 748.05369 | Z52: 1027.5838 | AA52: 1162.6621 | AB52: 1148.6121 | AC52: 1232.4152 | AD52: 1053.6043 | AE52: 1437.3242 | AF52: 1551.0697 | AG52: 1792.1723 | AH52: 2673.3302 | AI52: 2247.1651 | AJ52: 1574.5407 | AK52: 1457.4436 | AL52: 1723.4321 | AM52: 918.44889 | AN52: 813.15373 | AO52: 857.69448 | AP52: 1475.7076 | AQ52: 1287.7287 | AR52: 1208.8266 | AS52: 1203.8857 | AT52: 1191.4207 | AU52: 1175.7734 | AV52: 800.41251 | AW52: 815.01067 | AX52: 741.97976 | AY52: 869.25555 | AZ52: 999.07628 | BA52: 813.83587 | BB52: 884.89227 | BC52: 901.04149 | BD52: 1128.0907 | BE52: 1174.4633 | BF52: 984.77589 | BG52: 1114.3815 | BH52: 696.51208 | BI52: 820.30732 | BJ52: 560.72948 | BK52: 457.88029 | BL52: 485.0689 | BM52: 515.76792 | BN52: 450.03563 | BO52: 417.1035 | BP52: 387.70092 | BQ52: 406.76271 | BR52: 371.81269 | BS52: 588.14749 | BT52: 473.53857 | BU52: 501.13269 | BV52: 698.90832 | BW52: 616.3208 | BX52: 626.01151 | BY52: 534.27922 | BZ52: 528.94369 | CA52: 522.54847 | CB52: 491.94796 | CC52: 609.99884 | CD52: 471.63869 | CE52: 465.23868 | CF52: 756.7997 | CG52: 774.93569 | CH52: 869.77095 | CI52: 927.90307 | CJ52: 867.90594 | CK52: 1069.3103 | CL52: 1581.6491 | CM52: 1180.0027 | CN52: 1044.8949 | CO52: 1050.1039 | CP52: 1784.5714 | CQ52: 1800.1373 | CR52: 1179.6577 | CS52: 1389.4952 | CT52: 1518.1629 | CU52: 1425.3795 | CV52: 1309.8962 | CW52: 1327.5113 | CX52: 1149.5971 | CY52: 1171.0524 | CZ52: 1199.2699
A53: Trade credit and advances | B53: 51 | C53: 470.50392 | D53: 444.56917 | E53: 584.67315 | F53: 556.75704 | G53: 540.98833 | H53: 529.27716 | I53: 596.87888 | J53: 691.98873 | K53: 771.68793 | L53: 814.40909 | M53: 711.68426 | N53: 909.53828 | O53: 1006.9235 | P53: 966.35206 | Q53: 1037.8623 | R53: 1044.5926 | S53: 1222.3106 | T53: 1229.8057 | U53: 1245.0455 | V53: 1243.8966 | W53: 1259.3509 | X53: 1441.4214 | Y53: 1969.5001 | Z53: 2320.2873 | AA53: 2683.9924 | AB53: 2704.247 | AC53: 3053.0864 | AD53: 3434.9763 | AE53: 3704.2485 | AF53: 3665.5202 | AG53: 3619.6311 | AH53: 4094.9822 | AI53: 4001.825 | AJ53: 3763.711 | AK53: 4336.2829 | AL53: 4102.0631 | AM53: 3788.31 | AN53: 4065.7034 | AO53: 4129.4207 | AP53: 4227.3816 | AQ53: 5305.6492 | AR53: 4330.0825 | AS53: 4527.5219 | AT53: 4923.4452 | AU53: 5455.0606 | AV53: 5578.0654 | AW53: 5875.9119 | AX53: 6090.2437 | AY53: 6307.9021 | AZ53: 5688.727 | BA53: 6283.6057 | BB53: 6994.1769 | BC53: 7218.5781 | BD53: 6629.6469 | BE53: 7160.0269 | BF53: 7099.3158 | BG53: 6808.8308 | BH53: 6403.6631 | BI53: 6065.1482 | BJ53: 4928.916 | BK53: 4837.5203 | BL53: 4736.6386 | BM53: 4805.2227 | BN53: 5043.8819 | BO53: 5202.5349 | BP53: 5260.1955 | BQ53: 5390.1822 | BR53: 5682.4362 | BS53: 5649.1745 | BT53: 5643.3565 | BU53: 5865.9703 | BV53: 6058.2189 | BW53: 6124.2032 | BX53: 5837.7204 | BY53: 6220.9806 | BZ53: 6545.4938 | CA53: 6696.4409 | CB53: 6328.3296 | CC53: 6643.1245 | CD53: 6919.7644 | CE53: 6787.7453 | CF53: 7063.0796 | CG53: 7708.3332 | CH53: 7538.9275 | CI53: 7616.7526 | CJ53: 7533.3039 | CK53: 8773.8029 | CL53: 8871.603 | CM53: 8760.8029 | CN53: 9314.2387 | CO53: 10119.735 | CP53: 10250.589 | CQ53: 10198.302 | CR53: 10148.012 | CS53: 10326.792 | CT53: 10247.51 | CU53: 9880.2401 | CV53: 10748.496 | CW53: 11603.451 | CX53: 11293.077 | CY53: 11037.32 | CZ53: 11567.417
A54: Other debt liabilities | B54: 52 | C54: 183.30999 | D54: 179.72702 | E54: 180.5054 | F54: 131.00456 | G54: 137.84286 | H54: 123.622 | I54: 141.10615 | J54: 101.90499 | K54: 127.80326 | L54: 98.840911 | M54: 163.79735 | N54: 84.001677 | O54: 142.60416 | P54: 57.648661 | Q54: 55.05512 | R54: 57.60716 | S54: 71.47622 | T54: 69.04622 | U54: 57.84754 | V54: 55.14689 | W54: 70.92948 | X54: 46.10908 | Y54: 78.26642 | Z54: 37.41352 | AA54: 56.55309 | AB54: 99.43291 | AC54: 106.30056 | AD54: 147.87155 | AE54: 180.06628 | AF54: 134.37283 | AG54: 135.90707 | AH54: 126.13852 | AI54: 134.10336 | AJ54: 79.125 | AK54: 98.45107 | AL54: 190.76227 | AM54: 152.36546 | AN54: 117.86921 | AO54: 131.71836 | AP54: 116.22524 | AQ54: 178.15876 | AR54: 129.44142 | AS54: 122.38773 | AT54: 118.10596 | AU54: 145.54587 | AV54: 132.96242 | AW54: 149.29288 | AX54: 132.20339 | AY54: 173.40543 | AZ54: 242.63335 | BA54: 253.84256 | BB54: 316.23195 | BC54: 110.15688 | BD54: 162.96926 | BE54: 161.06106 | BF54: 69.24546 | BG54: 106.20013 | BH54: 109.21098 | BI54: 72.8006 | BJ54: 68.13021 | BK54: 102.94407 | BL54: 123.93465 | BM54: 68.82195 | BN54: 304.84737 | BO54: 101.20967 | BP54: 119.22177 | BQ54: 126.271 | BR54: 197.04286 | BS54: 109.23139 | BT54: 68.7657 | BU54: 145.24609 | BV54: 135.36316 | BW54: 108.72752 | BX54: 52.10148 | BY54: 54.39041 | BZ54: 41.21857 | CA54: 59.90172 | CB54: 95.25019 | CC54: 89.00895 | CD54: 48.69923 | CE54: 62.97777 | CF54: 200.38779 | CG54: 305.4921 | CH54: 182.39336 | CI54: 1108.3195 | CJ54: 127.03606 | CK54: 592.18957 | CL54: 657.52171 | CM54: 450.33904 | CN54: 578.74788 | CO54: 632.09051 | CP54: 560.51565 | CQ54: 665.57677 | CR54: 595.33617 | CS54: 717.17066 | CT54: 645.96646 | CU54: 777.95787 | CV54: 1264.072 | CW54: 1205.3267 | CX54: 722.79774 | CY54: 839.06676 | CZ54: 1227.8195
A55: Long-term | B55: 53=54+55+56+57+58= 61+64 | C55: 1604.4521 | D55: 1648.4505 | E55: 1665.8919 | F55: 1905.4586 | G55: 1858.1532 | H55: 2018.0872 | I55: 2074.0199 | J55: 2228.0328 | K55: 2199.065 | L55: 2554.415 | M55: 2714.0981 | N55: 2979.2238 | O55: 3069.8548 | P55: 3109.525 | Q55: 3384.7505 | R55: 3572.7611 | S55: 4294.9286 | T55: 4443.6391 | U55: 5102.4636 | V55: 5687.593 | W55: 5604.1982 | X55: 6075.3915 | Y55: 6803.8661 | Z55: 7183.0493 | AA55: 8700.8737 | AB55: 9497.0195 | AC55: 10756.407 | AD55: 12678.225 | AE55: 13945.86 | AF55: 15570.117 | AG55: 16172.134 | AH55: 17647.502 | AI55: 20476.23 | AJ55: 22188.295 | AK55: 23684.848 | AL55: 24568.348 | AM55: 24949.985 | AN55: 24897.953 | AO55: 25795.058 | AP55: 25952.787 | AQ55: 34427.67 | AR55: 33946.67 | AS55: 34403.447 | AT55: 33952.525 | AU55: 36312.763 | AV55: 37448.076 | AW55: 39748.528 | AX55: 40771.453 | AY55: 42960.481 | AZ55: 44184.96 | BA55: 48911.232 | BB55: 49344.219 | BC55: 50698.885 | BD55: 51156.768 | BE55: 54556.528 | BF55: 50196.734 | BG55: 51543.407 | BH55: 34709.172 | BI55: 34174.868 | BJ55: 33622.385 | BK55: 31159.962 | BL55: 31128.177 | BM55: 33712.968 | BN55: 33729.859 | BO55: 33117.966 | BP55: 34313.83 | BQ55: 36239.857 | BR55: 37058.71 | BS55: 37267.81 | BT55: 37017.336 | BU55: 36371.696 | BV55: 34413.515 | BW55: 32812.427 | BX55: 32504.502 | BY55: 32852.196 | BZ55: 33897.373 | CA55: 33761.656 | CB55: 30489.283 | CC55: 32395.606 | CD55: 33260.918 | CE55: 34072.065 | CF55: 33391.989 | CG55: 33873.373 | CH55: 34317.291 | CI55: 34360.421 | CJ55: 32015.72 | CK55: 33156.208 | CL55: 32641.399 | CM55: 31836.157 | CN55: 32327.623 | CO55: 31966.685 | CP55: 32408.874 | CQ55: 32799.447 | CR55: 33249.15 | CS55: 33465.105 | CT55: 33289.837 | CU55: 33089.14 | CV55: 34887.818 | CW55: 36014.37 | CX55: 37506.177 | CY55: 42015.409 | CZ55: 43329.936
A56: Currency and deposits | B56: 54 | C56: 0 | D56: 0 | E56: 0 | F56: 0 | G56: 0 | H56: 0 | I56: 0 | J56: 0 | K56: 0 | L56: 0 | M56: 0 | N56: 0 | O56: 0 | P56: 0 | Q56: 0 | R56: 0 | S56: 0 | T56: 0 | U56: 0 | V56: 0 | W56: 0 | X56: 0 | Y56: 0 | Z56: 0 | AA56: 0 | AB56: 0 | AC56: 0 | AD56: 0 | AE56: 0 | AF56: 0 | AG56: 0 | AH56: 0 | AI56: 0 | AJ56: 0 | AK56: 0 | AL56: 0 | AM56: 0 | AN56: 0 | AO56: 0 | AP56: 0 | AQ56: 0 | AR56: 0 | AS56: 0 | AT56: 0 | AU56: 0 | AV56: 0 | AW56: 0 | AX56: 0 | AY56: 0 | AZ56: 0 | BA56: 0 | BB56: 0 | BC56: 0 | BD56: 0 | BE56: 0 | BF56: 0 | BG56: 0 | BH56: 0 | BI56: 0 | BJ56: 0 | BK56: 0 | BL56: 0 | BM56: 0 | BN56: 0 | BO56: 0 | BP56: 0 | BQ56: 0 | BR56: 0 | BS56: 0 | BT56: 0 | BU56: 0 | BV56: 0 | BW56: 0 | BX56: 0 | BY56: 0 | BZ56: 0 | CA56: 0 | CB56: 0 | CC56: 0 | CD56: 0 | CE56: 0 | CF56: 0 | CG56: 0 | CH56: 0 | CI56: 0 | CJ56: 0 | CK56: 0 | CL56: 0 | CM56: 0 | CN56: 0 | CO56: 0 | CP56: 0 | CQ56: 0 | CR56: 0 | CS56: 0 | CT56: 0 | CU56: 0 | CV56: 0 | CW56: 0 | CX56: 0 | CY56: 0 | CZ56: 0
A57: Debt securities1 | B57: 55 | C57: 14.76991 | D57: 13.83986 | E57: 16.08565 | F57: 151.94749 | G57: 132.86969 | H57: 128.66951 | I57: 121.04222 | J57: 123.15899 | K57: 98.563269 | L57: 85.144923 | M57: 90.664184 | N57: 96.162978 | O57: 110.0444 | P57: 115.74523 | Q57: 141.47816 | R57: 155.24734 | S57: 147.8394 | T57: 169.40655 | U57: 221.24526 | V57: 244.05967 | W57: 146.813 | X57: 147.19171 | Y57: 148.39786 | Z57: 69.842381 | AA57: 87.811705 | AB57: 257.52477 | AC57: 616.13296 | AD57: 660.74658 | AE57: 669.49105 | AF57: 714.41376 | AG57: 784.95923 | AH57: 685.31094 | AI57: 602.12971 | AJ57: 761.58693 | AK57: 807.13029 | AL57: 805.69825 | AM57: 800.16056 | AN57: 794.40572 | AO57: 1183.4139 | AP57: 1224.3789 | AQ57: 9053.4376 | AR57: 9727.229 | AS57: 9864.0074 | AT57: 9198.8702 | AU57: 10254.434 | AV57: 10769.803 | AW57: 10646.525 | AX57: 11048.281 | AY57: 11130.07 | AZ57: 10744.024 | BA57: 14412.082 | BB57: 13078.366 | BC57: 12975.578 | BD57: 12836.422 | BE57: 15687.125 | BF57: 15429.036 | BG57: 15912.831 | BH57: 14253.002 | BI57: 13572.726 | BJ57: 12974.401 | BK57: 9617.7717 | BL57: 9449.9423 | BM57: 9915.1648 | BN57: 10245.959 | BO57: 9891.5796 | BP57: 10137.453 | BQ57: 12745.1 | BR57: 13120.419 | BS57: 12926.334 | BT57: 12211.317 | BU57: 11791.746 | BV57: 10251.902 | BW57: 10097.812 | BX57: 9859.952 | BY57: 10113.99 | BZ57: 10660.547 | CA57: 9491.1329 | CB57: 8083.0343 | CC57: 9278.3395 | CD57: 10235.876 | CE57: 10540.234 | CF57: 10391.683 | CG57: 10626.348 | CH57: 10467.445 | CI57: 10724.089 | CJ57: 8546.9152 | CK57: 7708.8699 | CL57: 7401.6572 | CM57: 6936.6833 | CN57: 7086.3698 | CO57: 6767.3921 | CP57: 7046.213 | CQ57: 7149.6037 | CR57: 7106.1161 | CS57: 7098.374 | CT57: 6590.6747 | CU57: 6633.6299 | CV57: 7394.6409 | CW57: 7876.8619 | CX57: 8216.3209 | CY57: 8882.392 | CZ57: 9201.8255
A58: Loans | B58: 56 | C58: 1275.6337 | D58: 1295.7617 | E58: 1303.4126 | F58: 1370.7247 | G58: 1370.7124 | H58: 1500.3896 | I58: 1513.6084 | J58: 1612.1393 | K58: 1594.9521 | L58: 1935.1771 | M58: 2054.8922 | N58: 2273.6056 | O58: 2350.9915 | P58: 2362.1833 | Q58: 2506.7791 | R58: 2648.6867 | S58: 3374.6003 | T58: 3446.0727 | U58: 3980.2142 | V58: 4359.33 | W58: 4393.7465 | X58: 4801.156 | Y58: 5468.7154 | Z58: 6002.7362 | AA58: 7380.7377 | AB58: 7912.7233 | AC58: 8824.8598 | AD58: 10530.313 | AE58: 11589.837 | AF58: 13168.681 | AG58: 13693.016 | AH58: 15185.528 | AI58: 18062.353 | AJ58: 19720.847 | AK58: 21211.715 | AL58: 22071.463 | AM58: 22586.184 | AN58: 22584.345 | AO58: 23027.24 | AP58: 23106.048 | AQ58: 23658.195 | AR58: 22411.263 | AS58: 22802.819 | AT58: 23016.142 | AU58: 24336.103 | AV58: 24931.237 | AW58: 27329.155 | AX58: 27879.364 | AY58: 29883.355 | AZ58: 31334.368 | BA58: 32386.778 | BB58: 34056.509 | BC58: 35615.664 | BD58: 36157.15 | BE58: 36594.644 | BF58: 32583.352 | BG58: 33284.914 | BH58: 18023.193 | BI58: 18127.051 | BJ58: 17820.384 | BK58: 18900.845 | BL58: 19058.817 | BM58: 20894.786 | BN58: 20811.022 | BO58: 20939.287 | BP58: 21908.927 | BQ58: 21420.521 | BR58: 22012.667 | BS58: 22258.539 | BT58: 22622.658 | BU58: 22191.235 | BV58: 22078.928 | BW58: 20680.895 | BX58: 20565.19 | BY58: 20672.687 | BZ58: 21189.94 | CA58: 22309.857 | CB58: 20452.928 | CC58: 21043.768 | CD58: 21085.706 | CE58: 21572.192 | CF58: 21153.146 | CG58: 21360.261 | CH58: 21406.655 | CI58: 21261.457 | CJ58: 21000.758 | CK58: 23190.359 | CL58: 22989.382 | CM58: 22803.373 | CN58: 23034.513 | CO58: 23175.488 | CP58: 23384.626 | CQ58: 23823.54 | CR58: 24080.655 | CS58: 24249.831 | CT58: 24616.524 | CU58: 24340.794 | CV58: 25330.246 | CW58: 25811.938 | CX58: 26885.314 | CY58: 30735.049 | CZ58: 31550.005
A59: Trade credit and advances | B59: 57 | C59: 314.04847 | D59: 338.84894 | E59: 346.39367 | F59: 382.78641 | G59: 354.57111 | H59: 389.02809 | I59: 439.36925 | J59: 492.73455 | K59: 505.54962 | L59: 534.093 | M59: 568.54166 | N59: 609.4552 | O59: 608.81888 | P59: 631.59649 | Q59: 736.49328 | R59: 768.82708 | S59: 772.48891 | T59: 828.15989 | U59: 901.00417 | V59: 1084.2033 | W59: 1063.6387 | X59: 1127.0438 | Y59: 1186.7529 | Z59: 1110.4708 | AA59: 1232.3243 | AB59: 1326.7714 | AC59: 1315.4145 | AD59: 1487.1655 | AE59: 1686.5316 | AF59: 1687.0223 | AG59: 1694.1587 | AH59: 1776.6627 | AI59: 1811.7472 | AJ59: 1705.8614 | AK59: 1666.0032 | AL59: 1691.1869 | AM59: 1563.6405 | AN59: 1519.2017 | AO59: 1584.4034 | AP59: 1622.3602 | AQ59: 1716.0376 | AR59: 1808.1778 | AS59: 1736.6202 | AT59: 1737.5134 | AU59: 1722.2257 | AV59: 1747.035 | AW59: 1772.8477 | AX59: 1843.8078 | AY59: 1947.0563 | AZ59: 2043.4399 | BA59: 2025.4688 | BB59: 2115.5146 | BC59: 2019.1523 | BD59: 2060.4326 | BE59: 2151.0677 | BF59: 1999.5174 | BG59: 2159.4824 | BH59: 2225.3463 | BI59: 2133.7926 | BJ59: 2509.8635 | BK59: 2348.8267 | BL59: 2321.3607 | BM59: 2321.6166 | BN59: 2162.8184 | BO59: 1814.7419 | BP59: 1760.1715 | BQ59: 1581.4752 | BR59: 1472.0446 | BS59: 1623.4677 | BT59: 1634.2677 | BU59: 1828.1518 | BV59: 1907.2912 | BW59: 1831.8168 | BX59: 1863.0515 | BY59: 1836.3926 | BZ59: 1825.8739 | CA59: 1749.2132 | CB59: 1686.6967 | CC59: 1783.0203 | CD59: 1664.7976 | CE59: 1689.8664 | CF59: 1547.7555 | CG59: 1520.9872 | CH59: 1952.6454 | CI59: 1894.0453 | CJ59: 1959.8052 | CK59: 1495.4671 | CL59: 1542.3701 | CM59: 1465.4323 | CN59: 1464.0869 | CO59: 1333.4048 | CP59: 1402.7681 | CQ59: 1229.3615 | CR59: 1388.1652 | CS59: 1437.8536 | CT59: 1436.7012 | CU59: 1499.309 | CV59: 1483.1194 | CW59: 1635.706 | CX59: 1730.9236 | CY59: 1668.0258 | CZ59: 1676.8778
A60: Other debt liabilities2 | B60: 58 | C60: 0 | D60: 0 | E60: 0 | F60: 0 | G60: 0 | H60: 0 | I60: 0 | J60: 0 | K60: 0 | L60: 0 | M60: 0 | N60: 0 | O60: 0 | P60: 0 | Q60: 0 | R60: 0 | S60: 0 | T60: 0 | U60: 0 | V60: 0 | W60: 0 | X60: 0 | Y60: 0 | Z60: 0 | AA60: 0 | AB60: 0 | AC60: 0 | AD60: 0 | AE60: 0 | AF60: 0 | AG60: 0 | AH60: 0 | AI60: 0 | AJ60: 0 | AK60: 0 | AL60: 0 | AM60: 0 | AN60: 0 | AO60: 0 | AP60: 0 | AQ60: 0 | AR60: 0 | AS60: 0 | AT60: 0 | AU60: 0 | AV60: 0 | AW60: 0 | AX60: 0 | AY60: 0 | AZ60: 63.12823 | BA60: 86.90316 | BB60: 93.8286 | BC60: 88.48976 | BD60: 102.76324 | BE60: 123.69107 | BF60: 184.82856 | BG60: 186.17951 | BH60: 207.63152 | BI60: 341.29802 | BJ60: 317.73758 | BK60: 292.51797 | BL60: 298.0571 | BM60: 581.40082 | BN60: 510.05969 | BO60: 472.35741 | BP60: 507.27767 | BQ60: 492.76088 | BR60: 453.57983 | BS60: 459.46877 | BT60: 549.09255 | BU60: 560.5624 | BV60: 175.39389 | BW60: 201.90392 | BX60: 216.30842 | BY60: 229.1257 | BZ60: 221.01205 | CA60: 211.45265 | CB60: 266.62392 | CC60: 290.47747 | CD60: 274.53812 | CE60: 269.77208 | CF60: 299.40428 | CG60: 365.77693 | CH60: 490.54606 | CI60: 480.82999 | CJ60: 508.24125 | CK60: 761.51186 | CL60: 707.98971 | CM60: 630.66817 | CN60: 742.65289 | CO60: 690.40019 | CP60: 575.26672 | CQ60: 596.94187 | CR60: 674.21331 | CS60: 679.04682 | CT60: 645.93718 | CU60: 615.4073 | CV60: 679.81181 | CW60: 689.86402 | CX60: 673.61872 | CY60: 729.94157 | CZ60: 901.22785
A61: Other financial corporations | B61: 59=60+61 | T61: 246.19093 | U61: 263.97274 | V61: 288.66654 | W61: 239.35511 | X61: 415.64351 | Y61: 515.40805 | Z61: 702.8834 | AA61: 1049.0014 | AB61: 1428.3426 | AC61: 2012.103 | AD61: 2250.059 | AE61: 2762.23 | AF61: 2769.3351 | AG61: 2992.4711 | AH61: 2708.6161 | AI61: 2056.9581 | AJ61: 1945.2347 | AK61: 1995.4286 | AL61: 2016.1781 | AM61: 1970.8968 | AN61: 1897.8502 | AO61: 1871.0818 | AP61: 1938.2714 | AQ61: 1910.4732 | AR61: 1997.3135 | AS61: 1989.6353 | AT61: 1992.7121 | AU61: 2133.8976 | AV61: 2123.1607 | AW61: 2105.6813 | AX61: 2106.2689 | AY61: 1982.1845 | AZ61: 1919.546 | BA61: 2835.9038 | BB61: 2854.4375 | BC61: 2897.205 | BD61: 2913.7038 | BE61: 3866.8002 | BF61: 3767.0216 | BG61: 3464.1606 | BH61: 3317.526 | BI61: 2588.67 | BJ61: 2440.0139 | BK61: 2611.699 | BL61: 2587.7258 | BM61: 2671.0655 | BN61: 2922.0815 | BO61: 2636.3121 | BP61: 2777.9732 | BQ61: 2780.0155 | BR61: 2890.8401 | BS61: 2816.0503 | BT61: 2908.2719 | BU61: 2902.7882 | BV61: 2394.198 | BW61: 2211.2275 | BX61: 1373.069 | BY61: 1345.8521 | BZ61: 1231.8438 | CA61: 1443.8623 | CB61: 1223.7173 | CC61: 1296.3462 | CD61: 1202.0482 | CE61: 1247.1945 | CF61: 1350.9891 | CG61: 1381.8 | CH61: 1349.1495 | CI61: 2498.5096 | CJ61: 1537.128 | CK61: 2170.3858 | CL61: 2852.0945 | CM61: 1861.4743 | CN61: 1935.4733 | CO61: 2191.3355 | CP61: 2348.5727 | CQ61: 2886.7298 | CR61: 3206.1836 | CS61: 3356.8806 | CT61: 3247.3572 | CU61: 3586.2017 | CV61: 4967.6201 | CW61: 5487.881 | CX61: 4840.335 | CY61: 6625.723 | CZ61: 8100.362
A62: Short-term | B62: 60 | T62: 62.02754 | U62: 65.40642 | V62: 65.24553 | W62: 83.32429 | X62: 94.28618 | Y62: 102.72515 | Z62: 100.98829 | AA62: 59.93689 | AB62: 164.1968 | AC62: 211.65541 | AD62: 256.15047 | AE62: 165.87899 | AF62: 125.70998 | AG62: 128.38672 | AH62: 129.63065 | AI62: 36.01087 | AJ62: 45.13263 | AK62: 72.85518 | AL62: 45.42804 | AM62: 53.5534 | AN62: 70.10051 | AO62: 78.80493 | AP62: 107.41051 | AQ62: 107.04519 | AR62: 152.08876 | AS62: 144.98324 | AT62: 90.30773 | AU62: 100.70682 | AV62: 109.97901 | AW62: 111.79245 | AX62: 96.99021 | AY62: 90.63624 | AZ62: 113.2853 | BA62: 125.99152 | BB62: 138.15945 | BC62: 115.56549 | BD62: 121.6325 | BE62: 131.67379 | BF62: 99.08746 | BG62: 68.07842 | BH62: 78.95588 | BI62: 170.33955 | BJ62: 82.169 | BK62: 57.34578 | BL62: 89.04746 | BM62: 97.05668 | BN62: 314.23979 | BO62: 76.62947 | BP62: 83.2158 | BQ62: 90.60717 | BR62: 166.57793 | BS62: 70.02536 | BT62: 72.24364 | BU62: 117.22506 | BV62: 110.49135 | BW62: 64.57497 | BX62: 48.72345 | BY62: 157.72703 | BZ62: 63.27027 | CA62: 80.17916 | CB62: 112.1005 | CC62: 116.08633 | CD62: 60.19067 | CE62: 38.16448 | CF62: 96.84093 | CG62: 116.33014 | CH62: 114.66178 | CI62: 1135.7739 | CJ62: 162.99244 | CK62: 617.74328 | CL62: 1341.8826 | CM62: 404.0027 | CN62: 200.51247 | CO62: 320.61013 | CP62: 186.33028 | CQ62: 399.396 | CR62: 409.57878 | CS62: 473.73519 | CT62: 481.95315 | CU62: 505.1395 | CV62: 879.03368 | CW62: 817.75529 | CX62: 351.1704 | CY62: 711.35544 | CZ62: 1313.1157
A63: Long-term | B63: 61 | T63: 184.16339 | U63: 198.56632 | V63: 223.42101 | W63: 156.03082 | X63: 321.35733 | Y63: 412.6829 | Z63: 601.89511 | AA63: 989.06447 | AB63: 1264.1458 | AC63: 1800.4476 | AD63: 1993.9085 | AE63: 2596.351 | AF63: 2643.6251 | AG63: 2864.0844 | AH63: 2578.9854 | AI63: 2020.9473 | AJ63: 1900.102 | AK63: 1922.5734 | AL63: 1970.7501 | AM63: 1917.3434 | AN63: 1827.7497 | AO63: 1792.2769 | AP63: 1830.8609 | AQ63: 1803.428 | AR63: 1845.2247 | AS63: 1844.652 | AT63: 1902.4043 | AU63: 2033.1908 | AV63: 2013.1817 | AW63: 1993.8888 | AX63: 2009.2787 | AY63: 1891.5483 | AZ63: 1806.2607 | BA63: 2709.9123 | BB63: 2716.278 | BC63: 2781.6395 | BD63: 2792.0713 | BE63: 3735.1264 | BF63: 3667.9342 | BG63: 3396.0822 | BH63: 3238.5702 | BI63: 2418.3305 | BJ63: 2357.8449 | BK63: 2554.3532 | BL63: 2498.6784 | BM63: 2574.0089 | BN63: 2607.8417 | BO63: 2559.6826 | BP63: 2694.7574 | BQ63: 2689.4084 | BR63: 2724.2622 | BS63: 2746.0249 | BT63: 2836.0283 | BU63: 2785.5631 | BV63: 2283.7066 | BW63: 2146.6526 | BX63: 1324.3455 | BY63: 1188.1251 | BZ63: 1168.5735 | CA63: 1363.6831 | CB63: 1111.6168 | CC63: 1180.2599 | CD63: 1141.8576 | CE63: 1209.03 | CF63: 1254.1482 | CG63: 1265.4699 | CH63: 1234.4877 | CI63: 1362.7357 | CJ63: 1374.1355 | CK63: 1552.6426 | CL63: 1510.2119 | CM63: 1457.4716 | CN63: 1734.9608 | CO63: 1870.7253 | CP63: 2162.2424 | CQ63: 2487.3338 | CR63: 2796.6049 | CS63: 2883.1454 | CT63: 2765.4041 | CU63: 3081.0622 | CV63: 4088.5864 | CW63: 4670.1258 | CX63: 4489.1646 | CY63: 5914.3676 | CZ63: 6787.2462
A64: Nonfinancial corporations, households, and NPISHs | B64: 62=63+64 | T64: 5824.3126 | U64: 6419.8777 | V64: 7033.4499 | W64: 7068.4515 | X64: 7716.3599 | Y64: 9086.2973 | Z64: 9866.8365 | AA64: 11556.674 | AB64: 12021.751 | AC64: 13136.79 | AD64: 15065.093 | AE64: 16505.565 | AF64: 18151.953 | AG64: 18727.486 | AH64: 21833.453 | AI64: 24802.455 | AJ64: 25660.48 | AK64: 27581.896 | AL64: 28568.428 | AM64: 27838.302 | AN64: 27996.919 | AO64: 29042.899 | AP64: 29833.83 | AQ64: 39288.734 | AR64: 37617.707 | AS64: 38267.607 | AT64: 38192.785 | AU64: 40955.245 | AV64: 41836.355 | AW64: 44483.062 | AX64: 45629.611 | AY64: 48328.86 | AZ64: 49195.85 | BA64: 53426.612 | BB64: 54685.083 | BC64: 56031.456 | BD64: 56163.771 | BE64: 59185.28 | BF64: 54583.05 | BG64: 56108.659 | BH64: 38601.033 | BI64: 38544.454 | BJ64: 36740.147 | BK64: 33946.607 | BL64: 33886.093 | BM64: 36431.715 | BN64: 36606.543 | BO64: 36202.502 | BP64: 37302.975 | BQ64: 39383.057 | BR64: 40419.161 | BS64: 40798.313 | BT64: 40294.724 | BU64: 39981.257 | BV64: 38911.807 | BW64: 37450.451 | BX64: 37647.266 | BY64: 38315.994 | BZ64: 39781.186 | CA64: 39596.684 | CB64: 36181.093 | CC64: 38441.392 | CD64: 39498.972 | CE64: 40140.833 | CF64: 40061.267 | CG64: 41280.334 | CH64: 41559.234 | CI64: 41514.887 | CJ64: 39006.837 | CK64: 41421.125 | CL64: 40900.079 | CM64: 40365.828 | CN64: 41330.031 | CO64: 41577.279 | CP64: 42655.977 | CQ64: 42576.733 | CR64: 41965.972 | CS64: 42541.683 | CT64: 42454.119 | CU64: 41586.516 | CV64: 43242.662 | CW64: 44662.779 | CX64: 45831.314 | CY64: 48437.124 | CZ64: 49224.08
A65: Short-term | B65: 63 | T65: 1564.8369 | U65: 1515.9805 | V65: 1569.2779 | W65: 1620.284 | X65: 1962.3257 | Y65: 2695.1141 | Z65: 3285.6823 | AA65: 3844.8648 | AB65: 3788.8773 | AC65: 4180.8308 | AD65: 4380.7767 | AE65: 5156.056 | AF65: 5225.4608 | AG65: 5419.4368 | AH65: 6764.9363 | AI65: 6347.1716 | AJ65: 5372.2861 | AK65: 5819.6215 | AL65: 5970.8294 | AM65: 4805.6609 | AN65: 4926.7158 | AO65: 5040.1186 | AP65: 5711.9039 | AQ65: 6664.4915 | AR65: 5516.2618 | AS65: 5708.812 | AT65: 6142.6641 | AU65: 6675.673 | AV65: 6401.4613 | AW65: 6728.423 | AX65: 6867.4366 | AY65: 7259.9269 | AZ65: 6817.1513 | BA65: 7225.2927 | BB65: 8057.1417 | BC65: 8114.211 | BD65: 7799.0744 | BE65: 8363.8775 | BF65: 8054.2497 | BG65: 7961.3341 | BH65: 7130.4303 | BI65: 6787.9166 | BJ65: 5475.6066 | BK65: 5340.9989 | BL65: 5256.5947 | BM65: 5292.7559 | BN65: 5484.5251 | BO65: 5644.2186 | BP65: 5683.9024 | BQ65: 5832.6088 | BR65: 6084.7138 | BS65: 6276.5281 | BT65: 6113.4172 | BU65: 6395.124 | BV65: 6781.999 | BW65: 6784.6766 | BX65: 6467.1099 | BY65: 6651.9232 | BZ65: 7052.3858 | CA65: 7198.7119 | CB65: 6803.4272 | CC65: 7226.046 | CD65: 7379.9117 | CE65: 7277.7973 | CF65: 7923.4261 | CG65: 8672.4308 | CH65: 8476.43 | CI65: 8517.2013 | CJ65: 8365.2535 | CK65: 9817.5595 | CL65: 9768.8912 | CM65: 9987.1419 | CN65: 10737.369 | CO65: 11481.319 | CP65: 12409.346 | CQ65: 12264.62 | CR65: 11513.427 | CS65: 11959.723 | CT65: 11929.686 | CU65: 11578.438 | CV65: 12443.43 | CW65: 13318.534 | CX65: 12814.301 | CY65: 12336.083 | CZ65: 12681.39
A66: Long-term | B66: 64 | T66: 4259.4757 | U66: 4903.8973 | V66: 5464.172 | W66: 5448.1674 | X66: 5754.0342 | Y66: 6391.1832 | Z66: 6581.1542 | AA66: 7711.8092 | AB66: 8232.8737 | AC66: 8955.9597 | AD66: 10684.317 | AE66: 11349.509 | AF66: 12926.492 | AG66: 13308.05 | AH66: 15068.517 | AI66: 18455.283 | AJ66: 20288.193 | AK66: 21762.275 | AL66: 22597.598 | AM66: 23032.641 | AN66: 23070.203 | AO66: 24002.781 | AP66: 24121.927 | AQ66: 32624.242 | AR66: 32101.445 | AS66: 32558.794 | AT66: 32050.121 | AU66: 34279.572 | AV66: 35434.894 | AW66: 37754.639 | AX66: 38762.175 | AY66: 41068.933 | AZ66: 42378.699 | BA66: 46201.32 | BB66: 46627.941 | BC66: 47917.245 | BD66: 48364.696 | BE66: 50821.402 | BF66: 46528.8 | BG66: 48147.325 | BH66: 31470.602 | BI66: 31756.538 | BJ66: 31264.54 | BK66: 28605.608 | BL66: 28629.499 | BM66: 31138.959 | BN66: 31122.018 | BO66: 30558.283 | BP66: 31619.072 | BQ66: 33550.449 | BR66: 34334.448 | BS66: 34521.785 | BT66: 34181.307 | BU66: 33586.133 | BV66: 32129.808 | BW66: 30665.775 | BX66: 31180.156 | BY66: 31664.071 | BZ66: 32728.8 | CA66: 32397.973 | CB66: 29377.666 | CC66: 31215.346 | CD66: 32119.06 | CE66: 32863.035 | CF66: 32137.841 | CG66: 32607.903 | CH66: 33082.804 | CI66: 32997.685 | CJ66: 30641.584 | CK66: 31603.566 | CL66: 31131.188 | CM66: 30378.686 | CN66: 30592.662 | CO66: 30095.959 | CP66: 30246.631 | CQ66: 30312.113 | CR66: 30452.545 | CS66: 30581.96 | CT66: 30524.433 | CU66: 30008.078 | CV66: 30799.232 | CW66: 31344.245 | CX66: 33017.013 | CY66: 36101.041 | CZ66: 36542.69
A67: Direct investment: Intercompany lending | B67: 65=66+67+68 | C67: 7086.9024 | D67: 7500.9893 | E67: 7802.1439 | F67: 8257.8496 | G67: 8879.2937 | H67: 9313.1171 | I67: 9710.0523 | J67: 10198.12 | K67: 10709.685 | L67: 10841.9 | M67: 11362.399 | N67: 11829.037 | O67: 11983.002 | P67: 12690.202 | Q67: 13086.608 | R67: 13602.334 | S67: 16674.975 | T67: 17190.766 | U67: 17141.24 | V67: 18181.588 | W67: 19221.957 | X67: 21081.356 | Y67: 22327.755 | Z67: 24169.677 | AA67: 25513.032 | AB67: 26511.547 | AC67: 26746.358 | AD67: 28639.176 | AE67: 30080.622 | AF67: 31178.995 | AG67: 32845.963 | AH67: 38215.517 | AI67: 40198.758 | AJ67: 41517.286 | AK67: 43118.882 | AL67: 47309.65 | AM67: 49632.022 | AN67: 51168.981 | AO67: 54549.949 | AP67: 56519.019 | AQ67: 52274.742 | AR67: 56585.923 | AS67: 59296.105 | AT67: 62146.419 | AU67: 62576.197 | AV67: 65277.908 | AW67: 66536.086 | AX67: 67614.35 | AY67: 67608.264 | AZ67: 70545.576 | BA67: 72373.955 | BB67: 73557.035 | BC67: 74179.492 | BD67: 75919.273 | BE67: 76001.01 | BF67: 80794.159 | BG67: 79134.829 | BH67: 94988.09 | BI67: 96696.497 | BJ67: 96333.649 | BK67: 96263.51 | BL67: 96934.586 | BM67: 99503.703 | BN67: 104320.1 | BO67: 104688.04 | BP67: 105258.9 | BQ67: 106200.14 | BR67: 106065.71 | BS67: 104372.69 | BT67: 105581.73 | BU67: 104849.32 | BV67: 104161.65 | BW67: 102592.4 | BX67: 103542.37 | BY67: 102971.31 | BZ67: 101297.74 | CA67: 100376.84 | CB67: 101034.47 | CC67: 103119.57 | CD67: 102851.39 | CE67: 102540.21 | CF67: 101256.51 | CG67: 100449.03 | CH67: 98130.269 | CI67: 96228.768 | CJ67: 94454.938 | CK67: 94387.507 | CL67: 94354.967 | CM67: 93679.757 | CN67: 93856.738 | CO67: 94120.143 | CP67: 93465.905 | CQ67: 93003.766 | CR67: 92928.724 | CS67: 93712.199 | CT67: 92076.267 | CU67: 91140.924 | CV67: 92518.09 | CW67: 92080.777 | CX67: 88707.794 | CY67: 89897.376 | CZ67: 87378.377
A68: Debt liabilities of direct investment enterprises to direct investors | B68: 66 | C68: 7086.9024 | D68: 7450.6573 | E68: 7749.8949 | F68: 8207.4466 | G68: 8826.9847 | H68: 9262.6611 | I68: 9657.7003 | J68: 10147.606 | K68: 10657.239 | L68: 10791.339 | M68: 11184.913 | N68: 11653.492 | O68: 11805.592 | P68: 12514.618 | Q68: 12905.931 | R68: 13329.278 | S68: 14973.269 | T68: 15475.979 | U68: 15445.033 | V68: 16170.609 | W68: 17174.956 | X68: 18989.428 | Y68: 19851.332 | Z68: 20852.883 | AA68: 22229.5 | AB68: 23194.41 | AC68: 24271.755 | AD68: 26142.277 | AE68: 27621.868 | AF68: 28751.262 | AG68: 30244.094 | AH68: 32535.564 | AI68: 34861.117 | AJ68: 36175.393 | AK68: 37960.014 | AL68: 40531.386 | AM68: 42988.378 | AN68: 44498.074 | AO68: 46462.958 | AP68: 48378.52 | AQ68: 49721.773 | AR68: 53155.139 | AS68: 56441.396 | AT68: 58299.469 | AU68: 59589.394 | AV68: 62297.375 | AW68: 63411.832 | AX68: 63904.21 | AY68: 63632.576 | AZ68: 66712.773 | BA68: 68157.937 | BB68: 69431.786 | BC68: 69896.542 | BD68: 71644.395 | BE68: 72688.446 | BF68: 73431.653 | BG68: 72220.206 | BH68: 73229.03 | BI68: 74552.913 | BJ68: 75396.223 | BK68: 75992.368 | BL68: 77015.421 | BM68: 76884.444 | BN68: 77802.272 | BO68: 78026.665 | BP68: 79034.063 | BQ68: 80260.836 | BR68: 81568.643 | BS68: 80428.169 | BT68: 81493.468 | BU68: 81373.993 | BV68: 81668.214 | BW68: 81391.235 | BX68: 82596.362 | BY68: 83525.801 | BZ68: 83154.027 | CA68: 82230.497 | CB68: 82204.191 | CC68: 83082.659 | CD68: 82671.634 | CE68: 82432.915 | CF68: 82120.773 | CG68: 81713.047 | CH68: 80866.937 | CI68: 79283.933 | CJ68: 77986.639 | CK68: 77978.84 | CL68: 78328.886 | CM68: 78093.522 | CN68: 78874.572 | CO68: 79385.538 | CP68: 79037.058 | CQ68: 78463.319 | CR68: 78594.466 | CS68: 78995.966 | CT68: 77943.195 | CU68: 76986.6 | CV68: 78712.615 | CW68: 77992.466 | CX68: 76958.581 | CY68: 76971.283 | CZ68: 77586.094
A69: Debt liabilities of direct investors to direct investment enterprises (reverse investment) | B69: 67 | C69: 0 | D69: 50.332 | E69: 52.249 | F69: 50.403 | G69: 52.309 | H69: 50.456 | I69: 52.352 | J69: 50.514 | K69: 52.446 | L69: 50.5609 | M69: 177.4859 | N69: 175.5457 | O69: 177.4102 | P69: 175.584 | Q69: 180.67695 | R69: 273.05655 | S69: 1701.7051 | T69: 1714.7879 | U69: 1696.2071 | V69: 2010.9788 | W69: 2047.0012 | X69: 2091.9279 | Y69: 2476.4229 | Z69: 3316.7938 | AA69: 3283.5315 | AB69: 3317.1372 | AC69: 2474.6037 | AD69: 2496.899 | AE69: 2458.7533 | AF69: 2427.7327 | AG69: 2601.8682 | AH69: 5679.9522 | AI69: 5337.641 | AJ69: 5341.8932 | AK69: 5158.8672 | AL69: 6778.2637 | AM69: 6643.644 | AN69: 6670.9062 | AO69: 8086.9905 | AP69: 8140.4985 | AQ69: 2552.9699 | AR69: 2060.3087 | AS69: 1741.9829 | AT69: 2722.7682 | AU69: 2597.7677 | AV69: 2604.2168 | AW69: 2742.6347 | AX69: 3328.1153 | AY69: 3429.1865 | AZ69: 3443.6913 | BA69: 3547.4162 | BB69: 3230.6671 | BC69: 3392.2069 | BD69: 3376.7536 | BE69: 2265.1118 | BF69: 2074.8155 | BG69: 1536.3951 | BH69: 1425.981 | BI69: 1448.1732 | BJ69: 1139.5294 | BK69: 932.65412 | BL69: 738.38237 | BM69: 2959.0191 | BN69: 7029.7773 | BO69: 7063.8651 | BP69: 7134.3057 | BQ69: 6830.819 | BR69: 6555.3055 | BS69: 6687.7281 | BT69: 7084.6051 | BU69: 7130.7105 | BV69: 6742.6162 | BW69: 6571.8942 | BX69: 6852.8459 | BY69: 6766.1302 | BZ69: 6796.2114 | CA69: 6961.7495 | CB69: 7710.7829 | CC69: 9167.4561 | CD69: 9915.6121 | CE69: 10014.558 | CF69: 9870.6296 | CG69: 9994.2748 | CH69: 9241.6966 | CI69: 9275.0195 | CJ69: 9255.8225 | CK69: 9789.0547 | CL69: 9706.3809 | CM69: 9881.6124 | CN69: 10041.744 | CO69: 10135.693 | CP69: 10038.742 | CQ69: 10195.545 | CR69: 10172.142 | CS69: 10317.586 | CT69: 10166.197 | CU69: 10297.809 | CV69: 10193.958 | CW69: 10327.972 | CX69: 8175.2473 | CY69: 8313.663 | CZ69: 6815.3488
A70: Debt liabilities between fellow enterprises | B70: 68 | AR70: 1370.4756 | AS70: 1112.7263 | AT70: 1124.1819 | AU70: 389.03566 | AV70: 376.31616 | AW70: 381.61906 | AX70: 382.02446 | AY70: 546.50203 | AZ70: 389.11097 | BA70: 668.60226 | BB70: 894.58175 | BC70: 890.74268 | BD70: 898.12402 | BE70: 1047.4514 | BF70: 5287.6907 | BG70: 5378.2289 | BH70: 20333.079 | BI70: 20695.411 | BJ70: 19797.897 | BK70: 19338.488 | BL70: 19180.783 | BM70: 19660.24 | BN70: 19488.052 | BO70: 19597.513 | BP70: 19090.534 | BQ70: 19108.482 | BR70: 17941.758 | BS70: 17256.791 | BT70: 17003.658 | BU70: 16344.62 | BV70: 15750.817 | BW70: 14629.272 | BX70: 14093.164 | BY70: 12679.38 | BZ70: 11347.502 | CA70: 11184.596 | CB70: 11119.5 | CC70: 10869.457 | CD70: 10264.14 | CE70: 10092.736 | CF70: 9265.1061 | CG70: 8741.7105 | CH70: 8021.6347 | CI70: 7669.8156 | CJ70: 7212.4768 | CK70: 6619.6119 | CL70: 6319.7007 | CM70: 5704.6226 | CN70: 4940.4216 | CO70: 4598.9121 | CP70: 4390.1055 | CQ70: 4344.9017 | CR70: 4162.1154 | CS70: 4398.6461 | CT70: 3966.875 | CU70: 3856.5143 | CV70: 3611.5169 | CW70: 3760.3393 | CX70: 3573.9653 | CY70: 4612.4298 | CZ70: 2976.9341
A71: Memorandum Items
A72: Government guaranteed external debt | B72: 69 | C72: 644.255 | D72: 639.505 | E72: 603.451 | F72: 580.557 | G72: 537.769 | H72: 610.692 | I72: 538.184 | J72: 541.381 | K72: 536.938 | L72: 535.483 | M72: 543.756 | N72: 575.598 | O72: 549.409 | P72: 549.441 | Q72: 565.052 | R72: 610.478 | S72: 633.278 | T72: 634.994 | U72: 626.07231 | V72: 654.386 | W72: 592.54464 | X72: 603.596 | Y72: 595.053 | Z72: 598.983 | AA72: 552.643 | AB72: 565.162 | AC72: 531.604 | AD72: 520.851 | AE72: 500.558 | AF72: 524.303 | AG72: 481.476 | AH72: 482.898 | AI72: 513.011 | AJ72: 505.382 | AK72: 494.688 | AL72: 515.61 | AM72: 486.244 | AN72: 491.516 | AO72: 322.098 | AP72: 321.422 | AQ72: 310.478 | AR72: 307.703 | AS72: 306.25 | AT72: 300.6978 | AU72: 441.997 | AV72: 446.723 | AW72: 466.434 | AX72: 469.642 | AY72: 470.56228 | AZ72: 471.701 | BA72: 469.006 | BB72: 482.53142 | BC72: 495.15337 | BD72: 443.00593 | BE72: 432.24157 | BF72: 428.178 | BG72: 416.327 | BH72: 529.974 | BI72: 518.607 | BJ72: 475.718 | BK72: 665.695 | BL72: 663.301 | BM72: 651.808 | BN72: 581.369 | BO72: 828.339 | BP72: 823.512 | BQ72: 716.032 | BR72: 942.301 | BS72: 1314.137 | BT72: 1319.72 | BU72: 1506.993 | BV72: 1548.293 | BW72: 1590.173 | BX72: 1591.288 | BY72: 1745.954 | BZ72: 1417.947 | CA72: 1564.101 | CB72: 1537.684 | CC72: 1598.84 | CD72: 1656.123 | CE72: 1636.032 | CF72: 1679.382 | CG72: 1737.289 | CH72: 1897.687 | CI72: 2260.3406 | CJ72: 2254.786 | CK72: 2512.16 | CL72: 2403.851 | CM72: 2365.699 | CN72: 2414.534 | CO72: 2488.337 | CP72: 2444.3745 | CQ72: 2772.8296 | CR72: 2786.0046 | CS72: 2916.5221 | CT72: 2917.3364 | CU72: 2973.9116 | CV72: 3115.2111 | CW72: 3194.2826 | CX72: 3185.6496 | CY72: 3283.5105 | CZ72: 3260.2552
A73: Debt securities (nominal value) | B73: 70=71+72+73+74 | X73: 2184.4771 | Y73: 2398.4293 | Z73: 2431.9839 | AA73: 3568.9895 | AB73: 4636.5275 | AC73: 6579.9657 | AD73: 4429.308 | AE73: 3389.3227 | AF73: 3306.0929 | AG73: 3120.0145 | AH73: 3295.0838 | AI73: 2871.4159 | AJ73: 2568.1991 | AK73: 3680.8083 | AL73: 3623.0593 | AM73: 3785.6947 | AN73: 8344.6119 | AO73: 7831.3533 | AP73: 11181.972 | AQ73: 19199.82 | AR73: 22135.552 | AS73: 22172.475 | AT73: 20017 | AU73: 19247.969 | AV73: 18890.418 | AW73: 23662.77 | AX73: 23390.601 | AY73: 16297.684 | AZ73: 16603.518 | BA73: 20390.467 | BB73: 18901.961 | BC73: 18595.964 | BD73: 18268.138 | BE73: 20398.197 | BF73: 20250.191 | BG73: 23524.059 | BH73: 21956.507 | BI73: 20749.525 | BJ73: 24034.292 | BK73: 19839.813 | BL73: 18900.327 | BM73: 18756.389 | BN73: 18383.199 | BO73: 17723.986 | BP73: 17606.553 | BQ73: 19691.255 | BR73: 20206.82 | BS73: 19962.059 | BT73: 20315.941 | BU73: 19414.181 | BV73: 16994.336 | BW73: 18109.862 | BX73: 17295.172 | BY73: 16996.125 | BZ73: 18150.582 | CA73: 17217.272 | CB73: 17528.055 | CC73: 17187.026 | CD73: 17517.97 | CE73: 18351.172 | CF73: 18663.578 | CG73: 19992.381 | CH73: 20083.358 | CI73: 20053.926 | CJ73: 19035.542 | CK73: 18838.874 | CL73: 17982.524 | CM73: 16885.943 | CN73: 16073.877 | CO73: 15456.986 | CP73: 15722.412 | CQ73: 14123.067 | CR73: 13893.083 | CS73: 14026.084 | CT73: 13772.648 | CU73: 14467.137 | CV73: 16000.502 | CW73: 16831.022 | CX73: 18370.995 | CY73: 22732.64 | CZ73: 24076.286
A74: General Government | B74: 71 | X74: 46.529355 | Y74: 30.789529 | Z74: 35.427261 | AA74: 52.813501 | AB74: 116.61602 | AC74: 68.750061 | AD74: 93.575008 | AE74: 60.305237 | AF74: 54.272434 | AG74: 72.358075 | AH74: 101.01746 | AI74: 23.758383 | AJ74: 0.04002642 | AK74: 0.040276577 | AL74: 0.053381915 | AM74: 0.020275007 | AN74: 0.020447284 | AO74: 13.583399 | AP74: 41.198712 | AQ74: 49.128928 | AR74: 57.597732 | AS74: 176.45676 | AT74: 194.20835 | AU74: 31.620369 | AV74: 38.967133 | AW74: 21.20144 | AX74: 21.126852 | AY74: 14.082394 | AZ74: 14.073058 | BA74: 13.997626 | BB74: 13.818123 | BC74: 14.670562 | BD74: 0.67423643 | BE74: 0.66880449 | BF74: 0.67476086 | BG74: 2003.4131 | BH74: 2027.1511 | BI74: 1924.6672 | BJ74: 5362.9411 | BK74: 5248.7927 | BL74: 5040.8307 | BM74: 4965.6116 | BN74: 4662.8119 | BO74: 4347.299 | BP74: 4403.534 | BQ74: 4370.2174 | BR74: 4453.2873 | BS74: 4101.5605 | BT74: 3558.5729 | BU74: 3295.2118 | BV74: 3235.7762 | BW74: 4228.5277 | BX74: 4304.7438 | BY74: 4428.0313 | BZ74: 5480.7675 | CA74: 5148.4011 | CB74: 5044.9876 | CC74: 5084.813 | CD74: 5704.8655 | CE74: 5919.361 | CF74: 6242.7381 | CG74: 7250.1197 | CH74: 7599.8207 | CI74: 7578.601 | CJ74: 7065.412 | CK74: 7370.1159 | CL74: 6658.5553 | CM74: 6392.137 | CN74: 6209.4144 | CO74: 6088.8199 | CP74: 6321.591 | CQ74: 5231.7272 | CR74: 4987.3396 | CS74: 4810.4707 | CT74: 5487.7094 | CU74: 5725.758 | CV74: 5694.9942 | CW74: 5785.7214 | CX74: 7507.3305 | CY74: 9593.7507 | CZ74: 10440.974
A75: Central Bank | B75: 72 | X75: 240.4823 | Y75: 91.85036 | Z75: 190.16858 | AA75: 1072.9653 | AB75: 2077.9874 | AC75: 3141.7294 | AD75: 932.31864 | AE75: 104.77186 | AF75: 104.86823 | AG75: 30.260612 | AH75: 34.550747 | AI75: 9.9522293 | AJ75: 0 | AK75: 4.6785159 | AL75: 0 | AM75: 376.13075 | AN75: 741.19957 | AO75: 467.57218 | AP75: 85.41064 | AQ75: 230.89384 | AR75: 2524.6494 | AS75: 1857.6193 | AT75: 131.11965 | AU75: 19.845013 | AV75: 0 | AW75: 0 | AX75: 0 | AY75: 0 | AZ75: 0 | BA75: 1.3188262 | BB75: 0 | BC75: 0 | BD75: 0 | BE75: 0 | BF75: 0 | BG75: 0 | BH75: 0 | BI75: 0 | BJ75: 0 | BK75: 0 | BL75: 0 | BM75: 61.66727 | BN75: 125.59039 | BO75: 226.08656 | BP75: 621.85432 | BQ75: 585.82202 | BR75: 356.65663 | BS75: 420.08293 | BT75: 1425.9637 | BU75: 706.1747 | BV75: 285.09276 | BW75: 278.12892 | BX75: 451.9193 | BY75: 274.7344 | BZ75: 156.65424 | CA75: 415.04871 | CB75: 485.18575 | CC75: 348.55781 | CD75: 312.92527 | CE75: 834.50489 | CF75: 1349.5925 | CG75: 1152.2692 | CH75: 989.43555 | CI75: 489.34928 | CJ75: 246.64749 | CK75: 256.75935 | CL75: 167.81691 | CM75: 216.21608 | CN75: 242.07239 | CO75: 103.00459 | CP75: 169.30259 | CQ75: 22.974046 | CR75: 146.77767 | CS75: 0 | CT75: 125.59222 | CU75: 199.25119 | CV75: 178.12551 | CW75: 6.1629211 | CX75: 0 | CY75: 296.7183 | CZ75: 260.75903
A76: Banks | B76: 73 | X76: 1754.0012 | Y76: 2128.8514 | Z76: 2138.3765 | AA76: 2357.9308 | AB76: 2189.0907 | AC76: 2757.5375 | AD76: 2749.0429 | AE76: 2561.5632 | AF76: 2441.5692 | AG76: 2236.5371 | AH76: 2472.1225 | AI76: 2219.7434 | AJ76: 1806.7494 | AK76: 2868.1552 | AL76: 2816.4186 | AM76: 2593.4481 | AN76: 6802.5315 | AO76: 6535.5 | AP76: 10219.1 | AQ76: 10685.543 | AR76: 10841.048 | AS76: 11364.053 | AT76: 10890.939 | AU76: 10419.207 | AV76: 10112.878 | AW76: 14383.367 | AX76: 14091.301 | AY76: 6985.3907 | AZ76: 7313.0258 | BA76: 6767.1146 | BB76: 6697.8943 | BC76: 6309.709 | BD76: 6134.9166 | BE76: 5833.9784 | BF76: 5805.7303 | BG76: 5219.8848 | BH76: 5134.1987 | BI76: 5029.6542 | BJ76: 4921.7962 | BK76: 4768.7379 | BL76: 4224.9058 | BM76: 4041.504 | BN76: 3954.9336 | BO76: 3648.5387 | BP76: 3059.5657 | BQ76: 2537.563 | BR76: 2465.132 | BS76: 2757.4748 | BT76: 2706.2581 | BU76: 2595.1611 | BV76: 2580.7292 | BW76: 2549.7553 | BX76: 2318.2084 | BY76: 2288.4148 | BZ76: 2100.4707 | CA76: 1969.2576 | CB76: 2366.0679 | CC76: 2219.8012 | CD76: 1912.6421 | CE76: 1677.5909 | CF76: 1353.4607 | CG76: 1800.0467 | CH76: 1808.4946 | CI76: 1852.8609 | CJ76: 1850.836 | CK76: 1529.0181 | CL76: 1453.5849 | CM76: 803.79132 | CN76: 766.47299 | CO76: 581.29407 | CP76: 536.65489 | CQ76: 540.14718 | CR76: 526.89777 | CS76: 1014.8799 | CT76: 961.94599 | CU76: 1365.0342 | CV76: 1805.6492 | CW76: 2010.6259 | CX76: 2217.9005 | CY76: 3599.0002 | CZ76: 3669.0844
A77: Other Sectors (inc. bonds held by affilated non-residents) | B77: 74 | X77: 143.46421 | Y77: 146.93801 | Z77: 68.011597 | AA77: 85.279906 | AB77: 252.83344 | AC77: 611.94872 | AD77: 654.37144 | AE77: 662.68246 | AF77: 705.38303 | AG77: 780.85869 | AH77: 687.39309 | AI77: 617.96185 | AJ77: 761.40968 | AK77: 807.93433 | AL77: 806.5873 | AM77: 816.09563 | AN77: 800.86033 | AO77: 814.69774 | AP77: 836.26188 | AQ77: 8234.2549 | AR77: 8712.2572 | AS77: 8774.3464 | AT77: 8800.733 | AU77: 8777.2968 | AV77: 8738.5723 | AW77: 9258.202 | AX77: 9278.1727 | AY77: 9298.2106 | AZ77: 9276.4188 | BA77: 13608.036 | BB77: 12190.248 | BC77: 12271.585 | BD77: 12132.547 | BE77: 14563.55 | BF77: 14443.786 | BG77: 16300.761 | BH77: 14795.157 | BI77: 13795.204 | BJ77: 13749.555 | BK77: 9822.2825 | BL77: 9634.59 | BM77: 9687.6066 | BN77: 9639.8629 | BO77: 9502.0613 | BP77: 9521.5988 | BQ77: 12197.652 | BR77: 12931.744 | BS77: 12682.941 | BT77: 12625.146 | BU77: 12817.633 | BV77: 10892.738 | BW77: 11053.45 | BX77: 10220.301 | BY77: 10004.944 | BZ77: 10412.689 | CA77: 9684.5641 | CB77: 9631.8138 | CC77: 9533.854 | CD77: 9587.5369 | CE77: 9919.7152 | CF77: 9717.7867 | CG77: 9789.9457 | CH77: 9685.6071 | CI77: 10133.115 | CJ77: 9872.6464 | CK77: 9682.981 | CL77: 9702.5667 | CM77: 9473.7982 | CN77: 8855.9176 | CO77: 8683.8674 | CP77: 8694.8631 | CQ77: 8328.2191 | CR77: 8232.0679 | CS77: 8200.7337 | CT77: 7197.4008 | CU77: 7177.0939 | CV77: 8321.7336 | CW77: 9028.5115 | CX77: 8645.7641 | CY77: 9243.1705 | CZ77: 9705.4679
A79: 1Debt securities are recorded at market value (at its existence)
A80: 2Including insurance and pension programs, standardized guarantees as well as other long-term liabilities listed in the structure of IIP

Sheet 2. analytical presentation
A1: External debt: analytical presentation
A2: mln.US dollars
A3: Indicator's name | B3: Row's code | C3: 41730 | D3: 41821 | E3: 41913 | F3: 42005 | G3: 42095 | H3: 42186 | I3: 42278 | J3: 42370 | K3: 42461 | L3: 42552 | M3: 42644 | N3: 42736 | O3: 42826 | P3: 42917 | Q3: 43009 | R3: 43101 | S3: 43191 | T3: 43282 | U3: 43374 | V3: 43466 | W3: 43556 | X3: 43647 | Y3: 43739 | Z3: 43831 | AA3: 43922 | AB3: 44013 | AC3: 44105 | AD3: 44197 | AE3: 44287 | AF3: 44378 | AG3: 44470 | AH3: 44562 | AI3: 44652 | AJ3: 44743 | AK3: 44835 | AL3: 44927 | AM3: 45017 | AN3: 45108 | AO3: 45200 | AP3: 45292 | AQ3: 45383 | AR3: 45474 | AS3: 45566 | AT3: 45658 | AU3: 45748 | AV3: 45839 | AW3: 45931 | AX3: 46023 | AY3: 46113
A4: External Debt (ED) | B4: 1=2=7=14=21 | C4: 151504.68 | D4: 155583.92 | E4: 155674.88 | F4: 157114.53 | G4: 154065.71 | H4: 155281.01 | I4: 155284.28 | J4: 153006.61 | K4: 153335.14 | L4: 159864.39 | M4: 164849.21 | N4: 163528.49 | O4: 165292.7 | P4: 167774.33 | Q4: 168847.75 | R4: 167482.72 | S4: 167755.6 | T4: 165679.6 | U4: 162643.83 | V4: 160331.29 | W4: 160238.82 | X4: 160393.97 | Y4: 160328.62 | Z4: 159544.22 | AA4: 155466.74 | AB4: 160585.79 | AC4: 161706.54 | AD4: 163980.07 | AE4: 163955.09 | AF4: 166483.08 | AG4: 165761.72 | AH4: 164131.07 | AI4: 159896.77 | AJ4: 164152.25 | AK4: 161096.2 | AL4: 161144.27 | AM4: 162813.97 | AN4: 162802.62 | AO4: 163809.5 | AP4: 163711.96 | AQ4: 163952.93 | AR4: 166853.1 | AS4: 166367.06 | AT4: 164677.5 | AU4: 170037.8 | AV4: 172547.08 | AW4: 171558.26 | AX4: 181841.59 | AY4: 182778.24
A5: by remaining maturity: | B5: 2=3+4
A6: Short-term (an original maturity basis) | B6: 3 | C6: 9277.9631 | D6: 9867.1725 | E6: 9291.2238 | F6: 9713.7711 | G6: 8085.0413 | H6: 7796.8116 | I6: 6429.2748 | J6: 6260.3316 | K6: 6238.1279 | L6: 6326.146 | M6: 6733.0899 | N6: 6560.2863 | O6: 7052.3174 | P6: 7193.6603 | Q6: 7407.5321 | R6: 7489.1819 | S6: 8306.197 | T6: 8085.9598 | U6: 8157.0621 | V6: 8150.4561 | W6: 8197.3064 | X6: 8290.6416 | Y6: 8225.3025 | Z6: 8801.1863 | AA6: 8347.7253 | AB6: 8894.1643 | AC6: 9151.283 | AD6: 9481.0146 | AE6: 10955.212 | AF6: 12243.771 | AG6: 11585.003 | AH6: 12009.62 | AI6: 11720.057 | AJ6: 14150.405 | AK6: 15527.76 | AL6: 16335.689 | AM6: 17256.953 | AN6: 17200.649 | AO6: 18225.459 | AP6: 19389.554 | AQ6: 19132.3 | AR6: 20633.718 | AS6: 21269.029 | AT6: 19468.737 | AU6: 21617.707 | AV6: 22418.968 | AW6: 20927.888 | AX6: 21688.322 | AY6: 23576.213
A7: Long-term | B7: 4 | C7: 142226.72 | D7: 145716.75 | E7: 146383.66 | F7: 147400.76 | G7: 145980.66 | H7: 147484.19 | I7: 148855 | J7: 146746.28 | K7: 147097.02 | L7: 153538.25 | M7: 158116.12 | N7: 156968.21 | O7: 158240.38 | P7: 160580.67 | Q7: 161440.22 | R7: 159993.53 | S7: 159449.4 | T7: 157593.64 | U7: 154486.76 | V7: 152180.84 | W7: 152041.51 | X7: 152103.33 | Y7: 152103.32 | Z7: 150743.03 | AA7: 147119.02 | AB7: 151691.63 | AC7: 152555.25 | AD7: 154499.06 | AE7: 152999.88 | AF7: 154239.31 | AG7: 154176.72 | AH7: 152121.45 | AI7: 148176.72 | AJ7: 150001.84 | AK7: 145568.44 | AL7: 144808.58 | AM7: 145557.02 | AN7: 145601.97 | AO7: 145584.04 | AP7: 144322.41 | AQ7: 144820.63 | AR7: 146219.38 | AS7: 145098.04 | AT7: 145208.76 | AU7: 148420.09 | AV7: 150128.12 | AW7: 150630.37 | AX7: 160153.27 | AY7: 159202.03
A8: inc. long-term debt obligations due for payment within one year | B8: 5 | C8: 12776.501 | D8: 12518.268 | E8: 12705.501 | F8: 12939.069 | G8: 11249.487 | H8: 11046.571 | I8: 11745.146 | J8: 11432.146 | K8: 12087.807 | L8: 12493.542 | M8: 12519.18 | N8: 12316.278 | O8: 12269.342 | P8: 13699.521 | Q8: 12947.237 | R8: 13754.751 | S8: 13999.877 | T8: 14513.798 | U8: 12742.285 | V8: 11875.012 | W8: 11819.341 | X8: 11515.146 | Y8: 10932.373 | Z8: 9832.8466 | AA8: 9713.1004 | AB8: 15109.887 | AC8: 10154.847 | AD8: 9868.067 | AE8: 9735.5885 | AF8: 9526.675 | AG8: 13067.792 | AH8: 18108.974 | AI8: 19965.688 | AJ8: 21102.073 | AK8: 17577.241 | AL8: 20619.609 | AM8: 20466.853 | AN8: 19969.502 | AO8: 17220.32 | AP8: 15160.962 | AQ8: 14974.096 | AR8: 16120.865 | AS8: 16484.757 | AT8: 17805.168 | AU8: 21454.855 | AV8: 20863.603 | AW8: 19817.041 | AX8: 21573.263 | AY8: 19450.566
A9: Reference: ED due for payment within one year | B9: 6=3+5 | C9: 22054.464 | D9: 22385.441 | E9: 21996.725 | F9: 22652.84 | G9: 19334.529 | H9: 18843.383 | I9: 18174.421 | J9: 17692.477 | K9: 18325.935 | L9: 18819.688 | M9: 19252.27 | N9: 18876.564 | O9: 19321.659 | P9: 20893.181 | Q9: 20354.769 | R9: 21243.933 | S9: 22306.074 | T9: 22599.758 | U9: 20899.347 | V9: 20025.468 | W9: 20016.648 | X9: 19805.787 | Y9: 19157.676 | Z9: 18634.033 | AA9: 18060.826 | AB9: 24004.052 | AC9: 19306.13 | AD9: 19349.082 | AE9: 20690.8 | AF9: 21770.446 | AG9: 24652.794 | AH9: 30118.594 | AI9: 31685.745 | AJ9: 35252.478 | AK9: 33105.001 | AL9: 36955.298 | AM9: 37723.806 | AN9: 37170.151 | AO9: 35445.779 | AP9: 34550.516 | AQ9: 34106.395 | AR9: 36754.584 | AS9: 37753.786 | AT9: 37273.905 | AU9: 43072.562 | AV9: 43282.57 | AW9: 40744.929 | AX9: 43261.585 | AY9: 43026.779
A10: by resident's sector: | B10: 7=8+9+10+11+12
A11: General Government | B11: 8 | C11: 5066.2462 | D11: 5045.1768 | E11: 5116.6368 | F11: 7333.7497 | G11: 7105.9885 | H11: 7005.6957 | I11: 10319.729 | J11: 11313.193 | K11: 11337.067 | L11: 12696.818 | M11: 12698.964 | N11: 12092.075 | O11: 12170.192 | P11: 12145.184 | Q11: 12313.301 | R11: 12067.476 | S11: 11137.89 | T11: 10690.4 | U11: 10651.472 | V11: 11554.788 | W11: 11488.784 | X11: 11888.719 | Y11: 12793.613 | Z11: 12417.6 | AA11: 11428.362 | AB11: 11834.52 | AC11: 12295.063 | AD11: 13885.041 | AE11: 14471.581 | AF11: 15682.086 | AG11: 15936.662 | AH11: 15859.324 | AI11: 14153.244 | AJ11: 14283.313 | AK11: 12939.095 | AL11: 13389.992 | AM11: 12857.149 | AN11: 12686.181 | AO11: 12610.291 | AP11: 11809.413 | AQ11: 11227.058 | AR11: 10883.271 | AS11: 11660.378 | AT11: 12773.497 | AU11: 12526.665 | AV11: 12475.636 | AW11: 14035.644 | AX11: 15999.525 | AY11: 16541.489
A12: Central Bank | B12: 9 | C12: 870.42072 | D12: 805.71878 | E12: 857.4888 | F12: 953.65208 | G12: 760.26513 | H12: 779.21428 | I12: 875.29489 | J12: 898.82369 | K12: 892.03691 | L12: 893.99357 | M12: 739.38577 | N12: 756.29982 | O12: 1120.3822 | P12: 1097.8499 | Q12: 869.73808 | R12: 926.31534 | S12: 1899.1809 | T12: 1188.5697 | U12: 774.57793 | V12: 770.39637 | W12: 938.78931 | X12: 759.41161 | Y12: 634.03784 | Z12: 891.10116 | AA12: 949.8852 | AB12: 825.9092 | AC12: 805.59551 | AD12: 1329.3693 | AE12: 1835.9915 | AF12: 1714.6907 | AG12: 3051.342 | AH12: 2535.7666 | AI12: 2519.3343 | AJ12: 2214.3143 | AK12: 2043.6277 | AL12: 2171.8023 | AM12: 2217.8953 | AN12: 2065.0931 | AO12: 2097.6294 | AP12: 2233.0697 | AQ12: 2094.1758 | AR12: 2035.9904 | AS12: 2204.0123 | AT12: 2469.9652 | AU12: 2212.7413 | AV12: 2205.8534 | AW12: 2165.8445 | AX12: 2594.4324 | AY12: 2381.7913
A13: Banks | B13: 10 | C13: 10571.265 | D13: 10679.937 | E13: 10556.523 | F13: 10119.481 | G13: 9292.8033 | H13: 9666.474 | I13: 8575.4406 | J13: 7972.7792 | K13: 7697.6335 | L13: 7667.0987 | M13: 7562.138 | N13: 7153.2613 | O13: 6662.2755 | P13: 6168.0824 | Q13: 6289.0029 | R13: 6501.874 | S13: 5933.7993 | T13: 6067.2627 | U13: 5750.1249 | V13: 5752.027 | W13: 5248.5359 | X13: 5112.6818 | Y13: 4590.2035 | Z13: 4818.126 | AA13: 4649.2102 | AB13: 5068.0528 | AC13: 5053.4719 | AD13: 4837.4289 | AE13: 4978.7574 | AF13: 5975.1364 | AG13: 5735.0681 | AH13: 5493.8196 | AI13: 8225.2913 | AJ13: 9675.5996 | AK13: 8006.333 | AL13: 9675.4202 | AM13: 10616.682 | AN13: 10162.586 | AO13: 10631.119 | AP13: 11202.252 | AQ13: 12530.813 | AR13: 14323.072 | AS13: 14724.93 | AT13: 13120.393 | AU13: 14570.022 | AV13: 15634.157 | AW13: 15977.332 | AX13: 18287.41 | AY13: 19152.14
A14: Other Sectors | B14: 11 | C14: 59077.474 | D14: 63052.08 | E14: 58350.072 | F14: 59572.82 | G14: 41918.559 | H14: 41133.124 | I14: 39180.161 | J14: 36558.306 | K14: 36473.819 | L14: 39102.781 | M14: 39528.624 | N14: 38838.814 | O14: 40080.948 | P14: 42163.073 | Q14: 43310.002 | R14: 43614.363 | S14: 43202.996 | T14: 42884.045 | U14: 41306.005 | V14: 39661.679 | W14: 39020.335 | X14: 39661.846 | Y14: 41013.029 | Z14: 41040.547 | AA14: 37404.81 | AB14: 39737.738 | AC14: 40701.02 | AD14: 41388.027 | AE14: 41412.256 | AF14: 42662.134 | AG14: 42908.383 | AH14: 44013.396 | AI14: 40543.965 | AJ14: 43591.511 | AK14: 43752.173 | AL14: 42227.302 | AM14: 43265.504 | AN14: 43768.614 | AO14: 45004.55 | AP14: 45463.463 | AQ14: 45172.156 | AR14: 45898.563 | AS14: 45701.476 | AT14: 45172.717 | AU14: 48210.282 | AV14: 50150.66 | AW14: 50671.649 | AX14: 55062.847 | AY14: 57324.442
A15: Direct investment: Intercompany lending | B15: 12 | C15: 75919.273 | D15: 76001.01 | E15: 80794.159 | F15: 79134.829 | G15: 94988.09 | H15: 96696.497 | I15: 96333.649 | J15: 96263.51 | K15: 96934.586 | L15: 99503.703 | M15: 104320.1 | N15: 104688.04 | O15: 105258.9 | P15: 106200.14 | Q15: 106065.71 | R15: 104372.69 | S15: 105581.73 | T15: 104849.32 | U15: 104161.65 | V15: 102592.4 | W15: 103542.37 | X15: 102971.31 | Y15: 101297.74 | Z15: 100376.84 | AA15: 101034.47 | AB15: 103119.57 | AC15: 102851.39 | AD15: 102540.21 | AE15: 101256.51 | AF15: 100449.03 | AG15: 98130.269 | AH15: 96228.768 | AI15: 94454.938 | AJ15: 94387.507 | AK15: 94354.967 | AL15: 93679.757 | AM15: 93856.738 | AN15: 94120.143 | AO15: 93465.905 | AP15: 93003.766 | AQ15: 92928.724 | AR15: 93712.199 | AS15: 92076.267 | AT15: 91140.924 | AU15: 92518.09 | AV15: 92080.777 | AW15: 88707.794 | AX15: 89897.376 | AY15: 87378.377
A16: Reference: ED not included intercompany lending | B16: 13=8+9+10+11 | C16: 75585.406 | D16: 79582.913 | E16: 74880.72 | F16: 77979.703 | G16: 59077.615 | H16: 58584.508 | I16: 58950.626 | J16: 56743.102 | K16: 56400.557 | L16: 60360.691 | M16: 60529.112 | N16: 58840.45 | O16: 60033.798 | P16: 61574.19 | Q16: 62782.043 | R16: 63110.028 | S16: 62173.867 | T16: 60830.277 | U16: 58482.18 | V16: 57738.891 | W16: 56696.444 | X16: 57422.658 | Y16: 59030.883 | Z16: 59167.374 | AA16: 54432.268 | AB16: 57466.22 | AC16: 58855.15 | AD16: 61439.866 | AE16: 62698.586 | AF16: 66034.048 | AG16: 67631.455 | AH16: 67902.307 | AI16: 65441.835 | AJ16: 69764.739 | AK16: 66741.229 | AL16: 67464.516 | AM16: 68957.23 | AN16: 68682.474 | AO16: 70343.59 | AP16: 70708.198 | AQ16: 71024.203 | AR16: 73140.897 | AS16: 74290.797 | AT16: 73536.573 | AU16: 77519.711 | AV16: 80466.306 | AW16: 82850.469 | AX16: 91944.214 | AY16: 95399.862
A17: by government participation: | B17: 14=15+16+18
A18: Public ED | B18: 15 | C18: 5936.667 | D18: 5850.8956 | E18: 5974.1256 | F18: 8287.4018 | G18: 7866.2536 | H18: 7784.9099 | I18: 11195.024 | J18: 12212.017 | K18: 12229.104 | L18: 13590.812 | M18: 13438.35 | N18: 12848.374 | O18: 13290.575 | P18: 13243.034 | Q18: 13183.039 | R18: 12993.791 | S18: 13037.071 | T18: 11878.969 | U18: 11426.05 | V18: 12325.185 | W18: 12427.573 | X18: 12648.131 | Y18: 13427.651 | Z18: 13308.702 | AA18: 12378.247 | AB18: 12660.429 | AC18: 13100.658 | AD18: 15214.41 | AE18: 16307.573 | AF18: 17396.777 | AG18: 18988.004 | AH18: 18395.091 | AI18: 16672.578 | AJ18: 16497.628 | AK18: 14982.723 | AL18: 15561.794 | AM18: 15075.044 | AN18: 14751.275 | AO18: 14707.92 | AP18: 14042.483 | AQ18: 13321.234 | AR18: 12919.261 | AS18: 13864.39 | AT18: 15243.463 | AU18: 14739.406 | AV18: 14681.489 | AW18: 16201.488 | AX18: 18593.957 | AY18: 18923.28
A19: ED of banks and organizations controlled by government | B19: 16 | C19: 27122.438 | D19: 28824.69 | E19: 28605.58 | F19: 27955.589 | G19: 23356.125 | H19: 23820.885 | I19: 22759.749 | J19: 20256.145 | K19: 20051.696 | L19: 22830.472 | M19: 23141.434 | N19: 17092.591 | O19: 22864.45 | P19: 25117.068 | Q19: 26324.904 | R19: 27326.696 | S19: 27073.457 | T19: 26409.291 | U19: 23984.815 | V19: 22690.591 | W19: 21801.886 | X19: 20946.53 | Y19: 20856.758 | Z19: 19054.583 | AA19: 17016.476 | AB19: 19055.962 | AC19: 19842.227 | AD19: 19922.194 | AE19: 19844.69 | AF19: 20596.795 | AG19: 20812.412 | AH19: 21591.121 | AI19: 18039.915 | AJ19: 18302.148 | AK19: 18272.163 | AL19: 15874.467 | AM19: 15764.467 | AN19: 15389.867 | AO19: 15626.216 | AP19: 15693.367 | AQ19: 15516.173 | AR19: 16788.513 | AS19: 16690.231 | AT19: 16933.541 | AU19: 17402.448 | AV19: 18900.411 | AW19: 20825.354 | AX19: 25220.828 | AY19: 25748.232
A20: inc. government guaranteed ED | B20: 17 | C20: 443.00593 | D20: 432.24157 | E20: 428.178 | F20: 416.327 | G20: 529.974 | H20: 518.607 | I20: 475.718 | J20: 665.695 | K20: 663.301 | L20: 651.808 | M20: 581.369 | N20: 828.339 | O20: 823.512 | P20: 716.032 | Q20: 942.301 | R20: 1314.137 | S20: 1319.72 | T20: 1506.993 | U20: 1548.293 | V20: 1590.173 | W20: 1591.288 | X20: 1745.954 | Y20: 1417.947 | Z20: 1564.101 | AA20: 1537.684 | AB20: 1598.84 | AC20: 1656.123 | AD20: 1636.032 | AE20: 1679.382 | AF20: 1737.289 | AG20: 1897.687 | AH20: 2260.3406 | AI20: 2254.786 | AJ20: 2512.16 | AK20: 2403.851 | AL20: 2365.699 | AM20: 2414.534 | AN20: 2488.337 | AO20: 2444.3745 | AP20: 2772.8296 | AQ20: 2786.0046 | AR20: 2916.5221 | AS20: 2917.3364 | AT20: 2973.9116 | AU20: 3115.2111 | AV20: 3194.2826 | AW20: 3185.6496 | AX20: 3283.5105 | AY20: 3260.2552
A21: Private sector ED | B21: 18 | C21: 118445.57 | D21: 120908.34 | E21: 121095.17 | F21: 120871.54 | G21: 122843.33 | H21: 123675.21 | I21: 121329.5 | J21: 120538.45 | K21: 121054.34 | L21: 123443.11 | M21: 128269.43 | N21: 133587.53 | O21: 129137.68 | P21: 129414.23 | Q21: 129339.81 | R21: 127162.23 | S21: 127645.07 | T21: 127391.34 | U21: 127232.96 | V21: 125315.52 | W21: 126009.36 | X21: 126799.31 | Y21: 126044.22 | Z21: 127180.93 | AA21: 126072.02 | AB21: 128869.4 | AC21: 128763.65 | AD21: 128843.47 | AE21: 127802.83 | AF21: 128489.51 | AG21: 125961.31 | AH21: 124144.86 | AI21: 125184.28 | AJ21: 129352.47 | AK21: 127841.31 | AL21: 129708.01 | AM21: 131974.46 | AN21: 132661.48 | AO21: 133475.36 | AP21: 133976.11 | AQ21: 135115.52 | AR21: 137145.32 | AS21: 135812.44 | AT21: 132500.49 | AU21: 137895.95 | AV21: 138965.18 | AW21: 134531.42 | AX21: 138026.81 | AY21: 138106.73
A22: inc. banks and organizations with 10–50% state ownership | B22: 18a | AL22: 16962.284 | AM22: 16678.652 | AN22: 16678.652 | AO22: 17096.795 | AP22: 16831.121 | AQ22: 16788.187 | AR22: 16756.614 | AS22: 17028.529 | AT22: 15974.174 | AU22: 15282.069 | AV22: 16445.26 | AW22: 16914.447 | AX22: 13966.554 | AY22: 11946.974
A23: Reference: Government and government guaranteed ED | B23: 19=15+17 | C23: 6379.6729 | D23: 6283.1372 | E23: 6402.3036 | F23: 8703.7288 | G23: 8396.2276 | H23: 8303.5169 | I23: 11670.742 | J23: 12877.712 | K23: 12892.405 | L23: 14242.62 | M23: 14019.719 | N23: 13676.713 | O23: 14114.087 | P23: 13959.066 | Q23: 14125.34 | R23: 14307.928 | S23: 14356.791 | T23: 13385.962 | U23: 12974.343 | V23: 13915.358 | W23: 14018.861 | X23: 14394.085 | Y23: 14845.598 | Z23: 14872.803 | AA23: 13915.931 | AB23: 14259.269 | AC23: 14756.781 | AD23: 16850.442 | AE23: 17986.955 | AF23: 19134.066 | AG23: 20885.691 | AH23: 20655.431 | AI23: 18927.364 | AJ23: 19009.788 | AK23: 17386.574 | AL23: 17927.493 | AM23: 17489.578 | AN23: 17239.612 | AO23: 17152.295 | AP23: 16815.313 | AQ23: 16107.239 | AR23: 15835.783 | AS23: 16781.727 | AT23: 18217.374 | AU23: 17854.617 | AV23: 17875.772 | AW23: 19387.138 | AX23: 21877.468 | AY23: 22183.535
A24: Reference: Public sector ED | B24: 20=15+16 | C24: 33059.105 | D24: 34675.585 | E24: 34579.705 | F24: 36242.991 | G24: 31222.379 | H24: 31605.795 | I24: 33954.773 | J24: 32468.162 | K24: 32280.8 | L24: 36421.284 | M24: 36579.784 | N24: 29940.965 | O24: 36155.025 | P24: 38360.102 | Q24: 39507.943 | R24: 40320.486 | S24: 40110.528 | T24: 38288.261 | U24: 35410.865 | V24: 35015.776 | W24: 34229.459 | X24: 33594.661 | Y24: 34284.408 | Z24: 32363.285 | AA24: 29394.723 | AB24: 31716.391 | AC24: 32942.885 | AD24: 35136.605 | AE24: 36152.263 | AF24: 37993.573 | AG24: 39800.416 | AH24: 39986.211 | AI24: 34712.493 | AJ24: 34799.776 | AK24: 33254.886 | AL24: 31436.261 | AM24: 30839.511 | AN24: 30141.141 | AO24: 30334.136 | AP24: 29735.85 | AQ24: 28837.407 | AR24: 29707.774 | AS24: 30554.621 | AT24: 32177.003 | AU24: 32141.854 | AV24: 33581.9 | AW24: 37026.842 | AX24: 43814.785 | AY24: 44671.512
A25: by financial instruments: | B25: 21=22+23+24+25+26+27
A26: special drawing rights | B26: 22 | C26: 536.33317 | D26: 536.43935 | E26: 516.71247 | F26: 503.20584 | G26: 480.65645 | H26: 487.50227 | I26: 488.05516 | J26: 481.83176 | K26: 488.67988 | L26: 484.963 | M26: 485.78832 | N26: 465.57053 | O26: 472.44981 | P26: 483.11851 | Q26: 490.44966 | R26: 493.57301 | S26: 505.04204 | T26: 488.08177 | U26: 487.11193 | V26: 483.1817 | W26: 482.2453 | X26: 482.94815 | Y26: 473.9668 | Z26: 480.42043 | AA26: 476.15593 | AB26: 479.35412 | AC26: 488.91064 | AD26: 500.36989 | AE26: 492.24868 | AF26: 495.69073 | AG26: 2060.4903 | AH26: 2040.1591 | AI26: 2016.4027 | AJ26: 1942.9366 | AK26: 1859.8237 | AL26: 1939.9431 | AM26: 1961.6266 | AN26: 1944.3713 | AO26: 1911.4927 | AP26: 1955.7413 | AQ26: 1929.1447 | AR26: 1916.8634 | AS26: 1975.1633 | AT26: 1901.0133 | AU26: 1932.3849 | AV26: 2001.9541 | AW26: 1996.3665 | AX26: 1998.0854 | AY26: 1979.2404
A27: currency and deposits | B27: 23 | C27: 1884.1145 | D27: 2054.5065 | E27: 1994.4075 | F27: 2247.0731 | G27: 1758.2409 | H27: 1719.5347 | I27: 1116.3196 | J27: 1135.493 | K27: 1113.7305 | L27: 1073.3887 | M27: 858.15874 | N27: 696.62156 | O27: 714.68105 | P27: 706.40781 | Q27: 777.83737 | R27: 719.42561 | S27: 752.00131 | T27: 760.76635 | U27: 786.33907 | V27: 1017.2316 | W27: 940.08632 | X27: 1151.9101 | Y27: 916.19144 | Z27: 1104.8782 | AA27: 965.56394 | AB27: 1176.9531 | AC27: 1343.2642 | AD27: 1396.0269 | AE27: 1638.8865 | AF27: 2155.5813 | AG27: 1769.0414 | AH27: 1846.3405 | AI27: 2018.0035 | AJ27: 2461.5148 | AK27: 4108.9441 | AL27: 5931.946 | AM27: 6586.0294 | AN27: 6857.821 | AO27: 7209.6306 | AP27: 7761.4436 | AQ27: 8457.1526 | AR27: 9143.087 | AS27: 8896.8465 | AT27: 8582.0463 | AU27: 9477.4859 | AV27: 9236.2999 | AW27: 8827.2721 | AX27: 9438.6638 | AY27: 8971.3692
A28: debt securities | B28: 24 | C28: 18190.908 | D28: 21151.167 | E28: 20938.576 | F28: 22504.594 | G28: 20717.141 | H28: 20154.109 | I28: 22571.486 | J28: 18655.671 | K28: 18356.52 | L28: 19136.424 | M28: 19484.955 | N28: 18142.284 | O28: 18624.419 | P28: 20748.087 | Q28: 21694.441 | R28: 21536.412 | S28: 21094.134 | T28: 19620.601 | U28: 17685.623 | V28: 18329.336 | W28: 18253.365 | X28: 18703.492 | Y28: 20239.95 | Z28: 18861.991 | AA28: 16856.386 | AB28: 18356.999 | AC28: 20009.168 | AD28: 21092.301 | AE28: 21227.811 | AF28: 22947.764 | AG28: 23032.227 | AH28: 22804.885 | AI28: 18695.576 | AJ28: 17853.938 | AK28: 16306.711 | AL28: 15199.978 | AM28: 14873.854 | AN28: 14148.445 | AO28: 14595.453 | AP28: 13784.457 | AQ28: 13575.195 | AR28: 13681.876 | AS28: 14016.875 | AT28: 14675.065 | AU28: 15403.767 | AV28: 15809.973 | AW28: 18198.654 | AX28: 22654.136 | AY28: 23755.442
A29: loans | B29: 25 | C29: 118321.63 | D29: 118491.63 | E29: 118853.42 | F29: 118942.03 | G29: 118527.2 | H29: 120724.19 | I29: 119979.67 | J29: 121697.05 | K29: 122167.27 | L29: 128081.74 | M29: 132561.81 | N29: 133570.61 | O29: 134716.2 | P29: 134652.79 | Q29: 133487.41 | R29: 133659.42 | S29: 134173.15 | T29: 132970.53 | U29: 131438.04 | V29: 128701.18 | W29: 128917.41 | X29: 128258.25 | Y29: 126676.95 | Z29: 127703.43 | AA29: 126059.23 | AB29: 128772.37 | AC29: 128287.49 | AD29: 129637.51 | AE29: 128489.77 | AF29: 127950.28 | AG29: 125830.19 | AH29: 123464.38 | AI29: 123614.45 | AJ29: 126332.61 | AK29: 122919.14 | AL29: 122989.24 | AM29: 122896.32 | AN29: 122528.11 | AO29: 122883.85 | AP29: 123244.04 | AQ29: 122056.96 | AR29: 123196.17 | AS29: 123212.9 | AT29: 122349.67 | AU29: 122590.78 | AV29: 124314.85 | AW29: 122555.12 | AX29: 128167.47 | AY29: 126549.05
A30: trade credits and advances | B30: 26 | C30: 11491.275 | D30: 12156.169 | E30: 12205.619 | F30: 11931.824 | G30: 11549.657 | H30: 10998.813 | I30: 10147.059 | J30: 9865.3118 | K30: 9870.286 | L30: 10007.533 | M30: 10152.564 | N30: 9877.2484 | O30: 9732.4584 | P30: 9738.1251 | Q30: 10225.036 | R30: 10150.37 | S30: 10146.201 | T30: 10569.36 | U30: 11111.309 | V30: 10689.887 | W30: 10572.139 | X30: 10647.371 | Y30: 10940.65 | Z30: 10751.443 | AA30: 10178.789 | AB30: 10573.072 | AC30: 10741.926 | AD30: 10553.928 | AE30: 10760.267 | AF30: 11387.497 | AG30: 11777.726 | AH30: 11982.177 | AI30: 11952.888 | AJ30: 13300.96 | AK30: 13887.468 | AL30: 13303.025 | AM30: 14023.608 | AN30: 14744.776 | AO30: 14972.018 | AP30: 14512.244 | AQ30: 14869.847 | AR30: 15700.051 | AS30: 15322.713 | AT30: 14714.627 | AU30: 16102.418 | AV30: 17264.628 | AW30: 17166.476 | AX30: 16489.176 | AY30: 17105.069
A31: other debt liabilities | B31: 27 | C31: 1080.4133 | D31: 1194.0072 | E31: 1166.1469 | F31: 985.8055 | G31: 1032.8103 | H31: 1196.8538 | I31: 981.68369 | J31: 1171.2577 | K31: 1338.6536 | L31: 1080.3442 | M31: 1305.933 | N31: 776.15508 | O31: 1032.4944 | P31: 1445.8029 | Q31: 2172.5745 | R31: 923.51283 | S31: 1085.0701 | T31: 1270.2563 | U31: 1135.4072 | V31: 1110.4774 | W31: 1073.5654 | X31: 1149.9995 | Y31: 1080.9124 | Z31: 642.05858 | AA31: 930.61778 | AB31: 1227.045 | AC31: 835.77379 | AD31: 799.93829 | AE31: 1346.1089 | AF31: 1546.2663 | AG31: 1292.0504 | AH31: 1993.1294 | AI31: 1599.4532 | AJ31: 2260.2864 | AK31: 2014.1132 | AL31: 1780.1424 | AM31: 2472.527 | AN31: 2579.0947 | AO31: 2237.0476 | AP31: 2454.0398 | AQ31: 3064.6286 | AR31: 3215.0494 | AS31: 2942.5685 | AT31: 2455.0765 | AU31: 4530.9647 | AV31: 3919.3796 | AW31: 2814.3741 | AX31: 3094.0588 | AY31: 4418.0658
A32: Reference: Debt securities by nominal value | B32: 28 | C32: 18268.138 | D32: 20398.197 | E32: 20250.191 | F32: 23524.059 | G32: 21956.507 | H32: 20749.525 | I32: 24034.292 | J32: 19839.813 | K32: 18900.327 | L32: 18756.389 | M32: 18383.199 | N32: 17723.986 | O32: 17606.553 | P32: 19691.255 | Q32: 20206.82 | R32: 19962.059 | S32: 20315.941 | T32: 19414.181 | U32: 16994.336 | V32: 18109.862 | W32: 17295.172 | X32: 16996.125 | Y32: 18150.582 | Z32: 17217.272 | AA32: 17528.055 | AB32: 17187.026 | AC32: 17517.97 | AD32: 18351.172 | AE32: 18663.578 | AF32: 19992.381 | AG32: 20083.358 | AH32: 20053.926 | AI32: 19035.542 | AJ32: 18838.874 | AK32: 17982.524 | AL32: 16885.943 | AM32: 16073.877 | AN32: 15456.986 | AO32: 15722.412 | AP32: 14123.067 | AQ32: 13893.083 | AR32: 14026.084 | AS32: 13772.648 | AT32: 14467.137 | AU32: 16000.502 | AV32: 16831.022 | AW32: 18370.995 | AX32: 22732.64 | AY32: 24076.286
A34: *The long-term debt that is due for repayment within one year is estimated based on the external debt service payment schedule as of specific date; therefore, historical data is not subject for revision

Sheet 3. indicators
A1: Absolute and comparative indicators of the external debt
A3: Indicator's name | B3: 1 q 2005 | C3: 2 q 2005 | D3: 3 q 2005 | E3: 4 q 2005 | F3: 2005 | G3: 1 q 2006 | H3: 2 q 2006 | I3: 3 q 2006 | J3: 4 q 2006 | K3: 2006 | L3: 1 q 2007 | M3: 2 q 2007 | N3: 3 q 2007 | O3: 4 q 2007 | P3: 2007 | Q3: 1 q 2008 | R3: 2 q 2008 | S3: 3 q 2008 | T3: 4 q 2008 | U3: 2008 | V3: 1 q 2009 | W3: 2 q 2009 | X3: 3 q 2009 | Y3: 4 q 2009 | Z3: 2009 | AA3: 1 q 2010 | AB3: 2 q 2010 | AC3: 3 q 2010 | AD3: 4 q 2010 | AE3: 2010 | AF3: 1 q 2011 | AG3: 2 q 2011 | AH3: 3 q 2011 | AI3: 4 q 2011 | AJ3: 2011 | AK3: 1 q 2012 | AL3: 2 q 2012 | AM3: 3 q 2012 | AN3: 4 q 2012 | AO3: 2012 | AP3: 1 q 2013 | AQ3: 2 q 2013 | AR3: 3 q 2013 | AS3: 4 q 2013 | AT3: 2013 | AU3: 1 q 2014 | AV3: 2 q 2014 | AW3: 3 q 2014 | AX3: 4 q 2014 | AY3: 2014 | AZ3: 1 q 2015 | BA3: 2 q 2015 | BB3: 3 q 2015 | BC3: 4 q 2015 | BD3: 2015 | BE3: 1 q 2016 | BF3: 2 q 2016 | BG3: 3 q 2016 | BH3: 4 q 2016 | BI3: 2016 | BJ3: 1 q 2017 | BK3: 2 q 2017 | BL3: 3 q 2017 | BM3: 4 q 2017 | BN3: 2017 | BO3: 1 q 2018 | BP3: 2 q 2018 | BQ3: 3 q 2018 | BR3: 4 q 2018 | BS3: 2018 | BT3: 1 q 2019 | BU3: 2 q 2019 | BV3: 3 q 2019 | BW3: 4 q 2019 | BX3: 2019 | BY3: 1 q 2020 | BZ3: 2 q 2020 | CA3: 3 q 2020 | CB3: 4 q 2020 | CC3: 2020 | CD3: 1 q 2021 | CE3: 2 q 2021 | CF3: 3 q 2021 | CG3: 4 q 2021 | CH3: 2021 | CI3: 1 q 2022 | CJ3: 2 q 2022 | CK3: 3 q 2022 | CL3: 4 q 2022 | CM3: 2022 | CN3: 1 q 2023 | CO3: 2 q 2023 | CP3: 3 q 2023 | CQ3: 4 q 2023 | CR3: 2023 | CS3: 1 q 2024 | CT3: 2 q 2024 | CU3: 3 q 2024 | CV3: 4 q 2024 | CW3: 2024 | CX3: 1 q 2025 | CY3: 2 q 2025 | CZ3: 3 q 2025 | DA3: 4 q 2025 | DB3: 2025 | DC3: 1 q 2026
A4: А. Absolute indicators (mln.US dollars)
A5: 1. External debt (estimate at the end of period) | B5: 34256.104 | C5: 35724.692 | D5: 38277.611 | E5: 43428.528 | F5: 43428.528 | G5: 48369.473 | H5: 53969.645 | I5: 60146.599 | J5: 74014.09 | K5: 74014.09 | L5: 81905.913 | M5: 92367.909 | N5: 94248.343 | O5: 96893.004 | P5: 96893.004 | Q5: 98877.328 | R5: 101204.66 | S5: 105995.33 | T5: 107933.38 | U5: 107933.38 | V5: 104803.67 | W5: 106675.74 | X5: 111527.94 | Y5: 112866.89 | Z5: 112866.89 | AA5: 110861.49 | AB5: 113619.66 | AC5: 111518.69 | AD5: 118222.76 | AE5: 118222.76 | AF5: 123359.16 | AG5: 124897.28 | AH5: 123708.36 | AI5: 125320.78 | AJ5: 125320.78 | AK5: 129154.05 | AL5: 132535.86 | AM5: 134414.12 | AN5: 136918.22 | AO5: 136918.22 | AP5: 139691.46 | AQ5: 145554.8 | AR5: 148162.71 | AS5: 150032.87 | AT5: 150032.87 | AU5: 151504.68 | AV5: 155583.92 | AW5: 155674.88 | AX5: 157114.53 | AY5: 157114.53 | AZ5: 154065.71 | BA5: 155281.01 | BB5: 155284.28 | BC5: 153006.61 | BD5: 153006.61 | BE5: 153335.14 | BF5: 159864.39 | BG5: 164849.21 | BH5: 163528.49 | BI5: 163528.49 | BJ5: 165292.7 | BK5: 167774.33 | BL5: 168847.75 | BM5: 167482.72 | BN5: 167482.72 | BO5: 167755.6 | BP5: 165679.6 | BQ5: 162643.83 | BR5: 160331.29 | BS5: 160331.29 | BT5: 160238.82 | BU5: 160393.97 | BV5: 160328.62 | BW5: 159544.22 | BX5: 159544.22 | BY5: 155466.74 | BZ5: 160585.79 | CA5: 161706.54 | CB5: 163980.07 | CC5: 163980.07 | CD5: 163955.09 | CE5: 166483.08 | CF5: 165761.72 | CG5: 164131.07 | CH5: 164131.07 | CI5: 159896.77 | CJ5: 164152.25 | CK5: 161096.2 | CL5: 161144.27 | CM5: 161144.27 | CN5: 162813.97 | CO5: 162802.62 | CP5: 163809.5 | CQ5: 163711.96 | CR5: 163711.96 | CS5: 163952.93 | CT5: 166853.1 | CU5: 166367.06 | CV5: 164677.5 | CW5: 164677.5 | CX5: 170037.8 | CY5: 172547.08 | CZ5: 171558.26 | DA5: 181841.59 | DB5: 181841.59 | DC5: 182778.24
A6: inc. intercompany lending | B6: 17190.766 | C6: 17141.24 | D6: 18181.588 | E6: 19221.957 | F6: 19221.957 | G6: 21081.356 | H6: 22327.755 | I6: 24169.677 | J6: 25513.032 | K6: 25513.032 | L6: 26511.547 | M6: 26746.358 | N6: 28639.176 | O6: 30080.622 | P6: 30080.622 | Q6: 31178.995 | R6: 32845.963 | S6: 38215.517 | T6: 40198.758 | U6: 40198.758 | V6: 41517.286 | W6: 43118.882 | X6: 47309.65 | Y6: 49632.022 | Z6: 49632.022 | AA6: 51168.981 | AB6: 54549.949 | AC6: 56519.019 | AD6: 52274.742 | AE6: 52274.742 | AF6: 56585.923 | AG6: 59296.105 | AH6: 62146.419 | AI6: 62576.197 | AJ6: 62576.197 | AK6: 65277.908 | AL6: 66536.086 | AM6: 67614.35 | AN6: 67608.264 | AO6: 67608.264 | AP6: 70545.576 | AQ6: 72373.955 | AR6: 73557.035 | AS6: 74179.492 | AT6: 74179.492 | AU6: 75919.273 | AV6: 76001.01 | AW6: 80794.159 | AX6: 79134.829 | AY6: 79134.829 | AZ6: 94988.09 | BA6: 96696.497 | BB6: 96333.649 | BC6: 96263.51 | BD6: 96263.51 | BE6: 96934.586 | BF6: 99503.703 | BG6: 104320.1 | BH6: 104688.04 | BI6: 104688.04 | BJ6: 105258.9 | BK6: 106200.14 | BL6: 106065.71 | BM6: 104372.69 | BN6: 104372.69 | BO6: 105581.73 | BP6: 104849.32 | BQ6: 104161.65 | BR6: 102592.4 | BS6: 102592.4 | BT6: 103542.37 | BU6: 102971.31 | BV6: 101297.74 | BW6: 100376.84 | BX6: 100376.84 | BY6: 101034.47 | BZ6: 103119.57 | CA6: 102851.39 | CB6: 102540.21 | CC6: 102540.21 | CD6: 101256.51 | CE6: 100449.03 | CF6: 98130.269 | CG6: 96228.768 | CH6: 96228.768 | CI6: 94454.938 | CJ6: 94387.507 | CK6: 94354.967 | CL6: 93679.757 | CM6: 93679.757 | CN6: 93856.738 | CO6: 94120.143 | CP6: 93465.905 | CQ6: 93003.766 | CR6: 93003.766 | CS6: 92928.724 | CT6: 93712.199 | CU6: 92076.267 | CV6: 91140.924 | CW6: 91140.924 | CX6: 92518.09 | CY6: 92080.777 | CZ6: 88707.794 | DA6: 89897.376 | DB6: 89897.376 | DC6: 87378.377
A7: 2. External debt, excluding intercompany lending (estimate at the end of period) | B7: 17065.337 | C7: 18583.452 | D7: 20096.023 | E7: 24206.571 | F7: 24206.571 | G7: 27288.118 | H7: 31641.89 | I7: 35976.922 | J7: 48501.058 | K7: 48501.058 | L7: 55394.366 | M7: 65621.55 | N7: 65609.167 | O7: 66812.382 | P7: 66812.382 | Q7: 67698.333 | R7: 68358.7 | S7: 67779.813 | T7: 67734.62 | U7: 67734.62 | V7: 63286.387 | W7: 63556.859 | X7: 64218.287 | Y7: 63234.867 | Z7: 63234.867 | AA7: 59692.509 | AB7: 59069.708 | AC7: 54999.674 | AD7: 65948.021 | AE7: 65948.021 | AF7: 66773.236 | AG7: 65601.173 | AH7: 61561.943 | AI7: 62744.581 | AJ7: 62744.581 | AK7: 63876.147 | AL7: 65999.779 | AM7: 66799.765 | AN7: 69309.955 | AO7: 69309.955 | AP7: 69145.886 | AQ7: 73180.846 | AR7: 74605.679 | AS7: 75853.376 | AT7: 75853.376 | AU7: 75585.406 | AV7: 79582.913 | AW7: 74880.72 | AX7: 77979.703 | AY7: 77979.703 | AZ7: 59077.615 | BA7: 58584.508 | BB7: 58950.626 | BC7: 56743.102 | BD7: 56743.102 | BE7: 56400.557 | BF7: 60360.691 | BG7: 60529.112 | BH7: 58840.45 | BI7: 58840.45 | BJ7: 60033.798 | BK7: 61574.19 | BL7: 62782.043 | BM7: 63110.028 | BN7: 63110.028 | BO7: 62173.867 | BP7: 60830.277 | BQ7: 58482.18 | BR7: 57738.891 | BS7: 57738.891 | BT7: 56696.444 | BU7: 57422.658 | BV7: 59030.883 | BW7: 59167.374 | BX7: 59167.374 | BY7: 54432.268 | BZ7: 57466.22 | CA7: 58855.15 | CB7: 61439.866 | CC7: 61439.866 | CD7: 62698.586 | CE7: 66034.048 | CF7: 67631.455 | CG7: 67902.307 | CH7: 67902.307 | CI7: 65441.835 | CJ7: 69764.739 | CK7: 66741.229 | CL7: 67464.516 | CM7: 67464.516 | CN7: 68957.23 | CO7: 68682.474 | CP7: 70343.59 | CQ7: 70708.198 | CR7: 70708.198 | CS7: 71024.203 | CT7: 73140.897 | CU7: 74290.797 | CV7: 73536.573 | CW7: 73536.573 | CX7: 77519.711 | CY7: 80466.306 | CZ7: 82850.469 | DA7: 91944.214 | DB7: 91944.214 | DC7: 95399.862
A8: 3. Long-term external debt service (incl. intercompany lending) | B8: 2000.5964 | C8: 3546.9919 | D8: 2759.6626 | E8: 5403.7217 | F8: 13710.973 | G8: 2488.0028 | H8: 3510.0455 | I8: 4455.2669 | J8: 5837.7391 | K8: 16291.054 | L8: 4582.2354 | M8: 7094.1665 | N8: 7422.1029 | O8: 9410.2593 | P8: 28508.764 | Q8: 8811.9053 | R8: 7777.6121 | S8: 8021.846 | T8: 9065.6727 | U8: 33677.036 | V8: 14614.042 | W8: 8288.8207 | X8: 6670.2364 | Y8: 9187.2904 | Z8: 38760.39 | AA8: 6380.3218 | AB8: 5704.6044 | AC8: 6027.5211 | AD8: 7173.6469 | AE8: 25286.094 | AF8: 6227.2842 | AG8: 7025.9015 | AH8: 7532.0828 | AI8: 8737.9441 | AJ8: 29523.213 | AK8: 5448.7551 | AL8: 7809.8398 | AM8: 6508.3943 | AN8: 12093.102 | AO8: 31860.091 | AP8: 7357.5327 | AQ8: 7623.4134 | AR8: 8397.745 | AS8: 8408.0193 | AT8: 31786.71 | AU8: 6572.2794 | AV8: 6844.0179 | AW8: 7423.8828 | AX8: 10850.531 | AY8: 31690.711 | AZ8: 10260.755 | BA8: 8415.8915 | BB8: 7600.3483 | BC8: 11925.044 | BD8: 38202.039 | BE8: 6529.9782 | BF8: 8392.8709 | BG8: 7608.4974 | BH8: 8841.7106 | BI8: 31373.057 | BJ8: 7215.1348 | BK8: 8198.1071 | BL8: 9159.3353 | BM8: 12527.952 | BN8: 37100.529 | BO8: 10018.038 | BP8: 14322.374 | BQ8: 11672.667 | BR8: 14474.504 | BS8: 50487.583 | BT8: 9024.9718 | BU8: 8775.3574 | BV8: 9704.8697 | BW8: 9505.9825 | BX8: 37011.181 | BY8: 6599.3062 | BZ8: 7694.9109 | CA8: 12566.667 | CB8: 7224.0394 | CC8: 34084.924 | CD8: 6801.6244 | CE8: 8538.4231 | CF8: 7759.5535 | CG8: 8875.0398 | CH8: 31974.641 | CI8: 8131.8772 | CJ8: 10538.339 | CK8: 10947.42 | CL8: 12702.491 | CM8: 42320.126 | CN8: 11059.081 | CO8: 12965.722 | CP8: 11475.082 | CQ8: 13310.841 | CR8: 48810.726 | CS8: 12508.243 | CT8: 12161.498 | CU8: 12522.556 | CV8: 13627.279 | CW8: 50819.577 | CX8: 12215.868 | CY8: 14678.395 | CZ8: 16234 | DA8: 16421.628 | DB8: 59549.891 | DC8: 15514.398
A9: 4. Long-term external debt service (excl. intercompany lending) | B9: 1127.2562 | C9: 1458.4069 | D9: 1580.3947 | E9: 4076.2628 | F9: 8242.3206 | G9: 1449.1516 | H9: 1907.2712 | I9: 2900.9757 | J9: 3989.1742 | K9: 10246.573 | L9: 3002.6216 | M9: 4530.7362 | N9: 5907.8622 | O9: 6868.8128 | P9: 20310.033 | Q9: 6487.3448 | R9: 5069.0764 | S9: 6448.6687 | T9: 6886.307 | U9: 24891.397 | V9: 12991.919 | W9: 6085.2358 | X9: 4983.3088 | Y9: 6759.8863 | Z9: 30820.35 | AA9: 3934.9926 | AB9: 3672.9709 | AC9: 3760.9151 | AD9: 4157.1191 | AE9: 15525.998 | AF9: 4164.0883 | AG9: 4023.6379 | AH9: 3976.3613 | AI9: 4611.5354 | AJ9: 16775.623 | AK9: 3147.7661 | AL9: 4380.0475 | AM9: 4043.1354 | AN9: 7240.0063 | AO9: 18810.955 | AP9: 4696.6889 | AQ9: 4688.0025 | AR9: 5257.4533 | AS9: 4592.586 | AT9: 19234.731 | AU9: 4175.8661 | AV9: 3991.6572 | AW9: 4096.536 | AX9: 5543.5485 | AY9: 17807.608 | AZ9: 6912.1017 | BA9: 5086.9265 | BB9: 4001.5277 | BC9: 8609.8371 | BD9: 24610.393 | BE9: 3090.682 | BF9: 3362.4313 | BG9: 3830.5925 | BH9: 4025.6979 | BI9: 14309.404 | BJ9: 2698.7925 | BK9: 3651.9948 | BL9: 2514.6499 | BM9: 5243.404 | BN9: 14108.841 | BO9: 3881.9512 | BP9: 7775.3318 | BQ9: 5429.6206 | BR9: 7079.4189 | BS9: 24166.323 | BT9: 5336.2207 | BU9: 5534.8925 | BV9: 6074.012 | BW9: 5183.6354 | BX9: 22128.761 | BY9: 2974.0791 | BZ9: 4134.9063 | CA9: 3771.241 | CB9: 3728.4351 | CC9: 14608.661 | CD9: 2594.7005 | CE9: 3314.0022 | CF9: 1924.4349 | CG9: 3887.1698 | CH9: 11720.307 | CI9: 2789.9464 | CJ9: 4320.3492 | CK9: 6276.4919 | CL9: 7522.3532 | CM9: 20909.141 | CN9: 6046.746 | CO9: 8548.6448 | CP9: 7234.1398 | CQ9: 8686.9232 | CR9: 30516.454 | CS9: 8586.2402 | CT9: 7831.1546 | CU9: 7334.5631 | CV9: 8792.6652 | CW9: 32544.623 | CX9: 8160.8807 | CY9: 8908.2807 | CZ9: 8364.4748 | DA9: 10786.238 | DB9: 36219.874 | DC9: 7952.252
A10: Б. Comparative indicators
A11: 1. External debt to GDP ratio (incl. intercompany lending, %) | B11: 76.046499 | C11: 74.507184 | D11: 74.394071 | E11: 76.18961 | F11: 76.025411 | G11: 78.422229 | H11: 79.466259 | I11: 81.321993 | J11: 91.210329 | K11: 91.371472 | L11: 95.357676 | M11: 100.53303 | N11: 96.352931 | O11: 92.253536 | P11: 92.407983 | Q11: 88.805964 | R11: 86.363304 | S11: 82.52471 | T11: 80.86598 | U11: 80.884901 | V11: 81.349793 | W11: 87.37532 | X11: 98.576108 | Y11: 98.293535 | Z11: 97.884578 | AA11: 92.334883 | AB11: 88.952788 | AC11: 82.853837 | AD11: 79.858469 | AE11: 79.851974 | AF11: 78.770358 | AG11: 75.302066 | AH11: 68.82866 | AI11: 65.12983 | AJ11: 65.058578 | AK11: 65.298636 | AL11: 65.566109 | AM11: 65.591811 | AN11: 65.906258 | AO11: 65.825402 | AP11: 65.635927 | AQ11: 67.041548 | AR11: 66.063659 | AS11: 63.515411 | AT11: 63.403108 | AU11: 64.038394 | AV11: 66.619038 | AW11: 67.455446 | AX11: 71.117997 | AY11: 70.958434 | AZ11: 70.322233 | BA11: 71.160049 | BB11: 74.10543 | BC11: 82.850475 | BD11: 82.981237 | BE11: 92.367638 | BF11: 106.56654 | BG11: 121.2395 | BH11: 118.66904 | BI11: 119.12188 | BJ11: 114.74851 | BK11: 112.28047 | BL11: 108.79957 | BM11: 100.83769 | BN11: 100.40551 | BO11: 98.559795 | BP11: 94.930167 | BQ11: 92.670942 | BR11: 90.271133 | BS11: 89.401839 | BT11: 91.023637 | BU11: 91.599072 | BV11: 91.246493 | BW11: 88.000814 | BX11: 87.822876 | BY11: 83.968791 | BZ11: 90.079214 | CA11: 91.137881 | CB11: 96.172503 | CC11: 95.847866 | CD11: 96.59307 | CE11: 94.577733 | CF11: 90.502075 | CG11: 83.126703 | CH11: 83.081109 | CI11: 78.865141 | CJ11: 77.946609 | CK11: 74.802873 | CL11: 71.332948 | CM11: 71.332948 | CN11: 69.440392 | CO11: 67.490479 | CP11: 65.557448 | CQ11: 62.742656 | CR11: 62.742656 | CS11: 61.434853 | CT11: 61.131999 | CU11: 59.62037 | CV11: 57.109851 | CW11: 56.554486 | CX11: 58.57566 | CY11: 59.161756 | CZ11: 58.233412 | DA11: 59.531833 | DB11: 59.442179 | DC11: 58.163597
A12: 2. External debt to GDP ratio (excl. intercompany lending, %) | B12: 37.884027 | C12: 38.757525 | D12: 39.057427 | E12: 42.467228 | F12: 42.375705 | G12: 44.242678 | H12: 46.590312 | I12: 48.643066 | J12: 59.769667 | K12: 59.875263 | L12: 64.492023 | M12: 71.422352 | N12: 67.074235 | O12: 63.613246 | P12: 63.719745 | Q12: 60.802773 | R12: 58.334103 | S12: 52.771282 | T12: 50.748217 | U12: 50.76009 | V12: 49.123607 | W12: 52.057768 | X12: 56.760566 | Y12: 55.069991 | Z12: 54.840869 | AA12: 49.717002 | AB12: 46.245653 | AC12: 40.862513 | AD12: 44.547326 | AE12: 44.543703 | AF12: 42.637708 | AG12: 39.551733 | AH12: 34.251735 | AI12: 32.60867 | AJ12: 32.572996 | AK12: 32.294962 | AL12: 32.650398 | AM12: 32.597154 | AN12: 33.362688 | AO12: 33.321757 | AP12: 32.489132 | AQ12: 33.706598 | AR12: 33.265617 | AS12: 32.11202 | AT12: 32.055241 | AU12: 31.948637 | AV12: 34.076381 | AW12: 32.446547 | AX12: 35.297564 | AY12: 35.218369 | AZ12: 26.965572 | BA12: 26.847305 | BB12: 28.132671 | BC12: 30.725423 | BD12: 30.773917 | BE12: 33.975161 | BF12: 40.23679 | BG12: 44.516557 | BH12: 42.699224 | BI12: 42.862164 | BJ12: 41.676305 | BK12: 41.207611 | BL12: 40.454549 | BM12: 37.99717 | BN12: 37.834319 | BO12: 36.5284 | BP12: 34.85419 | BQ12: 33.321884 | BR12: 32.508658 | BS12: 32.195605 | BT12: 32.206407 | BU12: 32.793391 | BV12: 33.595755 | BW12: 32.635323 | BX12: 32.569334 | BY12: 29.39929 | BZ12: 32.23518 | CA12: 33.170791 | CB12: 36.033803 | CC12: 35.912168 | CD12: 36.938461 | CE12: 37.513425 | CF12: 36.925213 | CG12: 34.390166 | CH12: 34.371303 | CI12: 32.277572 | CJ12: 33.127325 | CK12: 30.990401 | CL12: 29.864188 | CM12: 29.864188 | CN12: 29.410358 | CO12: 28.472596 | CP12: 28.151886 | CQ12: 27.098937 | CR12: 27.098937 | CS12: 26.613502 | CT12: 26.79752 | CU12: 26.623327 | CV12: 25.502347 | CW12: 25.25435 | CX12: 26.704463 | CY12: 27.589733 | CZ12: 28.122606 | DA12: 30.100966 | DB12: 30.055635 | DC12: 30.358095
A13: 3. External debt to EGSy ratio (incl. intercompany lending, %) | B13: 133.92106 | C13: 125.4716 | D13: 126.60457 | E13: 136.64948 | F13: 136.64948 | G13: 143.12127 | H13: 144.70795 | I13: 151.75089 | J13: 173.6789 | K13: 173.6789 | L13: 182.98379 | M13: 199.20018 | N13: 187.728 | O13: 174.96489 | P13: 174.96489 | Q13: 157.8231 | R13: 141.06214 | S13: 139.99536 | T13: 151.39201 | U13: 151.39201 | V13: 168.39795 | W13: 202.7203 | X13: 227.76179 | Y13: 216.99516 | Z13: 216.99516 | AA13: 190.79971 | AB13: 183.32226 | AC13: 174.63784 | AD13: 176.97209 | AE13: 176.97209 | AF13: 161.51483 | AG13: 150.43549 | AH13: 139.60884 | AI13: 134.17566 | AJ13: 134.17566 | AK13: 140.4511 | AL13: 145.30787 | AM13: 146.5317 | AN13: 148.32887 | AO13: 148.32887 | AP13: 153.53607 | AQ13: 160.22921 | AR13: 161.91217 | AS13: 160.17211 | AT13: 160.17211 | AU13: 164.76654 | AV13: 171.4519 | AW13: 179.06558 | AX13: 203.75691 | AY13: 203.75691 | AZ13: 223.14739 | BA13: 255.37106 | BB13: 295.34422 | BC13: 319.93136 | BD13: 319.93136 | BE13: 348.19704 | BF13: 381.49497 | BG13: 395.54909 | BH13: 379.36287 | BI13: 379.36287 | BJ13: 355.36508 | BK13: 342.01905 | BL13: 322.70356 | BM13: 299.21334 | BN13: 299.21334 | BO13: 280.6169 | BP13: 258.87733 | BQ13: 243.24992 | BR13: 241.66212 | BS13: 241.66212 | BT13: 240.94242 | BU13: 244.30404 | BV13: 244.15153 | BW13: 237.07903 | BX13: 237.07903 | BY13: 241.88396 | BZ13: 277.13358 | CA13: 305.36207 | CB13: 332.79668 | CC13: 332.79668 | CD13: 323.41097 | CE13: 284.83077 | CF13: 258.21418 | CG13: 228.83174 | CH13: 228.83174 | CI13: 199.37328 | CJ13: 192.64148 | CK13: 176.7346 | CL13: 171.75586 | CM13: 171.75586 | CN13: 177.3466 | CO13: 178.27064 | CP13: 180.29769 | CQ13: 180.41586 | CR13: 180.41586 | CS13: 180.50633 | CT13: 181.57498 | CU13: 181.8334 | CV13: 182.68031 | CW13: 182.68031 | CX13: 189.49003 | CY13: 194.27814 | CZ13: 191.41437 | DA13: 201.72286 | DB13: 201.72286 | DC13: 200.00156
A14: 4. External debt to EGSy ratio (excl. intercompany lending, %) | B14: 66.715351 | C14: 65.268454 | D14: 66.468316 | E14: 76.166874 | F14: 76.166874 | G14: 80.743281 | H14: 84.840894 | I14: 90.770384 | J14: 113.8109 | K14: 113.8109 | L14: 123.75506 | M14: 141.51912 | N14: 130.68323 | O14: 120.6467 | P14: 120.6467 | Q14: 108.05673 | R14: 95.280434 | S14: 89.521488 | T14: 95.007498 | U14: 95.007498 | V14: 101.68821 | W14: 120.77972 | X14: 131.14626 | Y14: 121.57383 | Z14: 121.57383 | AA14: 102.73462 | AB14: 95.307386 | AC14: 86.129275 | AD14: 98.720065 | AE14: 98.720065 | AF14: 87.426568 | AG14: 79.014891 | AH14: 69.474619 | AI14: 67.177971 | AJ14: 67.177971 | AK14: 69.463362 | AL14: 72.359942 | AM14: 72.821842 | AN14: 75.086189 | AO14: 75.086189 | AP14: 75.99883 | AQ14: 80.558723 | AR14: 81.529064 | AS14: 80.979558 | AT14: 80.979558 | AU14: 82.201722 | AV14: 87.699562 | AW14: 86.131814 | AX14: 101.12943 | AY14: 101.12943 | AZ14: 85.56749 | BA14: 96.346543 | BB14: 112.12164 | BC14: 118.6478 | BD14: 118.6478 | BE14: 128.07571 | BF14: 144.04271 | BG14: 145.23718 | BH14: 136.50148 | BI14: 136.50148 | BJ14: 129.0675 | BK14: 125.52305 | BL14: 119.98969 | BM14: 112.74812 | BN14: 112.74812 | BO14: 104.00272 | BP14: 95.048392 | BQ14: 87.465881 | BR14: 87.027945 | BS14: 87.027945 | BT14: 85.251369 | BU14: 87.463309 | BV14: 89.893372 | BW14: 87.921356 | BX14: 87.921356 | BY14: 84.688806 | BZ14: 99.173277 | CA14: 111.14041 | CB14: 124.69188 | CC14: 124.69188 | CD14: 123.67661 | CE14: 112.97562 | CF14: 105.35243 | CG14: 94.669476 | CH14: 94.669476 | CI14: 81.598604 | CJ14: 81.872669 | CK14: 73.220131 | CL14: 71.907152 | CM14: 71.907152 | CN14: 75.112292 | CO14: 75.208058 | CP14: 77.424002 | CQ14: 77.922711 | CR14: 77.922711 | CS14: 78.195117 | CT14: 79.594308 | CU14: 81.197252 | CV14: 81.575713 | CW14: 81.575713 | CX14: 86.387924 | CY14: 90.600456 | CZ14: 92.439559 | DA14: 101.99674 | DB14: 101.99674 | DC14: 104.38946
A15: 5. Long-term external debt service to EGSp ratio (incl. intercompany lending, %) | B15: 26.631283 | C15: 44.174576 | D15: 34.379357 | E15: 65.80126 | F15: 43.142085 | G15: 26.114235 | H15: 30.445613 | I15: 42.977058 | J15: 52.157256 | K15: 38.228024 | L15: 39.254324 | M15: 54.001419 | N15: 52.261115 | O15: 57.497492 | P15: 51.479803 | Q15: 46.512134 | R15: 34.985423 | S15: 44.147204 | T15: 75.88307 | U15: 47.236863 | V15: 147.80869 | W15: 65.693461 | X15: 45.952609 | Y15: 61.275037 | Z15: 74.519791 | AA15: 39.933974 | AB15: 34.590285 | AC15: 36.765536 | AD15: 39.988074 | AE15: 37.851702 | AF15: 24.372467 | AG15: 30.363409 | AH15: 34.265753 | AI15: 38.443524 | AJ15: 31.609256 | AK15: 22.60279 | AL15: 34.876023 | AM15: 28.924411 | AN15: 51.888144 | AO15: 34.515284 | AP15: 32.295102 | AQ15: 34.259551 | AR15: 36.247407 | AS15: 33.01431 | AT15: 33.934861 | AU15: 31.20217 | AV15: 32.519712 | AW15: 38.345974 | AX15: 69.380077 | AY15: 41.098689 | AZ15: 78.948023 | BA15: 65.699599 | BB15: 68.27709 | BC15: 109.53775 | BD15: 79.879099 | BE15: 70.909325 | BF15: 78.603449 | BG15: 69.783853 | BH15: 71.786111 | BI15: 72.781034 | BJ15: 57.188924 | BK15: 62.021906 | BL15: 64.631056 | BM15: 78.455503 | BN15: 66.281305 | BO15: 61.000162 | BP15: 82.140897 | BQ15: 68.520449 | BR15: 93.682426 | BS15: 76.098285 | BT15: 54.423812 | BU15: 52.912205 | BV15: 56.921562 | BW15: 55.659772 | BX15: 54.997763 | BY15: 48.666577 | BZ15: 75.022942 | CA15: 104.20162 | CB15: 53.92519 | CC15: 69.175169 | CD15: 45.397184 | CE15: 47.406771 | CF15: 43.579361 | CG15: 42.410265 | CH15: 44.579082 | CI15: 34.667876 | CJ15: 45.773994 | CK15: 46.102596 | CL15: 53.83127 | CM15: 45.106968 | CN15: 51.580732 | CO15: 57.522357 | CP15: 49.296878 | CQ15: 56.682166 | CR15: 53.790992 | CS15: 58.101277 | CT15: 51.525268 | CU15: 54.732391 | CV15: 61.566485 | CW15: 56.375257 | CX15: 57.846875 | CY15: 64.710968 | CZ15: 68.521641 | DA15: 72.495655 | DB15: 66.060652 | DC15: 69.379227
